Workbook
Name I18N_KEY: 'M2 · i18n'!$B$4:$B$215
Name I18N_FR: 'M2 · i18n'!$C$4:$C$215
Name I18N_EN: 'M2 · i18n'!$D$4:$D$215
Name MOIS_FR: 'M2 · i18n'!$J$4:$J$15
Name MOIS_EN: 'M2 · i18n'!$K$4:$K$15
Name P_START: 'M0 · Pilotage'!$D$12
Name P_END: 'M0 · Pilotage'!$D$13
Name PP_START: 'M0 · Pilotage'!$D$14
Name PP_END: 'M0 · Pilotage'!$D$15
Name PY_START: 'M0 · Pilotage'!$D$16
Name PY_END: 'M0 · Pilotage'!$D$17
Name LANG: 'M0 · Pilotage'!$D$4
Name GRAIN: 'M0 · Pilotage'!$D$5
Name ANNEE: 'M0 · Pilotage'!$D$6
Name MOIS: 'M0 · Pilotage'!$D$7
Name PERIODE: 'M0 · Pilotage'!$D$8
Name RAG_KEY: 'M1 · Paramètres'!$B$5:$B$126
Name RAG_SENS: 'M1 · Paramètres'!$C$5:$C$126
Name RAG_SV: 'M1 · Paramètres'!$D$5:$D$126
Name RAG_SA: 'M1 · Paramètres'!$E$5:$E$126
Name BUD_MONTHS: 'M1 · Paramètres'!$H$4:$S$4
Name HDR: 'M3 · Base mensuelle'!$D$3:$AM$3

Sheet Rapport Cosmos
C14: =IFERROR(IF(LANG="EN",INDEX(I18N_EN,MATCH("nav.title",I18N_KEY,0)),INDEX(I18N_FR,MATCH("nav.title",I18N_KEY,0))),"nav.title")
C17: =IFERROR(IF(LANG="EN",INDEX(I18N_EN,MATCH("nav.subtitle",I18N_KEY,0)),INDEX(I18N_FR,MATCH("nav.subtitle",I18N_KEY,0))),"nav.subtitle")
C21: =""&IFERROR(IF(LANG="EN",INDEX(I18N_EN,MATCH("nav.period",I18N_KEY,0)),INDEX(I18N_FR,MATCH("nav.period",I18N_KEY,0))),"nav.period")&" : "&IF(LANG="EN",INDEX(MOIS_EN,MONTH(PERIODE)),INDEX(MOIS_FR,MONTH(PERIODE)))&" "&YEAR(PERIODE)
C23: =IFERROR(IF(LANG="EN",INDEX(I18N_EN,MATCH("rag.global",I18N_KEY,0)),INDEX(I18N_FR,MATCH("rag.global",I18N_KEY,0))),"rag.global")
C43: =""&IFERROR(IF(LANG="EN",INDEX(I18N_EN,MATCH("msg.confidential",I18N_KEY,0)),INDEX(I18N_FR,MATCH("msg.confidential",I18N_KEY,0))),"msg.confidential")&" · "&IFERROR(IF(LANG="EN",INDEX(I18N_EN,MATCH("msg.version",I18N_KEY,0)),INDEX(I18N_FR,MATCH("msg.version",I18N_KEY,0))),"msg.version")&" · "&IFERROR(IF(LANG="EN",INDEX(I18N_EN,MATCH("msg.updated",I18N_KEY,0)),INDEX(I18N_FR,MATCH("msg.updated",I18N_KEY,0))),"msg.updated")&": "&TEXT(TODAY(),"yyyy-mm-dd")
C47: =" "&IFERROR(IF(LANG="EN",INDEX(I18N_EN,MATCH("nav.summary",I18N_KEY,0)),INDEX(I18N_FR,MATCH("nav.summary",I18N_KEY,0))),"nav.summary")
C49: ="◈ "&IFERROR(IF(LANG="EN",INDEX(I18N_EN,MATCH("nav.synthesis",I18N_KEY,0)),INDEX(I18N_FR,MATCH("nav.synthesis",I18N_KEY,0))),"nav.synthesis")
C50: ="2. "&IFERROR(IF(LANG="EN",INDEX(I18N_EN,MATCH("dept.rh",I18N_KEY,0)),INDEX(I18N_FR,MATCH("dept.rh",I18N_KEY,0))),"dept.rh") | I50: =IFERROR((INDEX('M3 · Base mensuelle'!$D$4:$AM$4,MATCH(P_END,HDR,0))),"")
C51: ="3. "&IFERROR(IF(LANG="EN",INDEX(I18N_EN,MATCH("dept.lease",I18N_KEY,0)),INDEX(I18N_FR,MATCH("dept.lease",I18N_KEY,0))),"dept.lease") | I51: =IFERROR((AVERAGEIFS('M3 · Base mensuelle'!$D$14:$AM$14,HDR,">="&P_START,HDR,"<="&P_END)),"")
C52: ="4. "&IFERROR(IF(LANG="EN",INDEX(I18N_EN,MATCH("dept.rec",I18N_KEY,0)),INDEX(I18N_FR,MATCH("dept.rec",I18N_KEY,0))),"dept.rec") | I52: =IFERROR((INDEX('M3 · Base mensuelle'!$D$26:$AM$26,MATCH(P_END,HDR,0)))/1000000,"")
C53: ="5. "&IFERROR(IF(LANG="EN",INDEX(I18N_EN,MATCH("dept.foot",I18N_KEY,0)),INDEX(I18N_FR,MATCH("dept.foot",I18N_KEY,0))),"dept.foot") | I53: =IFERROR((SUMIFS('M3 · Base mensuelle'!$D$44:$AM$44,HDR,">="&P_START,HDR,"<="&P_END)),"")
C54: ="6. "&IFERROR(IF(LANG="EN",INDEX(I18N_EN,MATCH("dept.mkt",I18N_KEY,0)),INDEX(I18N_FR,MATCH("dept.mkt",I18N_KEY,0))),"dept.mkt") | I54: =IFERROR((AVERAGEIFS('M3 · Base mensuelle'!$D$64:$AM$64,HDR,">="&P_START,HDR,"<="&P_END)),"")
C55: ="7. "&IFERROR(IF(LANG="EN",INDEX(I18N_EN,MATCH("dept.com",I18N_KEY,0)),INDEX(I18N_FR,MATCH("dept.com",I18N_KEY,0))),"dept.com") | I55: =IFERROR((SUMIFS('M3 · Base mensuelle'!$D$69:$AM$69,HDR,">="&P_START,HDR,"<="&P_END))/1000000,"")
C56: ="8. "&IFERROR(IF(LANG="EN",INDEX(I18N_EN,MATCH("dept.hsse",I18N_KEY,0)),INDEX(I18N_FR,MATCH("dept.hsse",I18N_KEY,0))),"dept.hsse") | I56: =IFERROR((INDEX('M3 · Base mensuelle'!$D$92:$AM$92,MATCH(P_END,HDR,0))),"")
C57: ="9. "&IFERROR(IF(LANG="EN",INDEX(I18N_EN,MATCH("dept.fac",I18N_KEY,0)),INDEX(I18N_FR,MATCH("dept.fac",I18N_KEY,0))),"dept.fac") | I57: =IFERROR((AVERAGEIFS('M3 · Base mensuelle'!$D$125:$AM$125,HDR,">="&P_START,HDR,"<="&P_END)),"")
C58: ="ⓘ "&IFERROR(IF(LANG="EN",INDEX(I18N_EN,MATCH("nav.methodo",I18N_KEY,0)),INDEX(I18N_FR,MATCH("nav.methodo",I18N_KEY,0))),"nav.methodo")
C61: =" 1. "&IFERROR(IF(LANG="EN",INDEX(I18N_EN,MATCH("nav.synthesis",I18N_KEY,0)),INDEX(I18N_FR,MATCH("nav.synthesis",I18N_KEY,0))),"nav.synthesis") | O61: ="↑ "&IFERROR(IF(LANG="EN",INDEX(I18N_EN,MATCH("nav.summary",I18N_KEY,0)),INDEX(I18N_FR,MATCH("nav.summary",I18N_KEY,0))),"nav.summary")
C63: ="▌ "&IFERROR(IF(LANG="EN",INDEX(I18N_EN,MATCH("msg.hero",I18N_KEY,0)),INDEX(I18N_FR,MATCH("msg.hero",I18N_KEY,0))),"msg.hero")
C65: =IFERROR(IF(LANG="EN",INDEX(I18N_EN,MATCH("kpi.com.total_sales",I18N_KEY,0)),INDEX(I18N_FR,MATCH("kpi.com.total_sales",I18N_KEY,0))),"kpi.com.total_sales") | E65: =IFERROR(IF(LANG="EN",INDEX(I18N_EN,MATCH("kpi.lease.occ_gla",I18N_KEY,0)),INDEX(I18N_FR,MATCH("kpi.lease.occ_gla",I18N_KEY,0))),"kpi.lease.occ_gla") | G65: =IFERROR(IF(LANG="EN",INDEX(I18N_EN,MATCH("kpi.foot.total",I18N_KEY,0)),INDEX(I18N_FR,MATCH("kpi.foot.total",I18N_KEY,0))),"kpi.foot.total") | I65: =IFERROR(IF(LANG="EN",INDEX(I18N_EN,MATCH("kpi.rec.recovery",I18N_KEY,0)),INDEX(I18N_FR,MATCH("kpi.rec.recovery",I18N_KEY,0))),"kpi.rec.recovery") | K65: =IFERROR(IF(LANG="EN",INDEX(I18N_EN,MATCH("kpi.lease.passing",I18N_KEY,0)),INDEX(I18N_FR,MATCH("kpi.lease.passing",I18N_KEY,0))),"kpi.lease.passing")
C66: =IFERROR((SUMIFS('M3 · Base mensuelle'!$D$69:$AM$69,HDR,">="&P_START,HDR,"<="&P_END))/1000000,"") | E66: =IFERROR((AVERAGEIFS('M3 · Base mensuelle'!$D$14:$AM$14,HDR,">="&P_START,HDR,"<="&P_END)),"") | G66: =IFERROR((SUMIFS('M3 · Base mensuelle'!$D$44:$AM$44,HDR,">="&P_START,HDR,"<="&P_END)),"") | I66: =IFERROR((AVERAGEIFS('M3 · Base mensuelle'!$D$32:$AM$32,HDR,">="&P_START,HDR,"<="&P_END)),"") | K66: =IFERROR((INDEX('M3 · Base mensuelle'!$D$18:$AM$18,MATCH(P_END,HDR,0)))/1000000,"")
C68: ="▌ "&IFERROR(IF(LANG="EN",INDEX(I18N_EN,MATCH("msg.heatmap",I18N_KEY,0)),INDEX(I18N_FR,MATCH("msg.heatmap",I18N_KEY,0))),"msg.heatmap")
C69: Dépt / Dept | D69: KPI | E69: Achievement
C70: =IFERROR(IF(LANG="EN",INDEX(I18N_EN,MATCH("dept.rh",I18N_KEY,0)),INDEX(I18N_FR,MATCH("dept.rh",I18N_KEY,0))),"dept.rh") | D70: =IFERROR(IF(LANG="EN",INDEX(I18N_EN,MATCH("kpi.rh.payroll_var",I18N_KEY,0)),INDEX(I18N_FR,MATCH("kpi.rh.payroll_var",I18N_KEY,0))),"kpi.rh.payroll_var") | E70: =IFERROR((AVERAGEIFS('M3 · Base mensuelle'!$D$9:$AM$9,HDR,">="&P_START,HDR,"<="&P_END)),"")
C71: =IFERROR(IF(LANG="EN",INDEX(I18N_EN,MATCH("dept.lease",I18N_KEY,0)),INDEX(I18N_FR,MATCH("dept.lease",I18N_KEY,0))),"dept.lease") | D71: =IFERROR(IF(LANG="EN",INDEX(I18N_EN,MATCH("kpi.lease.occ_gla",I18N_KEY,0)),INDEX(I18N_FR,MATCH("kpi.lease.occ_gla",I18N_KEY,0))),"kpi.lease.occ_gla") | E71: =IFERROR((AVERAGEIFS('M3 · Base mensuelle'!$D$14:$AM$14,HDR,">="&P_START,HDR,"<="&P_END)),"")
C72: =IFERROR(IF(LANG="EN",INDEX(I18N_EN,MATCH("dept.rec",I18N_KEY,0)),INDEX(I18N_FR,MATCH("dept.rec",I18N_KEY,0))),"dept.rec") | D72: =IFERROR(IF(LANG="EN",INDEX(I18N_EN,MATCH("kpi.rec.recovery",I18N_KEY,0)),INDEX(I18N_FR,MATCH("kpi.rec.recovery",I18N_KEY,0))),"kpi.rec.recovery") | E72: =IFERROR((AVERAGEIFS('M3 · Base mensuelle'!$D$32:$AM$32,HDR,">="&P_START,HDR,"<="&P_END)),"")
C73: =IFERROR(IF(LANG="EN",INDEX(I18N_EN,MATCH("dept.foot",I18N_KEY,0)),INDEX(I18N_FR,MATCH("dept.foot",I18N_KEY,0))),"dept.foot") | D73: =IFERROR(IF(LANG="EN",INDEX(I18N_EN,MATCH("kpi.foot.vs_budget",I18N_KEY,0)),INDEX(I18N_FR,MATCH("kpi.foot.vs_budget",I18N_KEY,0))),"kpi.foot.vs_budget") | E73: =IFERROR((AVERAGEIFS('M3 · Base mensuelle'!$D$45:$AM$45,HDR,">="&P_START,HDR,"<="&P_END)),"")
C74: =IFERROR(IF(LANG="EN",INDEX(I18N_EN,MATCH("dept.mkt",I18N_KEY,0)),INDEX(I18N_FR,MATCH("dept.mkt",I18N_KEY,0))),"dept.mkt") | D74: =IFERROR(IF(LANG="EN",INDEX(I18N_EN,MATCH("kpi.mkt.event_roi",I18N_KEY,0)),INDEX(I18N_FR,MATCH("kpi.mkt.event_roi",I18N_KEY,0))),"kpi.mkt.event_roi") | E74: =IFERROR((AVERAGEIFS('M3 · Base mensuelle'!$D$53:$AM$53,HDR,">="&P_START,HDR,"<="&P_END)),"")
C75: =IFERROR(IF(LANG="EN",INDEX(I18N_EN,MATCH("dept.com",I18N_KEY,0)),INDEX(I18N_FR,MATCH("dept.com",I18N_KEY,0))),"dept.com") | D75: =IFERROR(IF(LANG="EN",INDEX(I18N_EN,MATCH("kpi.com.lfl",I18N_KEY,0)),INDEX(I18N_FR,MATCH("kpi.com.lfl",I18N_KEY,0))),"kpi.com.lfl") | E75: =IFERROR((AVERAGEIFS('M3 · Base mensuelle'!$D$71:$AM$71,HDR,">="&P_START,HDR,"<="&P_END)),"")
C76: =IFERROR(IF(LANG="EN",INDEX(I18N_EN,MATCH("dept.hsse",I18N_KEY,0)),INDEX(I18N_FR,MATCH("dept.hsse",I18N_KEY,0))),"dept.hsse") | D76: =IFERROR(IF(LANG="EN",INDEX(I18N_EN,MATCH("kpi.hsse.action_close",I18N_KEY,0)),INDEX(I18N_FR,MATCH("kpi.hsse.action_close",I18N_KEY,0))),"kpi.hsse.action_close") | E76: =IFERROR((AVERAGEIFS('M3 · Base mensuelle'!$D$103:$AM$103,HDR,">="&P_START,HDR,"<="&P_END)),"")
C77: =IFERROR(IF(LANG="EN",INDEX(I18N_EN,MATCH("dept.fac",I18N_KEY,0)),INDEX(I18N_FR,MATCH("dept.fac",I18N_KEY,0))),"dept.fac") | D77: =IFERROR(IF(LANG="EN",INDEX(I18N_EN,MATCH("kpi.fac.sla",I18N_KEY,0)),INDEX(I18N_FR,MATCH("kpi.fac.sla",I18N_KEY,0))),"kpi.fac.sla") | E77: =IFERROR((AVERAGEIFS('M3 · Base mensuelle'!$D$125:$AM$125,HDR,">="&P_START,HDR,"<="&P_END)),"")
C80: =" 2. "&IFERROR(IF(LANG="EN",INDEX(I18N_EN,MATCH("dept.rh",I18N_KEY,0)),INDEX(I18N_FR,MATCH("dept.rh",I18N_KEY,0))),"dept.rh")&" · "&IF(LANG="EN",INDEX(MOIS_EN,MONTH(PERIODE)),INDEX(MOIS_FR,MONTH(PERIODE)))&" "&YEAR(PERIODE) | O80: ="↑ "&IFERROR(IF(LANG="EN",INDEX(I18N_EN,MATCH("nav.summary",I18N_KEY,0)),INDEX(I18N_FR,MATCH("nav.summary",I18N_KEY,0))),"nav.summary")
C81: =""&IFERROR(IF(LANG="EN",INDEX(I18N_EN,MATCH("nav.grain",I18N_KEY,0)),INDEX(I18N_FR,MATCH("nav.grain",I18N_KEY,0))),"nav.grain")&": "&IF(GRAIN="M",IFERROR(IF(LANG="EN",INDEX(I18N_EN,MATCH("grain.month",I18N_KEY,0)),INDEX(I18N_FR,MATCH("grain.month",I18N_KEY,0))),"grain.month"),IF(GRAIN="Q",IFERROR(IF(LANG="EN",INDEX(I18N_EN,MATCH("grain.quarter",I18N_KEY,0)),INDEX(I18N_FR,MATCH("grain.quarter",I18N_KEY,0))),"grain.quarter"),IFERROR(IF(LANG="EN",INDEX(I18N_EN,MATCH("grain.year",I18N_KEY,0)),INDEX(I18N_FR,MATCH("grain.year",I18N_KEY,0))),"grain.year")))
C84: =" "&IFERROR(IF(LANG="EN",INDEX(I18N_EN,MATCH("kpi.rh.headcount",I18N_KEY,0)),INDEX(I18N_FR,MATCH("kpi.rh.headcount",I18N_KEY,0))),"kpi.rh.headcount") | I84: =" "&IFERROR(IF(LANG="EN",INDEX(I18N_EN,MATCH("kpi.rh.fte_gap",I18N_KEY,0)),INDEX(I18N_FR,MATCH("kpi.rh.fte_gap",I18N_KEY,0))),"kpi.rh.fte_gap")
C85: =IFERROR((INDEX('M3 · Base mensuelle'!$D$4:$AM$4,MATCH(P_END,HDR,0))),"") | I85: =IFERROR((INDEX('M3 · Base mensuelle'!$D$5:$AM$5,MATCH(P_END,HDR,0))),"")
C86: =IFERROR((IFERROR((INDEX('M3 · Base mensuelle'!$D$4:$AM$4,MATCH(P_END,HDR,0))),""))/(IFERROR((INDEX('M3 · Base mensuelle'!$D$4:$AM$4,MATCH(PP_END,HDR,0))),""))-1,"") | I86: =IFERROR((IFERROR((INDEX('M3 · Base mensuelle'!$D$5:$AM$5,MATCH(P_END,HDR,0))),""))/(IFERROR((INDEX('M3 · Base mensuelle'!$D$5:$AM$5,MATCH(PP_END,HDR,0))),""))-1,"")
C89: =" "&IFERROR(IF(LANG="EN",INDEX(I18N_EN,MATCH("kpi.rh.open_pos",I18N_KEY,0)),INDEX(I18N_FR,MATCH("kpi.rh.open_pos",I18N_KEY,0))),"kpi.rh.open_pos") | I89: =" "&IFERROR(IF(LANG="EN",INDEX(I18N_EN,MATCH("kpi.rh.ttf",I18N_KEY,0)),INDEX(I18N_FR,MATCH("kpi.rh.ttf",I18N_KEY,0))),"kpi.rh.ttf")
C90: =IFERROR((INDEX('M3 · Base mensuelle'!$D$6:$AM$6,MATCH(P_END,HDR,0))),"") | I90: =IFERROR((AVERAGEIFS('M3 · Base mensuelle'!$D$7:$AM$7,HDR,">="&P_START,HDR,"<="&P_END)),"")
C91: =IFERROR((IFERROR((INDEX('M3 · Base mensuelle'!$D$6:$AM$6,MATCH(P_END,HDR,0))),""))/(IFERROR((INDEX('M3 · Base mensuelle'!$D$6:$AM$6,MATCH(PP_END,HDR,0))),""))-1,"") | I91: =IFERROR((IFERROR((AVERAGEIFS('M3 · Base mensuelle'!$D$7:$AM$7,HDR,">="&P_START,HDR,"<="&P_END)),""))/(IFERROR((AVERAGEIFS('M3 · Base mensuelle'!$D$7:$AM$7,HDR,">="&PP_START,HDR,"<="&PP_END)),""))-1,"")
C94: ="▌ "&IFERROR(IF(LANG="EN",INDEX(I18N_EN,MATCH("kpi.rh.headcount",I18N_KEY,0)),INDEX(I18N_FR,MATCH("kpi.rh.headcount",I18N_KEY,0))),"kpi.rh.headcount")&" — 12 mois / 12M"
C106: ="▌ "&IF(LANG="EN","Key gauges","Jauges clés")
C107: =IFERROR(IF(LANG="EN",INDEX(I18N_EN,MATCH("kpi.rh.payroll_var",I18N_KEY,0)),INDEX(I18N_FR,MATCH("kpi.rh.payroll_var",I18N_KEY,0))),"kpi.rh.payroll_var") | G107: =IFERROR(IF(LANG="EN",INDEX(I18N_EN,MATCH("kpi.rh.turnover",I18N_KEY,0)),INDEX(I18N_FR,MATCH("kpi.rh.turnover",I18N_KEY,0))),"kpi.rh.turnover") | K107: =IFERROR(IF(LANG="EN",INDEX(I18N_EN,MATCH("kpi.rh.absence",I18N_KEY,0)),INDEX(I18N_FR,MATCH("kpi.rh.absence",I18N_KEY,0))),"kpi.rh.absence")
C115: =IFERROR((AVERAGEIFS('M3 · Base mensuelle'!$D$9:$AM$9,HDR,">="&P_START,HDR,"<="&P_END)),"") | G115: =IFERROR((AVERAGEIFS('M3 · Base mensuelle'!$D$10:$AM$10,HDR,">="&P_START,HDR,"<="&P_END)),"") | K115: =IFERROR((AVERAGEIFS('M3 · Base mensuelle'!$D$11:$AM$11,HDR,">="&P_START,HDR,"<="&P_END)),"")
C119: ="▸ 2.1 "&IF(LANG="EN","Organizational Chart","Organigramme")
C120: =IF(LANG="EN","Centre Management","Direction du centre")
D121: =IF(LANG="EN","Property / Lease Manager","Property / Lease Manager")
E122: =IF(LANG="EN","Leasing","Gestion locative")
E123: =IF(LANG="EN","Finance & Recovery","Finance & Recouvrement")
E124: =IF(LANG="EN","Marketing","Marketing")
E125: =IF(LANG="EN","Security / HSSE","Sécurité / HSSE")
E126: =IF(LANG="EN","Facility","Facility")
D127: =IF(LANG="EN","Support & Administration","Support & Administration")
C129: ="💬 "&IFERROR(IF(LANG="EN",INDEX(I18N_EN,MATCH("col.comment",I18N_KEY,0)),INDEX(I18N_FR,MATCH("col.comment",I18N_KEY,0))),"col.comment")
C130: =IF(LANG="EN","Org chart — demo.","Organigramme — démo.")
C135: ="▸ 2.2 "&IF(LANG="EN","Human Capital Dashboard","Tableau de bord Capital Humain")
C136: =IFERROR(IF(LANG="EN",INDEX(I18N_EN,MATCH("col.kpi",I18N_KEY,0)),INDEX(I18N_FR,MATCH("col.kpi",I18N_KEY,0))),"col.kpi") | D136: =IFERROR(IF(LANG="EN",INDEX(I18N_EN,MATCH("col.unit",I18N_KEY,0)),INDEX(I18N_FR,MATCH("col.unit",I18N_KEY,0))),"col.unit") | E136: =IFERROR(IF(LANG="EN",INDEX(I18N_EN,MATCH("col.current",I18N_KEY,0)),INDEX(I18N_FR,MATCH("col.current",I18N_KEY,0))),"col.current") | F136: =IFERROR(IF(LANG="EN",INDEX(I18N_EN,MATCH("col.prev",I18N_KEY,0)),INDEX(I18N_FR,MATCH("col.prev",I18N_KEY,0))),"col.prev") | G136: =IFERROR(IF(LANG="EN",INDEX(I18N_EN,MATCH("col.delta_prev",I18N_KEY,0)),INDEX(I18N_FR,MATCH("col.delta_prev",I18N_KEY,0))),"col.delta_prev") | H136: =IFERROR(IF(LANG="EN",INDEX(I18N_EN,MATCH("col.py",I18N_KEY,0)),INDEX(I18N_FR,MATCH("col.py",I18N_KEY,0))),"col.py") | I136: =IFERROR(IF(LANG="EN",INDEX(I18N_EN,MATCH("col.delta_py",I18N_KEY,0)),INDEX(I18N_FR,MATCH("col.delta_py",I18N_KEY,0))),"col.delta_py") | J136: =IFERROR(IF(LANG="EN",INDEX(I18N_EN,MATCH("col.budget",I18N_KEY,0)),INDEX(I18N_FR,MATCH("col.budget",I18N_KEY,0))),"col.budget") | K136: =IFERROR(IF(LANG="EN",INDEX(I18N_EN,MATCH("col.var",I18N_KEY,0)),INDEX(I18N_FR,MATCH("col.var",I18N_KEY,0))),"col.var") | L136: =IFERROR(IF(LANG="EN",INDEX(I18N_EN,MATCH("col.rag",I18N_KEY,0)),INDEX(I18N_FR,MATCH("col.rag",I18N_KEY,0))),"col.rag")
C137: =IFERROR(IF(LANG="EN",INDEX(I18N_EN,MATCH("kpi.rh.headcount",I18N_KEY,0)),INDEX(I18N_FR,MATCH("kpi.rh.headcount",I18N_KEY,0))),"kpi.rh.headcount") | D137: ETP | E137: =IFERROR((INDEX('M3 · Base mensuelle'!$D$4:$AM$4,MATCH(P_END,HDR,0))),"") | F137: =IFERROR((INDEX('M3 · Base mensuelle'!$D$4:$AM$4,MATCH(PP_END,HDR,0))),"") | G137: =IFERROR((E137)/(F137)-1,"") | H137: =IFERROR((INDEX('M3 · Base mensuelle'!$D$4:$AM$4,MATCH(PY_END,HDR,0))),"") | I137: =IFERROR((E137)/(H137)-1,"") | K137: =IFERROR((E137)/(J137)-1,"") | L137: =IF(O137="","",IF(O137="green",IFERROR(IF(LANG="EN",INDEX(I18N_EN,MATCH("rag.green",I18N_KEY,0)),INDEX(I18N_FR,MATCH("rag.green",I18N_KEY,0))),"rag.green"),IF(O137="amber",IFERROR(IF(LANG="EN",INDEX(I18N_EN,MATCH("rag.amber",I18N_KEY,0)),INDEX(I18N_FR,MATCH("rag.amber",I18N_KEY,0))),"rag.amber"),IFERROR(IF(LANG="EN",INDEX(I18N_EN,MATCH("rag.red",I18N_KEY,0)),INDEX(I18N_FR,MATCH("rag.red",I18N_KEY,0))),"rag.red")))) | O137: =IFERROR(IF(IF(N(J137)>0,J137,H137)=0,"",IF(INDEX(RAG_SENS,MATCH("kpi.rh.headcount",RAG_KEY,0))="UP",IF((E137/IF(N(J137)>0,J137,H137))>=INDEX(RAG_SV,MATCH("kpi.rh.headcount",RAG_KEY,0)),"green",IF((E137/IF(N(J137)>0,J137,H137))>=INDEX(RAG_SA,MATCH("kpi.rh.headcount",RAG_KEY,0)),"amber","red")),IF((E137/IF(N(J137)>0,J137,H137))<=INDEX(RAG_SV,MATCH("kpi.rh.headcount",RAG_KEY,0)),"green",IF((E137/IF(N(J137)>0,J137,H137))<=INDEX(RAG_SA,MATCH("kpi.rh.headcount",RAG_KEY,0)),"amber","red")))),"")
C138: =IFERROR(IF(LANG="EN",INDEX(I18N_EN,MATCH("kpi.rh.fte_gap",I18N_KEY,0)),INDEX(I18N_FR,MATCH("kpi.rh.fte_gap",I18N_KEY,0))),"kpi.rh.fte_gap") | D138: ETP | E138: =IFERROR((INDEX('M3 · Base mensuelle'!$D$5:$AM$5,MATCH(P_END,HDR,0))),"") | F138: =IFERROR((INDEX('M3 · Base mensuelle'!$D$5:$AM$5,MATCH(PP_END,HDR,0))),"") | G138: =IFERROR((E138)/(F138)-1,"") | H138: =IFERROR((INDEX('M3 · Base mensuelle'!$D$5:$AM$5,MATCH(PY_END,HDR,0))),"") | I138: =IFERROR((E138)/(H138)-1,"") | J138: =IFERROR((SUMPRODUCT((BUD_MONTHS>=MONTH(P_START))*(BUD_MONTHS<=MONTH(P_END))*'M1 · Paramètres'!$H$6:$S$6)/SUMPRODUCT((BUD_MONTHS>=MONTH(P_START))*(BUD_MONTHS<=MONTH(P_END))*1)),"") | K138: =IFERROR((E138)/(J138)-1,"") | L138: =IF(O138="","",IF(O138="green",IFERROR(IF(LANG="EN",INDEX(I18N_EN,MATCH("rag.green",I18N_KEY,0)),INDEX(I18N_FR,MATCH("rag.green",I18N_KEY,0))),"rag.green"),IF(O138="amber",IFERROR(IF(LANG="EN",INDEX(I18N_EN,MATCH("rag.amber",I18N_KEY,0)),INDEX(I18N_FR,MATCH("rag.amber",I18N_KEY,0))),"rag.amber"),IFERROR(IF(LANG="EN",INDEX(I18N_EN,MATCH("rag.red",I18N_KEY,0)),INDEX(I18N_FR,MATCH("rag.red",I18N_KEY,0))),"rag.red")))) | O138: =IFERROR(IF(IF(N(J138)>0,J138,H138)=0,"",IF(INDEX(RAG_SENS,MATCH("kpi.rh.fte_gap",RAG_KEY,0))="UP",IF((E138/IF(N(J138)>0,J138,H138))>=INDEX(RAG_SV,MATCH("kpi.rh.fte_gap",RAG_KEY,0)),"green",IF((E138/IF(N(J138)>0,J138,H138))>=INDEX(RAG_SA,MATCH("kpi.rh.fte_gap",RAG_KEY,0)),"amber","red")),IF((E138/IF(N(J138)>0,J138,H138))<=INDEX(RAG_SV,MATCH("kpi.rh.fte_gap",RAG_KEY,0)),"green",IF((E138/IF(N(J138)>0,J138,H138))<=INDEX(RAG_SA,MATCH("kpi.rh.fte_gap",RAG_KEY,0)),"amber","red")))),"")
C139: =IFERROR(IF(LANG="EN",INDEX(I18N_EN,MATCH("kpi.rh.open_pos",I18N_KEY,0)),INDEX(I18N_FR,MATCH("kpi.rh.open_pos",I18N_KEY,0))),"kpi.rh.open_pos") | D139: nb | E139: =IFERROR((INDEX('M3 · Base mensuelle'!$D$6:$AM$6,MATCH(P_END,HDR,0))),"") | F139: =IFERROR((INDEX('M3 · Base mensuelle'!$D$6:$AM$6,MATCH(PP_END,HDR,0))),"") | G139: =IFERROR((E139)/(F139)-1,"") | H139: =IFERROR((INDEX('M3 · Base mensuelle'!$D$6:$AM$6,MATCH(PY_END,HDR,0))),"") | I139: =IFERROR((E139)/(H139)-1,"") | K139: =IFERROR((E139)/(J139)-1,"") | L139: =IF(O139="","",IF(O139="green",IFERROR(IF(LANG="EN",INDEX(I18N_EN,MATCH("rag.green",I18N_KEY,0)),INDEX(I18N_FR,MATCH("rag.green",I18N_KEY,0))),"rag.green"),IF(O139="amber",IFERROR(IF(LANG="EN",INDEX(I18N_EN,MATCH("rag.amber",I18N_KEY,0)),INDEX(I18N_FR,MATCH("rag.amber",I18N_KEY,0))),"rag.amber"),IFERROR(IF(LANG="EN",INDEX(I18N_EN,MATCH("rag.red",I18N_KEY,0)),INDEX(I18N_FR,MATCH("rag.red",I18N_KEY,0))),"rag.red")))) | O139: =IFERROR(IF(IF(N(J139)>0,J139,H139)=0,"",IF(INDEX(RAG_SENS,MATCH("kpi.rh.open_pos",RAG_KEY,0))="UP",IF((E139/IF(N(J139)>0,J139,H139))>=INDEX(RAG_SV,MATCH("kpi.rh.open_pos",RAG_KEY,0)),"green",IF((E139/IF(N(J139)>0,J139,H139))>=INDEX(RAG_SA,MATCH("kpi.rh.open_pos",RAG_KEY,0)),"amber","red")),IF((E139/IF(N(J139)>0,J139,H139))<=INDEX(RAG_SV,MATCH("kpi.rh.open_pos",RAG_KEY,0)),"green",IF((E139/IF(N(J139)>0,J139,H139))<=INDEX(RAG_SA,MATCH("kpi.rh.open_pos",RAG_KEY,0)),"amber","red")))),"")
C140: =IFERROR(IF(LANG="EN",INDEX(I18N_EN,MATCH("kpi.rh.ttf",I18N_KEY,0)),INDEX(I18N_FR,MATCH("kpi.rh.ttf",I18N_KEY,0))),"kpi.rh.ttf") | D140: j | E140: =IFERROR((AVERAGEIFS('M3 · Base mensuelle'!$D$7:$AM$7,HDR,">="&P_START,HDR,"<="&P_END)),"") | F140: =IFERROR((AVERAGEIFS('M3 · Base mensuelle'!$D$7:$AM$7,HDR,">="&PP_START,HDR,"<="&PP_END)),"") | G140: =IFERROR((E140)/(F140)-1,"") | H140: =IFERROR((AVERAGEIFS('M3 · Base mensuelle'!$D$7:$AM$7,HDR,">="&PY_START,HDR,"<="&PY_END)),"") | I140: =IFERROR((E140)/(H140)-1,"") | K140: =IFERROR((E140)/(J140)-1,"") | L140: =IF(O140="","",IF(O140="green",IFERROR(IF(LANG="EN",INDEX(I18N_EN,MATCH("rag.green",I18N_KEY,0)),INDEX(I18N_FR,MATCH("rag.green",I18N_KEY,0))),"rag.green"),IF(O140="amber",IFERROR(IF(LANG="EN",INDEX(I18N_EN,MATCH("rag.amber",I18N_KEY,0)),INDEX(I18N_FR,MATCH("rag.amber",I18N_KEY,0))),"rag.amber"),IFERROR(IF(LANG="EN",INDEX(I18N_EN,MATCH("rag.red",I18N_KEY,0)),INDEX(I18N_FR,MATCH("rag.red",I18N_KEY,0))),"rag.red")))) | O140: =IFERROR(IF(IF(N(J140)>0,J140,H140)=0,"",IF(INDEX(RAG_SENS,MATCH("kpi.rh.ttf",RAG_KEY,0))="UP",IF((E140/IF(N(J140)>0,J140,H140))>=INDEX(RAG_SV,MATCH("kpi.rh.ttf",RAG_KEY,0)),"green",IF((E140/IF(N(J140)>0,J140,H140))>=INDEX(RAG_SA,MATCH("kpi.rh.ttf",RAG_KEY,0)),"amber","red")),IF((E140/IF(N(J140)>0,J140,H140))<=INDEX(RAG_SV,MATCH("kpi.rh.ttf",RAG_KEY,0)),"green",IF((E140/IF(N(J140)>0,J140,H140))<=INDEX(RAG_SA,MATCH("kpi.rh.ttf",RAG_KEY,0)),"amber","red")))),"")
C141: =IFERROR(IF(LANG="EN",INDEX(I18N_EN,MATCH("kpi.rh.payroll",I18N_KEY,0)),INDEX(I18N_FR,MATCH("kpi.rh.payroll",I18N_KEY,0))),"kpi.rh.payroll") | D141: FCFA | E141: =IFERROR((SUMIFS('M3 · Base mensuelle'!$D$8:$AM$8,HDR,">="&P_START,HDR,"<="&P_END))/1000000,"") | F141: =IFERROR((SUMIFS('M3 · Base mensuelle'!$D$8:$AM$8,HDR,">="&PP_START,HDR,"<="&PP_END))/1000000,"") | G141: =IFERROR((E141)/(F141)-1,"") | H141: =IFERROR((SUMIFS('M3 · Base mensuelle'!$D$8:$AM$8,HDR,">="&PY_START,HDR,"<="&PY_END))/1000000,"") | I141: =IFERROR((E141)/(H141)-1,"") | J141: =IFERROR((SUMPRODUCT((BUD_MONTHS>=MONTH(P_START))*(BUD_MONTHS<=MONTH(P_END))*'M1 · Paramètres'!$H$9:$S$9))/1000000,"") | K141: =IFERROR((E141)/(J141)-1,"") | L141: =IF(O141="","",IF(O141="green",IFERROR(IF(LANG="EN",INDEX(I18N_EN,MATCH("rag.green",I18N_KEY,0)),INDEX(I18N_FR,MATCH("rag.green",I18N_KEY,0))),"rag.green"),IF(O141="amber",IFERROR(IF(LANG="EN",INDEX(I18N_EN,MATCH("rag.amber",I18N_KEY,0)),INDEX(I18N_FR,MATCH("rag.amber",I18N_KEY,0))),"rag.amber"),IFERROR(IF(LANG="EN",INDEX(I18N_EN,MATCH("rag.red",I18N_KEY,0)),INDEX(I18N_FR,MATCH("rag.red",I18N_KEY,0))),"rag.red")))) | O141: =IFERROR(IF(IF(N(J141)>0,J141,H141)=0,"",IF(INDEX(RAG_SENS,MATCH("kpi.rh.payroll",RAG_KEY,0))="UP",IF((E141/IF(N(J141)>0,J141,H141))>=INDEX(RAG_SV,MATCH("kpi.rh.payroll",RAG_KEY,0)),"green",IF((E141/IF(N(J141)>0,J141,H141))>=INDEX(RAG_SA,MATCH("kpi.rh.payroll",RAG_KEY,0)),"amber","red")),IF((E141/IF(N(J141)>0,J141,H141))<=INDEX(RAG_SV,MATCH("kpi.rh.payroll",RAG_KEY,0)),"green",IF((E141/IF(N(J141)>0,J141,H141))<=INDEX(RAG_SA,MATCH("kpi.rh.payroll",RAG_KEY,0)),"amber","red")))),"")
C142: =IFERROR(IF(LANG="EN",INDEX(I18N_EN,MATCH("kpi.rh.payroll_var",I18N_KEY,0)),INDEX(I18N_FR,MATCH("kpi.rh.payroll_var",I18N_KEY,0))),"kpi.rh.payroll_var") | D142: % | E142: =IFERROR((AVERAGEIFS('M3 · Base mensuelle'!$D$9:$AM$9,HDR,">="&P_START,HDR,"<="&P_END)),"") | F142: =IFERROR((AVERAGEIFS('M3 · Base mensuelle'!$D$9:$AM$9,HDR,">="&PP_START,HDR,"<="&PP_END)),"") | G142: =IFERROR((E142)/(F142)-1,"") | H142: =IFERROR((AVERAGEIFS('M3 · Base mensuelle'!$D$9:$AM$9,HDR,">="&PY_START,HDR,"<="&PY_END)),"") | I142: =IFERROR((E142)/(H142)-1,"") | K142: =IFERROR((E142)/(J142)-1,"") | L142: =IF(O142="","",IF(O142="green",IFERROR(IF(LANG="EN",INDEX(I18N_EN,MATCH("rag.green",I18N_KEY,0)),INDEX(I18N_FR,MATCH("rag.green",I18N_KEY,0))),"rag.green"),IF(O142="amber",IFERROR(IF(LANG="EN",INDEX(I18N_EN,MATCH("rag.amber",I18N_KEY,0)),INDEX(I18N_FR,MATCH("rag.amber",I18N_KEY,0))),"rag.amber"),IFERROR(IF(LANG="EN",INDEX(I18N_EN,MATCH("rag.red",I18N_KEY,0)),INDEX(I18N_FR,MATCH("rag.red",I18N_KEY,0))),"rag.red")))) | O142: =IFERROR(IF(IF(N(J142)>0,J142,H142)=0,"",IF(INDEX(RAG_SENS,MATCH("kpi.rh.payroll_var",RAG_KEY,0))="UP",IF((E142/IF(N(J142)>0,J142,H142))>=INDEX(RAG_SV,MATCH("kpi.rh.payroll_var",RAG_KEY,0)),"green",IF((E142/IF(N(J142)>0,J142,H142))>=INDEX(RAG_SA,MATCH("kpi.rh.payroll_var",RAG_KEY,0)),"amber","red")),IF((E142/IF(N(J142)>0,J142,H142))<=INDEX(RAG_SV,MATCH("kpi.rh.payroll_var",RAG_KEY,0)),"green",IF((E142/IF(N(J142)>0,J142,H142))<=INDEX(RAG_SA,MATCH("kpi.rh.payroll_var",RAG_KEY,0)),"amber","red")))),"")
C143: =IFERROR(IF(LANG="EN",INDEX(I18N_EN,MATCH("kpi.rh.turnover",I18N_KEY,0)),INDEX(I18N_FR,MATCH("kpi.rh.turnover",I18N_KEY,0))),"kpi.rh.turnover") | D143: % | E143: =IFERROR((AVERAGEIFS('M3 · Base mensuelle'!$D$10:$AM$10,HDR,">="&P_START,HDR,"<="&P_END)),"") | F143: =IFERROR((AVERAGEIFS('M3 · Base mensuelle'!$D$10:$AM$10,HDR,">="&PP_START,HDR,"<="&PP_END)),"") | G143: =IFERROR((E143)/(F143)-1,"") | H143: =IFERROR((AVERAGEIFS('M3 · Base mensuelle'!$D$10:$AM$10,HDR,">="&PY_START,HDR,"<="&PY_END)),"") | I143: =IFERROR((E143)/(H143)-1,"") | K143: =IFERROR((E143)/(J143)-1,"") | L143: =IF(O143="","",IF(O143="green",IFERROR(IF(LANG="EN",INDEX(I18N_EN,MATCH("rag.green",I18N_KEY,0)),INDEX(I18N_FR,MATCH("rag.green",I18N_KEY,0))),"rag.green"),IF(O143="amber",IFERROR(IF(LANG="EN",INDEX(I18N_EN,MATCH("rag.amber",I18N_KEY,0)),INDEX(I18N_FR,MATCH("rag.amber",I18N_KEY,0))),"rag.amber"),IFERROR(IF(LANG="EN",INDEX(I18N_EN,MATCH("rag.red",I18N_KEY,0)),INDEX(I18N_FR,MATCH("rag.red",I18N_KEY,0))),"rag.red")))) | O143: =IFERROR(IF(IF(N(J143)>0,J143,H143)=0,"",IF(INDEX(RAG_SENS,MATCH("kpi.rh.turnover",RAG_KEY,0))="UP",IF((E143/IF(N(J143)>0,J143,H143))>=INDEX(RAG_SV,MATCH("kpi.rh.turnover",RAG_KEY,0)),"green",IF((E143/IF(N(J143)>0,J143,H143))>=INDEX(RAG_SA,MATCH("kpi.rh.turnover",RAG_KEY,0)),"amber","red")),IF((E143/IF(N(J143)>0,J143,H143))<=INDEX(RAG_SV,MATCH("kpi.rh.turnover",RAG_KEY,0)),"green",IF((E143/IF(N(J143)>0,J143,H143))<=INDEX(RAG_SA,MATCH("kpi.rh.turnover",RAG_KEY,0)),"amber","red")))),"")
C144: =IFERROR(IF(LANG="EN",INDEX(I18N_EN,MATCH("kpi.rh.absence",I18N_KEY,0)),INDEX(I18N_FR,MATCH("kpi.rh.absence",I18N_KEY,0))),"kpi.rh.absence") | D144: % | E144: =IFERROR((AVERAGEIFS('M3 · Base mensuelle'!$D$11:$AM$11,HDR,">="&P_START,HDR,"<="&P_END)),"") | F144: =IFERROR((AVERAGEIFS('M3 · Base mensuelle'!$D$11:$AM$11,HDR,">="&PP_START,HDR,"<="&PP_END)),"") | G144: =IFERROR((E144)/(F144)-1,"") | H144: =IFERROR((AVERAGEIFS('M3 · Base mensuelle'!$D$11:$AM$11,HDR,">="&PY_START,HDR,"<="&PY_END)),"") | I144: =IFERROR((E144)/(H144)-1,"") | K144: =IFERROR((E144)/(J144)-1,"") | L144: =IF(O144="","",IF(O144="green",IFERROR(IF(LANG="EN",INDEX(I18N_EN,MATCH("rag.green",I18N_KEY,0)),INDEX(I18N_FR,MATCH("rag.green",I18N_KEY,0))),"rag.green"),IF(O144="amber",IFERROR(IF(LANG="EN",INDEX(I18N_EN,MATCH("rag.amber",I18N_KEY,0)),INDEX(I18N_FR,MATCH("rag.amber",I18N_KEY,0))),"rag.amber"),IFERROR(IF(LANG="EN",INDEX(I18N_EN,MATCH("rag.red",I18N_KEY,0)),INDEX(I18N_FR,MATCH("rag.red",I18N_KEY,0))),"rag.red")))) | O144: =IFERROR(IF(IF(N(J144)>0,J144,H144)=0,"",IF(INDEX(RAG_SENS,MATCH("kpi.rh.absence",RAG_KEY,0))="UP",IF((E144/IF(N(J144)>0,J144,H144))>=INDEX(RAG_SV,MATCH("kpi.rh.absence",RAG_KEY,0)),"green",IF((E144/IF(N(J144)>0,J144,H144))>=INDEX(RAG_SA,MATCH("kpi.rh.absence",RAG_KEY,0)),"amber","red")),IF((E144/IF(N(J144)>0,J144,H144))<=INDEX(RAG_SV,MATCH("kpi.rh.absence",RAG_KEY,0)),"green",IF((E144/IF(N(J144)>0,J144,H144))<=INDEX(RAG_SA,MATCH("kpi.rh.absence",RAG_KEY,0)),"amber","red")))),"")
C145: =IFERROR(IF(LANG="EN",INDEX(I18N_EN,MATCH("kpi.rh.train_hours",I18N_KEY,0)),INDEX(I18N_FR,MATCH("kpi.rh.train_hours",I18N_KEY,0))),"kpi.rh.train_hours") | D145: h | E145: =IFERROR((AVERAGEIFS('M3 · Base mensuelle'!$D$12:$AM$12,HDR,">="&P_START,HDR,"<="&P_END)),"") | F145: =IFERROR((AVERAGEIFS('M3 · Base mensuelle'!$D$12:$AM$12,HDR,">="&PP_START,HDR,"<="&PP_END)),"") | G145: =IFERROR((E145)/(F145)-1,"") | H145: =IFERROR((AVERAGEIFS('M3 · Base mensuelle'!$D$12:$AM$12,HDR,">="&PY_START,HDR,"<="&PY_END)),"") | I145: =IFERROR((E145)/(H145)-1,"") | K145: =IFERROR((E145)/(J145)-1,"") | L145: =IF(O145="","",IF(O145="green",IFERROR(IF(LANG="EN",INDEX(I18N_EN,MATCH("rag.green",I18N_KEY,0)),INDEX(I18N_FR,MATCH("rag.green",I18N_KEY,0))),"rag.green"),IF(O145="amber",IFERROR(IF(LANG="EN",INDEX(I18N_EN,MATCH("rag.amber",I18N_KEY,0)),INDEX(I18N_FR,MATCH("rag.amber",I18N_KEY,0))),"rag.amber"),IFERROR(IF(LANG="EN",INDEX(I18N_EN,MATCH("rag.red",I18N_KEY,0)),INDEX(I18N_FR,MATCH("rag.red",I18N_KEY,0))),"rag.red")))) | O145: =IFERROR(IF(IF(N(J145)>0,J145,H145)=0,"",IF(INDEX(RAG_SENS,MATCH("kpi.rh.train_hours",RAG_KEY,0))="UP",IF((E145/IF(N(J145)>0,J145,H145))>=INDEX(RAG_SV,MATCH("kpi.rh.train_hours",RAG_KEY,0)),"green",IF((E145/IF(N(J145)>0,J145,H145))>=INDEX(RAG_SA,MATCH("kpi.rh.train_hours",RAG_KEY,0)),"amber","red")),IF((E145/IF(N(J145)>0,J145,H145))<=INDEX(RAG_SV,MATCH("kpi.rh.train_hours",RAG_KEY,0)),"green",IF((E145/IF(N(J145)>0,J145,H145))<=INDEX(RAG_SA,MATCH("kpi.rh.train_hours",RAG_KEY,0)),"amber","red")))),"")
C146: =IFERROR(IF(LANG="EN",INDEX(I18N_EN,MATCH("kpi.rh.train_cover",I18N_KEY,0)),INDEX(I18N_FR,MATCH("kpi.rh.train_cover",I18N_KEY,0))),"kpi.rh.train_cover") | D146: % | E146: =IFERROR((AVERAGEIFS('M3 · Base mensuelle'!$D$13:$AM$13,HDR,">="&P_START,HDR,"<="&P_END)),"") | F146: =IFERROR((AVERAGEIFS('M3 · Base mensuelle'!$D$13:$AM$13,HDR,">="&PP_START,HDR,"<="&PP_END)),"") | G146: =IFERROR((E146)/(F146)-1,"") | H146: =IFERROR((AVERAGEIFS('M3 · Base mensuelle'!$D$13:$AM$13,HDR,">="&PY_START,HDR,"<="&PY_END)),"") | I146: =IFERROR((E146)/(H146)-1,"") | K146: =IFERROR((E146)/(J146)-1,"") | L146: =IF(O146="","",IF(O146="green",IFERROR(IF(LANG="EN",INDEX(I18N_EN,MATCH("rag.green",I18N_KEY,0)),INDEX(I18N_FR,MATCH("rag.green",I18N_KEY,0))),"rag.green"),IF(O146="amber",IFERROR(IF(LANG="EN",INDEX(I18N_EN,MATCH("rag.amber",I18N_KEY,0)),INDEX(I18N_FR,MATCH("rag.amber",I18N_KEY,0))),"rag.amber"),IFERROR(IF(LANG="EN",INDEX(I18N_EN,MATCH("rag.red",I18N_KEY,0)),INDEX(I18N_FR,MATCH("rag.red",I18N_KEY,0))),"rag.red")))) | O146: =IFERROR(IF(IF(N(J146)>0,J146,H146)=0,"",IF(INDEX(RAG_SENS,MATCH("kpi.rh.train_cover",RAG_KEY,0))="UP",IF((E146/IF(N(J146)>0,J146,H146))>=INDEX(RAG_SV,MATCH("kpi.rh.train_cover",RAG_KEY,0)),"green",IF((E146/IF(N(J146)>0,J146,H146))>=INDEX(RAG_SA,MATCH("kpi.rh.train_cover",RAG_KEY,0)),"amber","red")),IF((E146/IF(N(J146)>0,J146,H146))<=INDEX(RAG_SV,MATCH("kpi.rh.train_cover",RAG_KEY,0)),"green",IF((E146/IF(N(J146)>0,J146,H146))<=INDEX(RAG_SA,MATCH("kpi.rh.train_cover",RAG_KEY,0)),"amber","red")))),"")
C147: ="◆ "&IFERROR(IF(LANG="EN",INDEX(I18N_EN,MATCH("msg.highlights",I18N_KEY,0)),INDEX(I18N_FR,MATCH("msg.highlights",I18N_KEY,0))),"msg.highlights")
C148: =IFERROR("▲ "&INDEX(C137:C146,MATCH(MAX(G137:G146),G137:G146,0))&" "&TEXT(MAX(G137:G146),"+0.0%;-0.0%"),"") | I148: =IFERROR("▼ "&INDEX(C137:C146,MATCH(MIN(G137:G146),G137:G146,0))&" "&TEXT(MIN(G137:G146),"+0.0%;-0.0%"),"")
C149: ="💬 "&IFERROR(IF(LANG="EN",INDEX(I18N_EN,MATCH("col.comment",I18N_KEY,0)),INDEX(I18N_FR,MATCH("col.comment",I18N_KEY,0))),"col.comment")
C150: =IF('C1 · Capital Humain'!$D$20<>"",'C1 · Capital Humain'!$D$20,IFERROR(SUBSTITUTE(SUBSTITUTE(IF(G137>=0,IFERROR(IF(LANG="EN",INDEX(I18N_EN,MATCH("narr.up",I18N_KEY,0)),INDEX(I18N_FR,MATCH("narr.up",I18N_KEY,0))),"narr.up"),IFERROR(IF(LANG="EN",INDEX(I18N_EN,MATCH("narr.down",I18N_KEY,0)),INDEX(I18N_FR,MATCH("narr.down",I18N_KEY,0))),"narr.down")),"{kpi}",IFERROR(IF(LANG="EN",INDEX(I18N_EN,MATCH("kpi.rh.headcount",I18N_KEY,0)),INDEX(I18N_FR,MATCH("kpi.rh.headcount",I18N_KEY,0))),"kpi.rh.headcount")),"{delta}",TEXT(ABS(G137),"0.0%")),""))
C155: ="🎯 2.3 "&IF(LANG="EN","Budget vs Actual","Budget vs Réalisé")
C156: ="▌ "&IF(LANG="EN","Actual vs Budget — 12 months","Réalisé vs Budget — 12 mois")
C169: =IFERROR(IF(LANG="EN",INDEX(I18N_EN,MATCH("col.kpi",I18N_KEY,0)),INDEX(I18N_FR,MATCH("col.kpi",I18N_KEY,0))),"col.kpi") | D169: =IFERROR(IF(LANG="EN",INDEX(I18N_EN,MATCH("col.unit",I18N_KEY,0)),INDEX(I18N_FR,MATCH("col.unit",I18N_KEY,0))),"col.unit") | E169: =IFERROR(IF(LANG="EN",INDEX(I18N_EN,MATCH("col.current",I18N_KEY,0)),INDEX(I18N_FR,MATCH("col.current",I18N_KEY,0))),"col.current") | F169: =IFERROR(IF(LANG="EN",INDEX(I18N_EN,MATCH("col.budget",I18N_KEY,0)),INDEX(I18N_FR,MATCH("col.budget",I18N_KEY,0))),"col.budget") | G169: =IFERROR(IF(LANG="EN",INDEX(I18N_EN,MATCH("col.var",I18N_KEY,0)),INDEX(I18N_FR,MATCH("col.var",I18N_KEY,0))),"col.var") | H169: =IFERROR(IF(LANG="EN",INDEX(I18N_EN,MATCH("col.rag",I18N_KEY,0)),INDEX(I18N_FR,MATCH("col.rag",I18N_KEY,0))),"col.rag")
C170: =IFERROR(IF(LANG="EN",INDEX(I18N_EN,MATCH("kpi.rh.fte_gap",I18N_KEY,0)),INDEX(I18N_FR,MATCH("kpi.rh.fte_gap",I18N_KEY,0))),"kpi.rh.fte_gap") | D170: ETP | E170: =IFERROR((INDEX('M3 · Base mensuelle'!$D$5:$AM$5,MATCH(P_END,HDR,0))),"") | F170: =IFERROR((SUMPRODUCT((BUD_MONTHS>=MONTH(P_START))*(BUD_MONTHS<=MONTH(P_END))*'M1 · Paramètres'!$H$6:$S$6)/SUMPRODUCT((BUD_MONTHS>=MONTH(P_START))*(BUD_MONTHS<=MONTH(P_END))*1)),"") | G170: =IFERROR((E170)/(F170)-1,"") | H170: =IF(P170="","",IF(P170="green",IFERROR(IF(LANG="EN",INDEX(I18N_EN,MATCH("rag.green",I18N_KEY,0)),INDEX(I18N_FR,MATCH("rag.green",I18N_KEY,0))),"rag.green"),IF(P170="amber",IFERROR(IF(LANG="EN",INDEX(I18N_EN,MATCH("rag.amber",I18N_KEY,0)),INDEX(I18N_FR,MATCH("rag.amber",I18N_KEY,0))),"rag.amber"),IFERROR(IF(LANG="EN",INDEX(I18N_EN,MATCH("rag.red",I18N_KEY,0)),INDEX(I18N_FR,MATCH("rag.red",I18N_KEY,0))),"rag.red")))) | P170: =IFERROR(IF(F170=0,"",IF(INDEX(RAG_SENS,MATCH("kpi.rh.fte_gap",RAG_KEY,0))="UP",IF((E170/F170)>=INDEX(RAG_SV,MATCH("kpi.rh.fte_gap",RAG_KEY,0)),"green",IF((E170/F170)>=INDEX(RAG_SA,MATCH("kpi.rh.fte_gap",RAG_KEY,0)),"amber","red")),IF((E170/F170)<=INDEX(RAG_SV,MATCH("kpi.rh.fte_gap",RAG_KEY,0)),"green",IF((E170/F170)<=INDEX(RAG_SA,MATCH("kpi.rh.fte_gap",RAG_KEY,0)),"amber","red")))),"")
C171: =IFERROR(IF(LANG="EN",INDEX(I18N_EN,MATCH("kpi.rh.payroll",I18N_KEY,0)),INDEX(I18N_FR,MATCH("kpi.rh.payroll",I18N_KEY,0))),"kpi.rh.payroll") | D171: FCFA | E171: =IFERROR((SUMIFS('M3 · Base mensuelle'!$D$8:$AM$8,HDR,">="&P_START,HDR,"<="&P_END))/1000000,"") | F171: =IFERROR((SUMPRODUCT((BUD_MONTHS>=MONTH(P_START))*(BUD_MONTHS<=MONTH(P_END))*'M1 · Paramètres'!$H$9:$S$9))/1000000,"") | G171: =IFERROR((E171)/(F171)-1,"") | H171: =IF(P171="","",IF(P171="green",IFERROR(IF(LANG="EN",INDEX(I18N_EN,MATCH("rag.green",I18N_KEY,0)),INDEX(I18N_FR,MATCH("rag.green",I18N_KEY,0))),"rag.green"),IF(P171="amber",IFERROR(IF(LANG="EN",INDEX(I18N_EN,MATCH("rag.amber",I18N_KEY,0)),INDEX(I18N_FR,MATCH("rag.amber",I18N_KEY,0))),"rag.amber"),IFERROR(IF(LANG="EN",INDEX(I18N_EN,MATCH("rag.red",I18N_KEY,0)),INDEX(I18N_FR,MATCH("rag.red",I18N_KEY,0))),"rag.red")))) | P171: =IFERROR(IF(F171=0,"",IF(INDEX(RAG_SENS,MATCH("kpi.rh.payroll",RAG_KEY,0))="UP",IF((E171/F171)>=INDEX(RAG_SV,MATCH("kpi.rh.payroll",RAG_KEY,0)),"green",IF((E171/F171)>=INDEX(RAG_SA,MATCH("kpi.rh.payroll",RAG_KEY,0)),"amber","red")),IF((E171/F171)<=INDEX(RAG_SV,MATCH("kpi.rh.payroll",RAG_KEY,0)),"green",IF((E171/F171)<=INDEX(RAG_SA,MATCH("kpi.rh.payroll",RAG_KEY,0)),"amber","red")))),"")
C172: ="💬 "&IFERROR(IF(LANG="EN",INDEX(I18N_EN,MATCH("col.comment",I18N_KEY,0)),INDEX(I18N_FR,MATCH("col.comment",I18N_KEY,0))),"col.comment")
C173: =IF(LANG="EN","Budget variance commentary.","Commentaire écart budgétaire.")
C180: =" 3. "&IFERROR(IF(LANG="EN",INDEX(I18N_EN,MATCH("dept.lease",I18N_KEY,0)),INDEX(I18N_FR,MATCH("dept.lease",I18N_KEY,0))),"dept.lease")&" · "&IF(LANG="EN",INDEX(MOIS_EN,MONTH(PERIODE)),INDEX(MOIS_FR,MONTH(PERIODE)))&" "&YEAR(PERIODE) | O180: ="↑ "&IFERROR(IF(LANG="EN",INDEX(I18N_EN,MATCH("nav.summary",I18N_KEY,0)),INDEX(I18N_FR,MATCH("nav.summary",I18N_KEY,0))),"nav.summary")
C181: =""&IFERROR(IF(LANG="EN",INDEX(I18N_EN,MATCH("nav.grain",I18N_KEY,0)),INDEX(I18N_FR,MATCH("nav.grain",I18N_KEY,0))),"nav.grain")&": "&IF(GRAIN="M",IFERROR(IF(LANG="EN",INDEX(I18N_EN,MATCH("grain.month",I18N_KEY,0)),INDEX(I18N_FR,MATCH("grain.month",I18N_KEY,0))),"grain.month"),IF(GRAIN="Q",IFERROR(IF(LANG="EN",INDEX(I18N_EN,MATCH("grain.quarter",I18N_KEY,0)),INDEX(I18N_FR,MATCH("grain.quarter",I18N_KEY,0))),"grain.quarter"),IFERROR(IF(LANG="EN",INDEX(I18N_EN,MATCH("grain.year",I18N_KEY,0)),INDEX(I18N_FR,MATCH("grain.year",I18N_KEY,0))),"grain.year")))
C184: =" "&IFERROR(IF(LANG="EN",INDEX(I18N_EN,MATCH("kpi.lease.occ_gla",I18N_KEY,0)),INDEX(I18N_FR,MATCH("kpi.lease.occ_gla",I18N_KEY,0))),"kpi.lease.occ_gla") | I184: =" "&IFERROR(IF(LANG="EN",INDEX(I18N_EN,MATCH("kpi.lease.occ_unit",I18N_KEY,0)),INDEX(I18N_FR,MATCH("kpi.lease.occ_unit",I18N_KEY,0))),"kpi.lease.occ_unit")
C185: =IFERROR((AVERAGEIFS('M3 · Base mensuelle'!$D$14:$AM$14,HDR,">="&P_START,HDR,"<="&P_END)),"") | I185: =IFERROR((AVERAGEIFS('M3 · Base mensuelle'!$D$15:$AM$15,HDR,">="&P_START,HDR,"<="&P_END)),"")
C186: =IFERROR((IFERROR((AVERAGEIFS('M3 · Base mensuelle'!$D$14:$AM$14,HDR,">="&P_START,HDR,"<="&P_END)),""))/(IFERROR((AVERAGEIFS('M3 · Base mensuelle'!$D$14:$AM$14,HDR,">="&PP_START,HDR,"<="&PP_END)),""))-1,"") | I186: =IFERROR((IFERROR((AVERAGEIFS('M3 · Base mensuelle'!$D$15:$AM$15,HDR,">="&P_START,HDR,"<="&P_END)),""))/(IFERROR((AVERAGEIFS('M3 · Base mensuelle'!$D$15:$AM$15,HDR,">="&PP_START,HDR,"<="&PP_END)),""))-1,"")
C189: =" "&IFERROR(IF(LANG="EN",INDEX(I18N_EN,MATCH("kpi.lease.gla_vacant",I18N_KEY,0)),INDEX(I18N_FR,MATCH("kpi.lease.gla_vacant",I18N_KEY,0))),"kpi.lease.gla_vacant") | I189: =" "&IFERROR(IF(LANG="EN",INDEX(I18N_EN,MATCH("kpi.lease.ocr",I18N_KEY,0)),INDEX(I18N_FR,MATCH("kpi.lease.ocr",I18N_KEY,0))),"kpi.lease.ocr")
C190: =IFERROR((INDEX('M3 · Base mensuelle'!$D$16:$AM$16,MATCH(P_END,HDR,0))),"") | I190: =IFERROR((AVERAGEIFS('M3 · Base mensuelle'!$D$17:$AM$17,HDR,">="&P_START,HDR,"<="&P_END)),"")
C191: =IFERROR((IFERROR((INDEX('M3 · Base mensuelle'!$D$16:$AM$16,MATCH(P_END,HDR,0))),""))/(IFERROR((INDEX('M3 · Base mensuelle'!$D$16:$AM$16,MATCH(PP_END,HDR,0))),""))-1,"") | I191: =IFERROR((IFERROR((AVERAGEIFS('M3 · Base mensuelle'!$D$17:$AM$17,HDR,">="&P_START,HDR,"<="&P_END)),""))/(IFERROR((AVERAGEIFS('M3 · Base mensuelle'!$D$17:$AM$17,HDR,">="&PP_START,HDR,"<="&PP_END)),""))-1,"")
C194: ="▌ "&IFERROR(IF(LANG="EN",INDEX(I18N_EN,MATCH("kpi.lease.occ_gla",I18N_KEY,0)),INDEX(I18N_FR,MATCH("kpi.lease.occ_gla",I18N_KEY,0))),"kpi.lease.occ_gla")&" — 12 mois / 12M"
C206: ="▌ "&IF(LANG="EN","Key gauges","Jauges clés")
C207: =IFERROR(IF(LANG="EN",INDEX(I18N_EN,MATCH("kpi.lease.occ_gla",I18N_KEY,0)),INDEX(I18N_FR,MATCH("kpi.lease.occ_gla",I18N_KEY,0))),"kpi.lease.occ_gla") | G207: =IFERROR(IF(LANG="EN",INDEX(I18N_EN,MATCH("kpi.lease.occ_unit",I18N_KEY,0)),INDEX(I18N_FR,MATCH("kpi.lease.occ_unit",I18N_KEY,0))),"kpi.lease.occ_unit") | K207: =IFERROR(IF(LANG="EN",INDEX(I18N_EN,MATCH("kpi.lease.ocr",I18N_KEY,0)),INDEX(I18N_FR,MATCH("kpi.lease.ocr",I18N_KEY,0))),"kpi.lease.ocr")
C215: =IFERROR((AVERAGEIFS('M3 · Base mensuelle'!$D$14:$AM$14,HDR,">="&P_START,HDR,"<="&P_END)),"") | G215: =IFERROR((AVERAGEIFS('M3 · Base mensuelle'!$D$15:$AM$15,HDR,">="&P_START,HDR,"<="&P_END)),"") | K215: =IFERROR((AVERAGEIFS('M3 · Base mensuelle'!$D$17:$AM$17,HDR,">="&P_START,HDR,"<="&P_END)),"")
C219: ="▸ 3.1 "&IF(LANG="EN","Building Summary","Synthèse de l'immeuble")
C220: Élément / Item | D220: Valeur / Value | E220: Unité / Unit
C221: GLA totale / Total GLA | D221: 18000 | E221: m²
C222: Unités / Units | D222: 96 | E222: nb
C223: Unités louées / Let units | D223: 86 | E223: nb
C224: GLA vacante / Vacant GLA | D224: 1800 | E224: m²
C225: Niveaux / Floors | D225: 3 | E225: nb
C226: Places de parking / Parking bays | D226: 450 | E226: nb
C227: Locataires actifs / Active tenants | D227: 92 | E227: nb
C237: ="💬 "&IFERROR(IF(LANG="EN",INDEX(I18N_EN,MATCH("col.comment",I18N_KEY,0)),INDEX(I18N_FR,MATCH("col.comment",I18N_KEY,0))),"col.comment")
C238: =IF(LANG="EN","Commentary / data source: management systems (demo).","Commentaire / source : systèmes de gestion (démo).")
C243: ="▸ 3.2 "&IF(LANG="EN","Rental Trading","Activité locative")
...

Sheet M0 · Pilotage
B1: M0 · PUPITRE DE PILOTAGE
B2: Sélecteurs globaux — pilotent tout le classeur
B4: 🌐 Langue (LANG) | D4: FR
B5: Granularité (GRAIN) | D5: M | F5: M = Mois · Q = Trimestre · Y = Année
B6: Année (ANNEE) | D6: 2026
B7: Mois (MOIS) | D7: 6
B8: Période (PERIODE) | D8: =DATE(ANNEE,MOIS,1) | F8: Libellé : | G8: =IF(LANG="EN",INDEX(MOIS_EN,MONTH(PERIODE)),INDEX(MOIS_FR,MONTH(PERIODE)))&" "&YEAR(PERIODE)
B11: MOTEUR TEMPOREL — bornes
B12: P_START | D12: =IF(GRAIN="M",PERIODE,IF(GRAIN="Q",DATE(ANNEE,(ROUNDUP(MOIS/3,0)-1)*3+1,1),DATE(ANNEE,1,1)))
B13: P_END | D13: =IF(GRAIN="M",PERIODE,IF(GRAIN="Q",EDATE(P_START,2),DATE(ANNEE,12,1)))
B14: PP_START | D14: =IF(GRAIN="M",EDATE(P_START,-1),IF(GRAIN="Q",EDATE(P_START,-3),EDATE(P_START,-12)))
B15: PP_END | D15: =IF(GRAIN="M",EDATE(P_END,-1),IF(GRAIN="Q",EDATE(P_END,-3),EDATE(P_END,-12)))
B16: PY_START | D16: =EDATE(P_START,-12)
B17: PY_END | D17: =EDATE(P_END,-12)
B20: SUIVI DE SAISIE (mois courant)
B21: Département | C21: Complétude % | D21: État
B22: =IFERROR(IF(LANG="EN",INDEX(I18N_EN,MATCH("dept.rh",I18N_KEY,0)),INDEX(I18N_FR,MATCH("dept.rh",I18N_KEY,0))),"dept.rh") | C22: =IFERROR(COUNT(INDEX('C1 · Capital Humain'!$D$8:$AM$17,0,MATCH(PERIODE,'C1 · Capital Humain'!$D$6:$AM$6,0)))/ROWS('C1 · Capital Humain'!$C$8:$C$17),0) | D22: =IF(C22>=1,"✓",IF(C22>0,"⌛","✗"))
B23: =IFERROR(IF(LANG="EN",INDEX(I18N_EN,MATCH("dept.lease",I18N_KEY,0)),INDEX(I18N_FR,MATCH("dept.lease",I18N_KEY,0))),"dept.lease") | C23: =IFERROR(COUNT(INDEX('C2 · Lease'!$D$8:$AM$19,0,MATCH(PERIODE,'C2 · Lease'!$D$6:$AM$6,0)))/ROWS('C2 · Lease'!$C$8:$C$19),0) | D23: =IF(C23>=1,"✓",IF(C23>0,"⌛","✗"))
B24: =IFERROR(IF(LANG="EN",INDEX(I18N_EN,MATCH("dept.rec",I18N_KEY,0)),INDEX(I18N_FR,MATCH("dept.rec",I18N_KEY,0))),"dept.rec") | C24: =IFERROR(COUNT(INDEX('C3 · Recouvrement'!$D$8:$AM$25,0,MATCH(PERIODE,'C3 · Recouvrement'!$D$6:$AM$6,0)))/ROWS('C3 · Recouvrement'!$C$8:$C$25),0) | D24: =IF(C24>=1,"✓",IF(C24>0,"⌛","✗"))
B25: =IFERROR(IF(LANG="EN",INDEX(I18N_EN,MATCH("dept.foot",I18N_KEY,0)),INDEX(I18N_FR,MATCH("dept.foot",I18N_KEY,0))),"dept.foot") | C25: =IFERROR(COUNT(INDEX('C4 · Footfall'!$D$8:$AM$14,0,MATCH(PERIODE,'C4 · Footfall'!$D$6:$AM$6,0)))/ROWS('C4 · Footfall'!$C$8:$C$14),0) | D25: =IF(C25>=1,"✓",IF(C25>0,"⌛","✗"))
B26: =IFERROR(IF(LANG="EN",INDEX(I18N_EN,MATCH("dept.mkt",I18N_KEY,0)),INDEX(I18N_FR,MATCH("dept.mkt",I18N_KEY,0))),"dept.mkt") | C26: =IFERROR(COUNT(INDEX('C5 · Marketing'!$D$8:$AM$24,0,MATCH(PERIODE,'C5 · Marketing'!$D$6:$AM$6,0)))/ROWS('C5 · Marketing'!$C$8:$C$24),0) | D26: =IF(C26>=1,"✓",IF(C26>0,"⌛","✗"))
B27: =IFERROR(IF(LANG="EN",INDEX(I18N_EN,MATCH("dept.com",I18N_KEY,0)),INDEX(I18N_FR,MATCH("dept.com",I18N_KEY,0))),"dept.com") | C27: =IFERROR(COUNT(INDEX('C6 · Commercial'!$D$8:$AM$26,0,MATCH(PERIODE,'C6 · Commercial'!$D$6:$AM$6,0)))/ROWS('C6 · Commercial'!$C$8:$C$26),0) | D27: =IF(C27>=1,"✓",IF(C27>0,"⌛","✗"))
B28: =IFERROR(IF(LANG="EN",INDEX(I18N_EN,MATCH("dept.hsse",I18N_KEY,0)),INDEX(I18N_FR,MATCH("dept.hsse",I18N_KEY,0))),"dept.hsse") | C28: =IFERROR(COUNT(INDEX('C7 · HSSE'!$D$8:$AM$26,0,MATCH(PERIODE,'C7 · HSSE'!$D$6:$AM$6,0)))/ROWS('C7 · HSSE'!$C$8:$C$26),0) | D28: =IF(C28>=1,"✓",IF(C28>0,"⌛","✗"))
B29: =IFERROR(IF(LANG="EN",INDEX(I18N_EN,MATCH("dept.fac",I18N_KEY,0)),INDEX(I18N_FR,MATCH("dept.fac",I18N_KEY,0))),"dept.fac") | C29: =IFERROR(COUNT(INDEX('C8 · Facility'!$D$8:$AM$27,0,MATCH(PERIODE,'C8 · Facility'!$D$6:$AM$6,0)))/ROWS('C8 · Facility'!$C$8:$C$27),0) | D29: =IF(C29>=1,"✓",IF(C29>0,"⌛","✗"))

Sheet C1 · Capital Humain
C1: ="▌ "&IFERROR(IF(LANG="EN",INDEX(I18N_EN,MATCH("msg.collect",I18N_KEY,0)),INDEX(I18N_FR,MATCH("msg.collect",I18N_KEY,0))),"msg.collect")&" · "&IFERROR(IF(LANG="EN",INDEX(I18N_EN,MATCH("dept.rh",I18N_KEY,0)),INDEX(I18N_FR,MATCH("dept.rh",I18N_KEY,0))),"dept.rh")
C2: =IFERROR(IF(LANG="EN",INDEX(I18N_EN,MATCH("msg.help",I18N_KEY,0)),INDEX(I18N_FR,MATCH("msg.help",I18N_KEY,0))),"msg.help")
C6: KPI \ Mois | D6: =DATE(2024,1,1) | E6: =DATE(2024,2,1) | F6: =DATE(2024,3,1) | G6: =DATE(2024,4,1) | H6: =DATE(2024,5,1) | I6: =DATE(2024,6,1) | J6: =DATE(2024,7,1) | K6: =DATE(2024,8,1) | L6: =DATE(2024,9,1) | M6: =DATE(2024,10,1) | N6: =DATE(2024,11,1) | O6: =DATE(2024,12,1) | P6: =DATE(2025,1,1) | Q6: =DATE(2025,2,1) | R6: =DATE(2025,3,1) | S6: =DATE(2025,4,1) | T6: =DATE(2025,5,1) | U6: =DATE(2025,6,1) | V6: =DATE(2025,7,1) | W6: =DATE(2025,8,1) | X6: =DATE(2025,9,1) | Y6: =DATE(2025,10,1) | Z6: =DATE(2025,11,1) | AA6: =DATE(2025,12,1) | AB6: =DATE(2026,1,1) | AC6: =DATE(2026,2,1) | AD6: =DATE(2026,3,1) | AE6: =DATE(2026,4,1) | AF6: =DATE(2026,5,1) | AG6: =DATE(2026,6,1) | AH6: =DATE(2026,7,1) | AI6: =DATE(2026,8,1) | AJ6: =DATE(2026,9,1) | AK6: =DATE(2026,10,1) | AL6: =DATE(2026,11,1) | AM6: =DATE(2026,12,1)
C8: =IFERROR(IF(LANG="EN",INDEX(I18N_EN,MATCH("kpi.rh.headcount",I18N_KEY,0)),INDEX(I18N_FR,MATCH("kpi.rh.headcount",I18N_KEY,0))),"kpi.rh.headcount") | D8: 118 | E8: 119 | F8: 122 | G8: 119 | H8: 118 | I8: 120 | J8: 118 | K8: 122 | L8: 120 | M8: 121 | N8: 125 | O8: 119 | P8: 125 | Q8: 117 | R8: 126 | S8: 127 | T8: 125 | U8: 122 | V8: 128 | W8: 128 | X8: 124 | Y8: 119 | Z8: 116 | AA8: 117 | AB8: 126 | AC8: 121 | AD8: 122 | AE8: 128 | AF8: 120 | AG8: 118 | AH8: 136 | AI8: 127 | AJ8: 134 | AK8: 117 | AL8: 120 | AM8: 121
C9: =IFERROR(IF(LANG="EN",INDEX(I18N_EN,MATCH("kpi.rh.fte_gap",I18N_KEY,0)),INDEX(I18N_FR,MATCH("kpi.rh.fte_gap",I18N_KEY,0))),"kpi.rh.fte_gap") | D9: 5 | E9: 5 | F9: 5 | G9: 5 | H9: 5 | I9: 5 | J9: 5 | K9: 5 | L9: 5 | M9: 5 | N9: 5 | O9: 5 | P9: 5 | Q9: 5 | R9: 5 | S9: 5 | T9: 5 | U9: 5 | V9: 5 | W9: 5 | X9: 5 | Y9: 5 | Z9: 5 | AA9: 5 | AB9: 5 | AC9: 5 | AD9: 5 | AE9: 5 | AF9: 6 | AG9: 5 | AH9: 6 | AI9: 5 | AJ9: 5 | AK9: 5 | AL9: 5 | AM9: 5
C10: =IFERROR(IF(LANG="EN",INDEX(I18N_EN,MATCH("kpi.rh.open_pos",I18N_KEY,0)),INDEX(I18N_FR,MATCH("kpi.rh.open_pos",I18N_KEY,0))),"kpi.rh.open_pos") | D10: 6 | E10: 6 | F10: 6 | G10: 6 | H10: 6 | I10: 6 | J10: 6 | K10: 6 | L10: 6 | M10: 6 | N10: 6 | O10: 6 | P10: 6 | Q10: 6 | R10: 6 | S10: 6 | T10: 6 | U10: 6 | V10: 6 | W10: 6 | X10: 6 | Y10: 6 | Z10: 6 | AA10: 6 | AB10: 6 | AC10: 6 | AD10: 6 | AE10: 7 | AF10: 7 | AG10: 7 | AH10: 6 | AI10: 6 | AJ10: 6 | AK10: 6 | AL10: 6 | AM10: 7
C11: =IFERROR(IF(LANG="EN",INDEX(I18N_EN,MATCH("kpi.rh.ttf",I18N_KEY,0)),INDEX(I18N_FR,MATCH("kpi.rh.ttf",I18N_KEY,0))),"kpi.rh.ttf") | D11: 38 | E11: 38 | F11: 38 | G11: 39 | H11: 38 | I11: 39 | J11: 39 | K11: 37 | L11: 39 | M11: 37 | N11: 39 | O11: 39 | P11: 39 | Q11: 39 | R11: 38 | S11: 38 | T11: 39 | U11: 39 | V11: 37 | W11: 42 | X11: 37 | Y11: 39 | Z11: 42 | AA11: 38 | AB11: 41 | AC11: 41 | AD11: 40 | AE11: 41 | AF11: 41 | AG11: 37 | AH11: 37 | AI11: 38 | AJ11: 41 | AK11: 40 | AL11: 40 | AM11: 42
C12: =IFERROR(IF(LANG="EN",INDEX(I18N_EN,MATCH("kpi.rh.payroll",I18N_KEY,0)),INDEX(I18N_FR,MATCH("kpi.rh.payroll",I18N_KEY,0))),"kpi.rh.payroll") | D12: 84240713 | E12: 85802099 | F12: 84566701 | G12: 85891507 | H12: 83678097 | I12: 85878154 | J12: 87060742 | K12: 87268156 | L12: 83337336 | M12: 86611209 | N12: 88878983 | O12: 87481372 | P12: 83646757 | Q12: 89653363 | R12: 86473615 | S12: 85766198 | T12: 91395465 | U12: 90927187 | V12: 83835309 | W12: 87223228 | X12: 91602388 | Y12: 89926782 | Z12: 89409756 | AA12: 93169709 | AB12: 85755050 | AC12: 86891331 | AD12: 90960759 | AE12: 80988412 | AF12: 87303163 | AG12: 94346920 | AH12: 90363355 | AI12: 96132159 | AJ12: 94404876 | AK12: 95454123 | AL12: 95969581 | AM12: 82370360
C13: =IFERROR(IF(LANG="EN",INDEX(I18N_EN,MATCH("kpi.rh.payroll_var",I18N_KEY,0)),INDEX(I18N_FR,MATCH("kpi.rh.payroll_var",I18N_KEY,0))),"kpi.rh.payroll_var") | D13: 1.0124 | E13: 1.0225 | F13: 1.0247 | G13: 1.0286 | H13: 1.0316 | I13: 1.0374 | J13: 1.0442 | K13: 1.0071 | L13: 1.0324 | M13: 1.0376 | N13: 1.0392 | O13: 1.0201 | P13: 1.0223 | Q13: 1.0075 | R13: 1.0836 | S13: 1.0818 | T13: 1.0267 | U13: 0.9866 | V13: 1.0421 | W13: 1.0634 | X13: 1.0307 | Y13: 1.0637 | Z13: 1.0765 | AA13: 0.9985 | AB13: 1.0668 | AC13: 1.1131 | AD13: 1.0728 | AE13: 0.9926 | AF13: 1.0181 | AG13: 1.1039 | AH13: 1.054 | AI13: 1.018 | AJ13: 1.0551 | AK13: 1.0779 | AL13: 1.1303 | AM13: 0.9877
C14: =IFERROR(IF(LANG="EN",INDEX(I18N_EN,MATCH("kpi.rh.turnover",I18N_KEY,0)),INDEX(I18N_FR,MATCH("kpi.rh.turnover",I18N_KEY,0))),"kpi.rh.turnover") | D14: 0.0305 | E14: 0.0295 | F14: 0.0304 | G14: 0.0305 | H14: 0.0309 | I14: 0.0308 | J14: 0.0308 | K14: 0.0306 | L14: 0.0309 | M14: 0.0313 | N14: 0.0301 | O14: 0.0302 | P14: 0.0311 | Q14: 0.0306 | R14: 0.0293 | S14: 0.0298 | T14: 0.0304 | U14: 0.0302 | V14: 0.0309 | W14: 0.0306 | X14: 0.0302 | Y14: 0.0311 | Z14: 0.0315 | AA14: 0.0327 | AB14: 0.0299 | AC14: 0.0307 | AD14: 0.0332 | AE14: 0.0311 | AF14: 0.0315 | AG14: 0.0295 | AH14: 0.0304 | AI14: 0.0307 | AJ14: 0.0304 | AK14: 0.0308 | AL14: 0.0316 | AM14: 0.0309
C15: =IFERROR(IF(LANG="EN",INDEX(I18N_EN,MATCH("kpi.rh.absence",I18N_KEY,0)),INDEX(I18N_FR,MATCH("kpi.rh.absence",I18N_KEY,0))),"kpi.rh.absence") | D15: 0.0402 | E15: 0.0399 | F15: 0.0397 | G15: 0.0397 | H15: 0.0403 | I15: 0.0411 | J15: 0.0393 | K15: 0.0397 | L15: 0.0411 | M15: 0.0413 | N15: 0.0413 | O15: 0.0413 | P15: 0.0388 | Q15: 0.0399 | R15: 0.0406 | S15: 0.042 | T15: 0.0399 | U15: 0.0413 | V15: 0.0431 | W15: 0.0386 | X15: 0.0406 | Y15: 0.0432 | Z15: 0.0417 | AA15: 0.0425 | AB15: 0.0396 | AC15: 0.0436 | AD15: 0.04 | AE15: 0.043 | AF15: 0.0409 | AG15: 0.0414 | AH15: 0.0446 | AI15: 0.0397 | AJ15: 0.0433 | AK15: 0.0433 | AL15: 0.0445 | AM15: 0.0407
C16: =IFERROR(IF(LANG="EN",INDEX(I18N_EN,MATCH("kpi.rh.train_hours",I18N_KEY,0)),INDEX(I18N_FR,MATCH("kpi.rh.train_hours",I18N_KEY,0))),"kpi.rh.train_hours") | D16: 2.5 | E16: 2.53 | F16: 2.54 | G16: 2.48 | H16: 2.51 | I16: 2.53 | J16: 2.46 | K16: 2.53 | L16: 2.53 | M16: 2.55 | N16: 2.54 | O16: 2.51 | P16: 2.49 | Q16: 2.57 | R16: 2.6 | S16: 2.58 | T16: 2.44 | U16: 2.59 | V16: 2.58 | W16: 2.57 | X16: 2.62 | Y16: 2.61 | Z16: 2.46 | AA16: 2.44 | AB16: 2.62 | AC16: 2.45 | AD16: 2.61 | AE16: 2.78 | AF16: 2.47 | AG16: 2.45 | AH16: 2.42 | AI16: 2.6 | AJ16: 2.84 | AK16: 2.67 | AL16: 2.8 | AM16: 2.82
C17: =IFERROR(IF(LANG="EN",INDEX(I18N_EN,MATCH("kpi.rh.train_cover",I18N_KEY,0)),INDEX(I18N_FR,MATCH("kpi.rh.train_cover",I18N_KEY,0))),"kpi.rh.train_cover") | D17: 0.5986 | E17: 0.589 | F17: 0.6042 | G17: 0.6035 | H17: 0.6007 | I17: 0.5882 | J17: 0.6017 | K17: 0.6087 | L17: 0.6167 | M17: 0.6101 | N17: 0.6082 | O17: 0.6159 | P17: 0.6258 | Q17: 0.6192 | R17: 0.6343 | S17: 0.5909 | T17: 0.6143 | U17: 0.5854 | V17: 0.5835 | W17: 0.6174 | X17: 0.6037 | Y17: 0.6315 | Z17: 0.6432 | AA17: 0.6454 | AB17: 0.6442 | AC17: 0.6161 | AD17: 0.6452 | AE17: 0.6431 | AF17: 0.5873 | AG17: 0.6513 | AH17: 0.595 | AI17: 0.6514 | AJ17: 0.676 | AK17: 0.6175 | AL17: 0.5739 | AM17: 0.6027
C19: 💬 Commentaires (KPI × mois)
C20: =IFERROR(IF(LANG="EN",INDEX(I18N_EN,MATCH("kpi.rh.headcount",I18N_KEY,0)),INDEX(I18N_FR,MATCH("kpi.rh.headcount",I18N_KEY,0))),"kpi.rh.headcount")
C21: =IFERROR(IF(LANG="EN",INDEX(I18N_EN,MATCH("kpi.rh.fte_gap",I18N_KEY,0)),INDEX(I18N_FR,MATCH("kpi.rh.fte_gap",I18N_KEY,0))),"kpi.rh.fte_gap")
C22: =IFERROR(IF(LANG="EN",INDEX(I18N_EN,MATCH("kpi.rh.open_pos",I18N_KEY,0)),INDEX(I18N_FR,MATCH("kpi.rh.open_pos",I18N_KEY,0))),"kpi.rh.open_pos")
C23: =IFERROR(IF(LANG="EN",INDEX(I18N_EN,MATCH("kpi.rh.ttf",I18N_KEY,0)),INDEX(I18N_FR,MATCH("kpi.rh.ttf",I18N_KEY,0))),"kpi.rh.ttf")
C24: =IFERROR(IF(LANG="EN",INDEX(I18N_EN,MATCH("kpi.rh.payroll",I18N_KEY,0)),INDEX(I18N_FR,MATCH("kpi.rh.payroll",I18N_KEY,0))),"kpi.rh.payroll")
C25: =IFERROR(IF(LANG="EN",INDEX(I18N_EN,MATCH("kpi.rh.payroll_var",I18N_KEY,0)),INDEX(I18N_FR,MATCH("kpi.rh.payroll_var",I18N_KEY,0))),"kpi.rh.payroll_var")
C26: =IFERROR(IF(LANG="EN",INDEX(I18N_EN,MATCH("kpi.rh.turnover",I18N_KEY,0)),INDEX(I18N_FR,MATCH("kpi.rh.turnover",I18N_KEY,0))),"kpi.rh.turnover")
C27: =IFERROR(IF(LANG="EN",INDEX(I18N_EN,MATCH("kpi.rh.absence",I18N_KEY,0)),INDEX(I18N_FR,MATCH("kpi.rh.absence",I18N_KEY,0))),"kpi.rh.absence")
C28: =IFERROR(IF(LANG="EN",INDEX(I18N_EN,MATCH("kpi.rh.train_hours",I18N_KEY,0)),INDEX(I18N_FR,MATCH("kpi.rh.train_hours",I18N_KEY,0))),"kpi.rh.train_hours")
C29: =IFERROR(IF(LANG="EN",INDEX(I18N_EN,MATCH("kpi.rh.train_cover",I18N_KEY,0)),INDEX(I18N_FR,MATCH("kpi.rh.train_cover",I18N_KEY,0))),"kpi.rh.train_cover")

Sheet C2 · Lease
C1: ="▌ "&IFERROR(IF(LANG="EN",INDEX(I18N_EN,MATCH("msg.collect",I18N_KEY,0)),INDEX(I18N_FR,MATCH("msg.collect",I18N_KEY,0))),"msg.collect")&" · "&IFERROR(IF(LANG="EN",INDEX(I18N_EN,MATCH("dept.lease",I18N_KEY,0)),INDEX(I18N_FR,MATCH("dept.lease",I18N_KEY,0))),"dept.lease")
C2: =IFERROR(IF(LANG="EN",INDEX(I18N_EN,MATCH("msg.help",I18N_KEY,0)),INDEX(I18N_FR,MATCH("msg.help",I18N_KEY,0))),"msg.help")
C6: KPI \ Mois | D6: =DATE(2024,1,1) | E6: =DATE(2024,2,1) | F6: =DATE(2024,3,1) | G6: =DATE(2024,4,1) | H6: =DATE(2024,5,1) | I6: =DATE(2024,6,1) | J6: =DATE(2024,7,1) | K6: =DATE(2024,8,1) | L6: =DATE(2024,9,1) | M6: =DATE(2024,10,1) | N6: =DATE(2024,11,1) | O6: =DATE(2024,12,1) | P6: =DATE(2025,1,1) | Q6: =DATE(2025,2,1) | R6: =DATE(2025,3,1) | S6: =DATE(2025,4,1) | T6: =DATE(2025,5,1) | U6: =DATE(2025,6,1) | V6: =DATE(2025,7,1) | W6: =DATE(2025,8,1) | X6: =DATE(2025,9,1) | Y6: =DATE(2025,10,1) | Z6: =DATE(2025,11,1) | AA6: =DATE(2025,12,1) | AB6: =DATE(2026,1,1) | AC6: =DATE(2026,2,1) | AD6: =DATE(2026,3,1) | AE6: =DATE(2026,4,1) | AF6: =DATE(2026,5,1) | AG6: =DATE(2026,6,1) | AH6: =DATE(2026,7,1) | AI6: =DATE(2026,8,1) | AJ6: =DATE(2026,9,1) | AK6: =DATE(2026,10,1) | AL6: =DATE(2026,11,1) | AM6: =DATE(2026,12,1)
C8: =IFERROR(IF(LANG="EN",INDEX(I18N_EN,MATCH("kpi.lease.occ_gla",I18N_KEY,0)),INDEX(I18N_FR,MATCH("kpi.lease.occ_gla",I18N_KEY,0))),"kpi.lease.occ_gla") | D8: 0.9166 | E8: 0.9057 | F8: 0.9252 | G8: 0.8982 | H8: 0.9049 | I8: 0.9111 | J8: 0.9091 | K8: 0.9169 | L8: 0.8952 | M8: 0.8985 | N8: 0.9345 | O8: 0.9115 | P8: 0.9184 | Q8: 0.9395 | R8: 0.9081 | S8: 0.9226 | T8: 0.9132 | U8: 0.9702 | V8: 0.924 | W8: 0.8889 | X8: 0.9566 | Y8: 0.9444 | Z8: 0.9493 | AA8: 0.9294 | AB8: 0.9012 | AC8: 0.9368 | AD8: 0.8896 | AE8: 0.9273 | AF8: 1.0218 | AG8: 0.9178 | AH8: 0.9898 | AI8: 0.9747 | AJ8: 0.9159 | AK8: 1.0147 | AL8: 0.9485 | AM8: 1.0212
C9: =IFERROR(IF(LANG="EN",INDEX(I18N_EN,MATCH("kpi.lease.occ_unit",I18N_KEY,0)),INDEX(I18N_FR,MATCH("kpi.lease.occ_unit",I18N_KEY,0))),"kpi.lease.occ_unit") | D9: 0.8928 | E9: 0.8903 | F9: 0.8969 | G9: 0.8952 | H9: 0.8736 | I9: 0.906 | J9: 0.8749 | K9: 0.8847 | L9: 0.8937 | M9: 0.883 | N9: 0.8839 | O9: 0.8884 | P9: 0.8956 | Q9: 0.9196 | R9: 0.9155 | S9: 0.9225 | T9: 0.9386 | U9: 0.8619 | V9: 0.9238 | W9: 0.9375 | X9: 0.9062 | Y9: 0.9267 | Z9: 0.9126 | AA9: 0.9219 | AB9: 0.8975 | AC9: 0.9426 | AD9: 0.9714 | AE9: 0.8912 | AF9: 0.9551 | AG9: 0.9544 | AH9: 0.8572 | AI9: 1.0021 | AJ9: 0.9576 | AK9: 0.8596 | AL9: 0.9845 | AM9: 0.9723
C10: =IFERROR(IF(LANG="EN",INDEX(I18N_EN,MATCH("kpi.lease.gla_vacant",I18N_KEY,0)),INDEX(I18N_FR,MATCH("kpi.lease.gla_vacant",I18N_KEY,0))),"kpi.lease.gla_vacant") | D10: 1821 | E10: 1791 | F10: 1800 | G10: 1831 | H10: 1766 | I10: 1841 | J10: 1829 | K10: 1790 | L10: 1783 | M10: 1800 | N10: 1880 | O10: 1785 | P10: 1818 | Q10: 1847 | R10: 1825 | S10: 1784 | T10: 1819 | U10: 1862 | V10: 1923 | W10: 1954 | X10: 1810 | Y10: 1912 | Z10: 1762 | AA10: 1887 | AB10: 1830 | AC10: 1881 | AD10: 1912 | AE10: 1935 | AF10: 1942 | AG10: 1942 | AH10: 1909 | AI10: 1867 | AJ10: 1929 | AK10: 1833 | AL10: 1748 | AM10: 1938
C11: =IFERROR(IF(LANG="EN",INDEX(I18N_EN,MATCH("kpi.lease.ocr",I18N_KEY,0)),INDEX(I18N_FR,MATCH("kpi.lease.ocr",I18N_KEY,0))),"kpi.lease.ocr") | D11: 0.122 | E11: 0.1192 | F11: 0.1207 | G11: 0.1223 | H11: 0.1184 | I11: 0.1207 | J11: 0.1247 | K11: 0.1246 | L11: 0.1254 | M11: 0.1221 | N11: 0.1186 | O11: 0.1224 | P11: 0.1239 | Q11: 0.1272 | R11: 0.1174 | S11: 0.1195 | T11: 0.1254 | U11: 0.1176 | V11: 0.129 | W11: 0.1202 | X11: 0.1206 | Y11: 0.1207 | Z11: 0.1196 | AA11: 0.118 | AB11: 0.1281 | AC11: 0.1315 | AD11: 0.1271 | AE11: 0.1211 | AF11: 0.1242 | AG11: 0.1317 | AH11: 0.1222 | AI11: 0.1366 | AJ11: 0.1176 | AK11: 0.129 | AL11: 0.122 | AM11: 0.1167
C12: =IFERROR(IF(LANG="EN",INDEX(I18N_EN,MATCH("kpi.lease.passing",I18N_KEY,0)),INDEX(I18N_FR,MATCH("kpi.lease.passing",I18N_KEY,0))),"kpi.lease.passing") | D12: 129764530 | E12: 131043491 | F12: 128026818 | G12: 129862843 | H12: 129967122 | I12: 130705085 | J12: 128331991 | K12: 132330926 | L12: 131473941 | M12: 130211241 | N12: 127293641 | O12: 128312731 | P12: 131198342 | Q12: 129237143 | R12: 128958100 | S12: 126828361 | T12: 135980065 | U12: 136136023 | V12: 137129180 | W12: 128030609 | X12: 137957388 | Y12: 140226642 | Z12: 134218110 | AA12: 139915939 | AB12: 133570830 | AC12: 138048352 | AD12: 140523802 | AE12: 127169287 | AF12: 124996274 | AG12: 138504021 | AH12: 134247626 | AI12: 136220143 | AJ12: 136364731 | AK12: 142909572 | AL12: 141524616 | AM12: 140759958
C13: =IFERROR(IF(LANG="EN",INDEX(I18N_EN,MATCH("kpi.lease.erv",I18N_KEY,0)),INDEX(I18N_FR,MATCH("kpi.lease.erv",I18N_KEY,0))),"kpi.lease.erv") | D13: 138479564 | E13: 139810739 | F13: 137998064 | G13: 141348838 | H13: 138452541 | I13: 140267887 | J13: 140514594 | K13: 140478018 | L13: 143911000 | M13: 142767433 | N13: 138521663 | O13: 141837570 | P13: 146864045 | Q13: 147522063 | R13: 143093812 | S13: 142326360 | T13: 143661996 | U13: 140005861 | V13: 143163471 | W13: 146646760 | X13: 152179944 | Y13: 150185582 | Z13: 144258527 | AA13: 154340131 | AB13: 138545326 | AC13: 147984290 | AD13: 139102545 | AE13: 153760433 | AF13: 141372067 | AG13: 146261270 | AH13: 150311426 | AI13: 143320863 | AJ13: 144314297 | AK13: 154286984 | AL13: 133005441 | AM13: 138067371
C14: =IFERROR(IF(LANG="EN",INDEX(I18N_EN,MATCH("kpi.lease.reversion",I18N_KEY,0)),INDEX(I18N_FR,MATCH("kpi.lease.reversion",I18N_KEY,0))),"kpi.lease.reversion") | D14: 0.0694 | E14: 0.0701 | F14: 0.0695 | G14: 0.0695 | H14: 0.0697 | I14: 0.0708 | J14: 0.0697 | K14: 0.0707 | L14: 0.0687 | M14: 0.0688 | N14: 0.0695 | O14: 0.0696 | P14: 0.0693 | Q14: 0.0724 | R14: 0.0741 | S14: 0.0699 | T14: 0.0673 | U14: 0.0756 | V14: 0.0726 | W14: 0.0733 | X14: 0.0676 | Y14: 0.0715 | Z14: 0.0742 | AA14: 0.075 | AB14: 0.075 | AC14: 0.0735 | AD14: 0.071 | AE14: 0.0705 | AF14: 0.0691 | AG14: 0.0685 | AH14: 0.0774 | AI14: 0.0768 | AJ14: 0.0765 | AK14: 0.0678 | AL14: 0.0755 | AM14: 0.0748
C15: =IFERROR(IF(LANG="EN",INDEX(I18N_EN,MATCH("kpi.lease.vac_age",I18N_KEY,0)),INDEX(I18N_FR,MATCH("kpi.lease.vac_age",I18N_KEY,0))),"kpi.lease.vac_age") | D15: 5 | E15: 5.07 | F15: 5.1 | G15: 5.05 | H15: 5.12 | I15: 4.98 | J15: 4.96 | K15: 4.97 | L15: 4.96 | M15: 5.01 | N15: 5.01 | O15: 5.02 | P15: 5.23 | Q15: 5.09 | R15: 5.18 | S15: 5.27 | T15: 5.29 | U15: 5.03 | V15: 4.86 | W15: 5 | X15: 5.1 | Y15: 5.09 | Z15: 4.99 | AA15: 5.13 | AB15: 4.91 | AC15: 5.01 | AD15: 5.09 | AE15: 5.45 | AF15: 4.77 | AG15: 5.31 | AH15: 5.44 | AI15: 5.66 | AJ15: 5.09 | AK15: 4.87 | AL15: 5.74 | AM15: 5.16
C16: =IFERROR(IF(LANG="EN",INDEX(I18N_EN,MATCH("kpi.lease.retention",I18N_KEY,0)),INDEX(I18N_FR,MATCH("kpi.lease.retention",I18N_KEY,0))),"kpi.lease.retention") | D16: 0.7939 | E16: 0.8099 | F16: 0.8106 | G16: 0.8156 | H16: 0.8088 | I16: 0.8066 | J16: 0.7987 | K16: 0.7886 | L16: 0.8251 | M16: 0.7874 | N16: 0.8031 | O16: 0.8012 | P16: 0.8444 | Q16: 0.7822 | R16: 0.8212 | S16: 0.7979 | T16: 0.8512 | U16: 0.8327 | V16: 0.8126 | W16: 0.8286 | X16: 0.8109 | Y16: 0.8462 | Z16: 0.8225 | AA16: 0.8577 | AB16: 0.86 | AC16: 0.8952 | AD16: 0.8182 | AE16: 0.8172 | AF16: 0.9018 | AG16: 0.8615 | AH16: 0.8045 | AI16: 0.8902 | AJ16: 0.7895 | AK16: 0.8838 | AL16: 0.8725 | AM16: 0.8936
C17: =IFERROR(IF(LANG="EN",INDEX(I18N_EN,MATCH("kpi.lease.incentives",I18N_KEY,0)),INDEX(I18N_FR,MATCH("kpi.lease.incentives",I18N_KEY,0))),"kpi.lease.incentives") | D17: 6107139 | E17: 5987312 | F17: 5893230 | G17: 5980245 | H17: 6116736 | I17: 5908179 | J17: 6221458 | K17: 6165922 | L17: 5918021 | M17: 6225955 | N17: 6011200 | O17: 5956161 | P17: 5871160 | Q17: 6272439 | R17: 6235738 | S17: 5877755 | T17: 5919520 | U17: 6169520 | V17: 6034425 | W17: 6449999 | X17: 5843532 | Y17: 5908654 | Z17: 6162752 | AA17: 5972535 | AB17: 6241516 | AC17: 6517375 | AD17: 6247846 | AE17: 6696480 | AF17: 6127668 | AG17: 6498916 | AH17: 5887653 | AI17: 6535122 | AJ17: 6560637 | AK17: 6646486 | AL17: 5986834 | AM17: 6430459
C18: =IFERROR(IF(LANG="EN",INDEX(I18N_EN,MATCH("kpi.lease.rent_sqm",I18N_KEY,0)),INDEX(I18N_FR,MATCH("kpi.lease.rent_sqm",I18N_KEY,0))),"kpi.lease.rent_sqm") | D18: 9100.49 | E18: 9081.38 | F18: 9151.4 | G18: 9070.59 | H18: 8968.36 | I18: 8838.79 | J18: 9091.8 | K18: 9271.62 | L18: 9031.75 | M18: 9121.75 | N18: 9156.12 | O18: 9287.86 | P18: 8875.02 | Q18: 9515.13 | R18: 9423.33 | S18: 9556.93 | T18: 9356.43 | U18: 9343.84 | V18: 9290.05 | W18: 9460.44 | X18: 9239.55 | Y18: 8874.41 | Z18: 9100.86 | AA18: 9276.64 | AB18: 8960.59 | AC18: 9744.11 | AD18: 9919.22 | AE18: 10174.94 | AF18: 8797.56 | AG18: 9277.39 | AH18: 9825.52 | AI18: 8867.79 | AJ18: 9706.92 | AK18: 8790.08 | AL18: 9161.24 | AM18: 9608.87
C19: =IFERROR(IF(LANG="EN",INDEX(I18N_EN,MATCH("kpi.lease.walt",I18N_KEY,0)),INDEX(I18N_FR,MATCH("kpi.lease.walt",I18N_KEY,0))),"kpi.lease.walt") | D19: 3.26 | E19: 3.24 | F19: 3.22 | G19: 3.23 | H19: 3.15 | I19: 3.24 | J19: 3.22 | K19: 3.17 | L19: 3.29 | M19: 3.26 | N19: 3.2 | O19: 3.32 | P19: 3.34 | Q19: 3.18 | R19: 3.33 | S19: 3.17 | T19: 3.34 | U19: 3.41 | V19: 3.44 | W19: 3.39 | X19: 3.11 | Y19: 3.19 | Z19: 3.12 | AA19: 3.29 | AB19: 3.35 | AC19: 3.1 | AD19: 3.58 | AE19: 3.37 | AF19: 3.44 | AG19: 3.6 | AH19: 3.33 | AI19: 3.3 | AJ19: 3.53 | AK19: 3.22 | AL19: 3.37 | AM19: 3.03
C21: 💬 Commentaires (KPI × mois)
C22: =IFERROR(IF(LANG="EN",INDEX(I18N_EN,MATCH("kpi.lease.occ_gla",I18N_KEY,0)),INDEX(I18N_FR,MATCH("kpi.lease.occ_gla",I18N_KEY,0))),"kpi.lease.occ_gla")
C23: =IFERROR(IF(LANG="EN",INDEX(I18N_EN,MATCH("kpi.lease.occ_unit",I18N_KEY,0)),INDEX(I18N_FR,MATCH("kpi.lease.occ_unit",I18N_KEY,0))),"kpi.lease.occ_unit")
C24: =IFERROR(IF(LANG="EN",INDEX(I18N_EN,MATCH("kpi.lease.gla_vacant",I18N_KEY,0)),INDEX(I18N_FR,MATCH("kpi.lease.gla_vacant",I18N_KEY,0))),"kpi.lease.gla_vacant")
C25: =IFERROR(IF(LANG="EN",INDEX(I18N_EN,MATCH("kpi.lease.ocr",I18N_KEY,0)),INDEX(I18N_FR,MATCH("kpi.lease.ocr",I18N_KEY,0))),"kpi.lease.ocr")
C26: =IFERROR(IF(LANG="EN",INDEX(I18N_EN,MATCH("kpi.lease.passing",I18N_KEY,0)),INDEX(I18N_FR,MATCH("kpi.lease.passing",I18N_KEY,0))),"kpi.lease.passing")
C27: =IFERROR(IF(LANG="EN",INDEX(I18N_EN,MATCH("kpi.lease.erv",I18N_KEY,0)),INDEX(I18N_FR,MATCH("kpi.lease.erv",I18N_KEY,0))),"kpi.lease.erv")
C28: =IFERROR(IF(LANG="EN",INDEX(I18N_EN,MATCH("kpi.lease.reversion",I18N_KEY,0)),INDEX(I18N_FR,MATCH("kpi.lease.reversion",I18N_KEY,0))),"kpi.lease.reversion")
C29: =IFERROR(IF(LANG="EN",INDEX(I18N_EN,MATCH("kpi.lease.vac_age",I18N_KEY,0)),INDEX(I18N_FR,MATCH("kpi.lease.vac_age",I18N_KEY,0))),"kpi.lease.vac_age")
C30: =IFERROR(IF(LANG="EN",INDEX(I18N_EN,MATCH("kpi.lease.retention",I18N_KEY,0)),INDEX(I18N_FR,MATCH("kpi.lease.retention",I18N_KEY,0))),"kpi.lease.retention")
C31: =IFERROR(IF(LANG="EN",INDEX(I18N_EN,MATCH("kpi.lease.incentives",I18N_KEY,0)),INDEX(I18N_FR,MATCH("kpi.lease.incentives",I18N_KEY,0))),"kpi.lease.incentives")
C32: =IFERROR(IF(LANG="EN",INDEX(I18N_EN,MATCH("kpi.lease.rent_sqm",I18N_KEY,0)),INDEX(I18N_FR,MATCH("kpi.lease.rent_sqm",I18N_KEY,0))),"kpi.lease.rent_sqm")
C33: =IFERROR(IF(LANG="EN",INDEX(I18N_EN,MATCH("kpi.lease.walt",I18N_KEY,0)),INDEX(I18N_FR,MATCH("kpi.lease.walt",I18N_KEY,0))),"kpi.lease.walt")

Sheet C3 · Recouvrement
C1: ="▌ "&IFERROR(IF(LANG="EN",INDEX(I18N_EN,MATCH("msg.collect",I18N_KEY,0)),INDEX(I18N_FR,MATCH("msg.collect",I18N_KEY,0))),"msg.collect")&" · "&IFERROR(IF(LANG="EN",INDEX(I18N_EN,MATCH("dept.rec",I18N_KEY,0)),INDEX(I18N_FR,MATCH("dept.rec",I18N_KEY,0))),"dept.rec")
C2: =IFERROR(IF(LANG="EN",INDEX(I18N_EN,MATCH("msg.help",I18N_KEY,0)),INDEX(I18N_FR,MATCH("msg.help",I18N_KEY,0))),"msg.help")
C6: KPI \ Mois | D6: =DATE(2024,1,1) | E6: =DATE(2024,2,1) | F6: =DATE(2024,3,1) | G6: =DATE(2024,4,1) | H6: =DATE(2024,5,1) | I6: =DATE(2024,6,1) | J6: =DATE(2024,7,1) | K6: =DATE(2024,8,1) | L6: =DATE(2024,9,1) | M6: =DATE(2024,10,1) | N6: =DATE(2024,11,1) | O6: =DATE(2024,12,1) | P6: =DATE(2025,1,1) | Q6: =DATE(2025,2,1) | R6: =DATE(2025,3,1) | S6: =DATE(2025,4,1) | T6: =DATE(2025,5,1) | U6: =DATE(2025,6,1) | V6: =DATE(2025,7,1) | W6: =DATE(2025,8,1) | X6: =DATE(2025,9,1) | Y6: =DATE(2025,10,1) | Z6: =DATE(2025,11,1) | AA6: =DATE(2025,12,1) | AB6: =DATE(2026,1,1) | AC6: =DATE(2026,2,1) | AD6: =DATE(2026,3,1) | AE6: =DATE(2026,4,1) | AF6: =DATE(2026,5,1) | AG6: =DATE(2026,6,1) | AH6: =DATE(2026,7,1) | AI6: =DATE(2026,8,1) | AJ6: =DATE(2026,9,1) | AK6: =DATE(2026,10,1) | AL6: =DATE(2026,11,1) | AM6: =DATE(2026,12,1)
C8: =IFERROR(IF(LANG="EN",INDEX(I18N_EN,MATCH("kpi.rec.ar",I18N_KEY,0)),INDEX(I18N_FR,MATCH("kpi.rec.ar",I18N_KEY,0))),"kpi.rec.ar") | D8: 414366239 | E8: 423691166 | F8: 427868099 | G8: 430455153 | H8: 422274770 | I8: 417312958 | J8: 421323105 | K8: 418676312 | L8: 427469318 | M8: 432535261 | N8: 434277838 | O8: 433743485 | P8: 405980915 | Q8: 433503113 | R8: 437962878 | S8: 428332176 | T8: 431661017 | U8: 429290326 | V8: 435181977 | W8: 436432471 | X8: 404109244 | Y8: 429291536 | Z8: 419364308 | AA8: 427123050 | AB8: 453950966 | AC8: 457319319 | AD8: 428557449 | AE8: 423915449 | AF8: 416939134 | AG8: 405813653 | AH8: 431597129 | AI8: 426008475 | AJ8: 410165856 | AK8: 442806424 | AL8: 461841565 | AM8: 442216050
C9: =IFERROR(IF(LANG="EN",INDEX(I18N_EN,MATCH("kpi.rec.aged_0_30",I18N_KEY,0)),INDEX(I18N_FR,MATCH("kpi.rec.aged_0_30",I18N_KEY,0))),"kpi.rec.aged_0_30") | D9: 176566869 | E9: 180754297 | F9: 179423367 | G9: 177081396 | H9: 183760409 | I9: 181867277 | J9: 184268933 | K9: 184056361 | L9: 185828978 | M9: 180357436 | N9: 181095844 | O9: 180360179 | P9: 185041949 | Q9: 183918861 | R9: 183453180 | S9: 190423099 | T9: 187808866 | U9: 193882507 | V9: 179122525 | W9: 181613421 | X9: 176474070 | Y9: 184523191 | Z9: 188173308 | AA9: 182658540 | AB9: 181372484 | AC9: 191136985 | AD9: 184673556 | AE9: 189343907 | AF9: 183707360 | AG9: 184781850 | AH9: 203125223 | AI9: 199056002 | AJ9: 191009753 | AK9: 190986143 | AL9: 200624780 | AM9: 193388919
C10: =IFERROR(IF(LANG="EN",INDEX(I18N_EN,MATCH("kpi.rec.aged_30_60",I18N_KEY,0)),INDEX(I18N_FR,MATCH("kpi.rec.aged_30_60",I18N_KEY,0))),"kpi.rec.aged_30_60") | D10: 108550253 | E10: 110765082 | F10: 109193395 | G10: 108751138 | H10: 110039028 | I10: 108454050 | J10: 110466456 | K10: 111915539 | L10: 115012160 | M10: 110822489 | N10: 108008822 | O10: 111232712 | P10: 111258396 | Q10: 111185637 | R10: 110171341 | S10: 115893686 | T10: 114806144 | U10: 112493638 | V10: 110216198 | W10: 111780647 | X10: 109670201 | Y10: 110338015 | Z10: 110261812 | AA10: 121184138 | AB10: 108690120 | AC10: 116174718 | AD10: 123333770 | AE10: 123298529 | AF10: 109777540 | AG10: 117784632 | AH10: 112556017 | AI10: 113152872 | AJ10: 117709844 | AK10: 117658869 | AL10: 118197095 | AM10: 110581346
C11: =IFERROR(IF(LANG="EN",INDEX(I18N_EN,MATCH("kpi.rec.aged_60_90",I18N_KEY,0)),INDEX(I18N_FR,MATCH("kpi.rec.aged_60_90",I18N_KEY,0))),"kpi.rec.aged_60_90") | D11: 70386245 | E11: 69678240 | F11: 69255412 | G11: 69239427 | H11: 71682043 | I11: 71531905 | J11: 71445015 | K11: 71157436 | L11: 70636251 | M11: 71219063 | N11: 71394960 | O11: 73304392 | P11: 72273684 | Q11: 72379882 | R11: 75142036 | S11: 70869042 | T11: 75688264 | U11: 75651951 | V11: 68457017 | W11: 70267868 | X11: 71645972 | Y11: 72446679 | Z11: 77042300 | AA11: 71145663 | AB11: 67736393 | AC11: 71409486 | AD11: 69999000 | AE11: 76030078 | AF11: 74772953 | AG11: 78143019 | AH11: 76966664 | AI11: 68449465 | AJ11: 68158913 | AK11: 70266074 | AL11: 69406139 | AM11: 78323891
C12: =IFERROR(IF(LANG="EN",INDEX(I18N_EN,MATCH("kpi.rec.aged_90p",I18N_KEY,0)),INDEX(I18N_FR,MATCH("kpi.rec.aged_90p",I18N_KEY,0))),"kpi.rec.aged_90p") | D12: 60534918 | E12: 60287047 | F12: 59252711 | G12: 59400795 | H12: 60219192 | I12: 61594454 | J12: 59207238 | K12: 61106803 | L12: 60326024 | M12: 58808372 | N12: 61960293 | O12: 60743638 | P12: 60998592 | Q12: 61169866 | R12: 60599209 | S12: 62201183 | T12: 61568342 | U12: 59152089 | V12: 58952636 | W12: 61838800 | X12: 58900756 | Y12: 61025435 | Z12: 59863154 | AA12: 58770612 | AB12: 64485475 | AC12: 62152726 | AD12: 58195819 | AE12: 65691317 | AF12: 62160595 | AG12: 65117660 | AH12: 57521279 | AI12: 59206431 | AJ12: 66476497 | AK12: 66612596 | AL12: 62497468 | AM12: 67337932
C13: =IFERROR(IF(LANG="EN",INDEX(I18N_EN,MATCH("kpi.rec.dso",I18N_KEY,0)),INDEX(I18N_FR,MATCH("kpi.rec.dso",I18N_KEY,0))),"kpi.rec.dso") | D13: 51.83 | E13: 51.98 | F13: 53.21 | G13: 52.49 | H13: 52.57 | I13: 52.28 | J13: 51.95 | K13: 53.05 | L13: 50.9 | M13: 50.97 | N13: 53.35 | O13: 53.59 | P13: 51.67 | Q13: 53.01 | R13: 53.17 | S13: 54.33 | T13: 55.25 | U13: 50.2 | V13: 50.23 | W13: 54.39 | X13: 51.3 | Y13: 52.4 | Z13: 52.54 | AA13: 50.69 | AB13: 52.94 | AC13: 55.2 | AD13: 55.05 | AE13: 52.15 | AF13: 51.45 | AG13: 51.34 | AH13: 51.25 | AI13: 58.66 | AJ13: 55.42 | AK13: 55.39 | AL13: 59.34 | AM13: 57.2
C14: =IFERROR(IF(LANG="EN",INDEX(I18N_EN,MATCH("kpi.rec.recovery",I18N_KEY,0)),INDEX(I18N_FR,MATCH("kpi.rec.recovery",I18N_KEY,0))),"kpi.rec.recovery") | D14: 0.8479 | E14: 0.8694 | F14: 0.8742 | G14: 0.8679 | H14: 0.8852 | I14: 0.8838 | J14: 0.8565 | K14: 0.8495 | L14: 0.8901 | M14: 0.8724 | N14: 0.8727 | O14: 0.867 | P14: 0.8937 | Q14: 0.8651 | R14: 0.8947 | S14: 0.8896 | T14: 0.8822 | U14: 0.8554 | V14: 0.9098 | W14: 0.9293 | X14: 0.8629 | Y14: 0.8696 | Z14: 0.9021 | AA14: 0.8759 | AB14: 0.8647 | AC14: 0.8922 | AD14: 0.8572 | AE14: 0.9008 | AF14: 0.947 | AG14: 0.8855 | AH14: 0.8436 | AI14: 0.8766 | AJ14: 0.9089 | AK14: 0.8383 | AL14: 0.8932 | AM14: 0.9082
C15: =IFERROR(IF(LANG="EN",INDEX(I18N_EN,MATCH("kpi.rec.collected",I18N_KEY,0)),INDEX(I18N_FR,MATCH("kpi.rec.collected",I18N_KEY,0))),"kpi.rec.collected") | D15: 217864475 | E15: 224823845 | F15: 220902073 | G15: 222287409 | H15: 221532781 | I15: 225166703 | J15: 223451470 | K15: 214214491 | L15: 229918726 | M15: 227057992 | N15: 225055896 | O15: 221566342 | P15: 216416927 | Q15: 223050401 | R15: 228360254 | S15: 224290683 | T15: 215558895 | U15: 215169290 | V15: 224761666 | W15: 217193818 | X15: 233355676 | Y15: 233959761 | Z15: 212659779 | AA15: 218553820 | AB15: 235005783 | AC15: 223499599 | AD15: 225671887 | AE15: 242713168 | AF15: 238339496 | AG15: 237871379 | AH15: 235641471 | AI15: 225501376 | AJ15: 207883442 | AK15: 216737295 | AL15: 230363336 | AM15: 237047742
C16: =IFERROR(IF(LANG="EN",INDEX(I18N_EN,MATCH("kpi.rec.billed",I18N_KEY,0)),INDEX(I18N_FR,MATCH("kpi.rec.billed",I18N_KEY,0))),"kpi.rec.billed") | D16: 255287224 | E16: 251754172 | F16: 260754423 | G16: 251360691 | H16: 258317165 | I16: 260378500 | J16: 257475358 | K16: 260364730 | L16: 261501874 | M16: 260030749 | N16: 249035225 | O16: 258260719 | P16: 261477816 | Q16: 259155411 | R16: 257737467 | S16: 265371948 | T16: 267334785 | U16: 263088925 | V16: 260119976 | W16: 273460879 | X16: 265460068 | Y16: 260738183 | Z16: 261242334 | AA16: 277468008 | AB16: 271665896 | AC16: 250224454 | AD16: 277937169 | AE16: 244864949 | AF16: 275202217 | AG16: 273821551 | AH16: 243682217 | AI16: 256203183 | AJ16: 252173252 | AK16: 251467645 | AL16: 269159741 | AM16: 242099283
C17: =IFERROR(IF(LANG="EN",INDEX(I18N_EN,MATCH("kpi.rec.dunning",I18N_KEY,0)),INDEX(I18N_FR,MATCH("kpi.rec.dunning",I18N_KEY,0))),"kpi.rec.dunning") | D17: 321 | E17: 319 | F17: 319 | G17: 324 | H17: 331 | I17: 319 | J17: 317 | K17: 321 | L17: 316 | M17: 323 | N17: 314 | O17: 322 | P17: 324 | Q17: 314 | R17: 336 | S17: 334 | T17: 320 | U17: 342 | V17: 339 | W17: 328 | X17: 316 | Y17: 353 | Z17: 324 | AA17: 331 | AB17: 318 | AC17: 345 | AD17: 314 | AE17: 337 | AF17: 343 | AG17: 357 | AH17: 344 | AI17: 325 | AJ17: 357 | AK17: 330 | AL17: 341 | AM17: 349
C18: =IFERROR(IF(LANG="EN",INDEX(I18N_EN,MATCH("kpi.rec.promises",I18N_KEY,0)),INDEX(I18N_FR,MATCH("kpi.rec.promises",I18N_KEY,0))),"kpi.rec.promises") | D18: 93381068 | E18: 95323186 | F18: 95188859 | G18: 96820275 | H18: 96742369 | I18: 96800200 | J18: 96459579 | K18: 95394957 | L18: 96219189 | M18: 95207955 | N18: 99656838 | O18: 96853626 | P18: 99398115 | Q18: 92393357 | R18: 97052571 | S18: 97977258 | T18: 96286786 | U18: 100157114 | V18: 96858285 | W18: 91172062 | X18: 98556585 | Y18: 95147760 | Z18: 92991475 | AA18: 96449820 | AB18: 97944111 | AC18: 98301381 | AD18: 95213612 | AE18: 101748049 | AF18: 104669822 | AG18: 100448939 | AH18: 105978963 | AI18: 92437172 | AJ18: 102124677 | AK18: 94314135 | AL18: 94323987 | AM18: 96671485
C19: =IFERROR(IF(LANG="EN",INDEX(I18N_EN,MATCH("kpi.rec.promise_kept",I18N_KEY,0)),INDEX(I18N_FR,MATCH("kpi.rec.promise_kept",I18N_KEY,0))),"kpi.rec.promise_kept") | D19: 0.7113 | E19: 0.7182 | F19: 0.7153 | G19: 0.7351 | H19: 0.7054 | I19: 0.7238 | J19: 0.7207 | K19: 0.7308 | L19: 0.7331 | M19: 0.7361 | N19: 0.7295 | O19: 0.7503 | P19: 0.7538 | Q19: 0.7258 | R19: 0.6999 | S19: 0.7062 | T19: 0.7212 | U19: 0.7359 | V19: 0.7083 | W19: 0.7189 | X19: 0.7607 | Y19: 0.7864 | Z19: 0.7313 | AA19: 0.7247 | AB19: 0.6965 | AC19: 0.6848 | AD19: 0.7938 | AE19: 0.7482 | AF19: 0.7676 | AG19: 0.7901 | AH19: 0.6858 | AI19: 0.7792 | AJ19: 0.7244 | AK19: 0.7077 | AL19: 0.7966 | AM19: 0.752
C20: =IFERROR(IF(LANG="EN",INDEX(I18N_EN,MATCH("kpi.rec.collected_dun",I18N_KEY,0)),INDEX(I18N_FR,MATCH("kpi.rec.collected_dun",I18N_KEY,0))),"kpi.rec.collected_dun") | D20: 60660271 | E20: 59877022 | F20: 59292513 | G20: 60593628 | H20: 60060349 | I20: 61597636 | J20: 61296495 | K20: 60115942 | L20: 61408223 | M20: 62957157 | N20: 60700930 | O20: 60915970 | P20: 62214323 | Q20: 58759682 | R20: 59088437 | S20: 58661512 | T20: 60263568 | U20: 60919024 | V20: 59684366 | W20: 65125967 | X20: 61972307 | Y20: 65817617 | Z20: 66226394 | AA20: 63970393 | AB20: 64468674 | AC20: 64743169 | AD20: 64982385 | AE20: 62402525 | AF20: 59973825 | AG20: 62329081 | AH20: 65504714 | AI20: 62290833 | AJ20: 67215858 | AK20: 67508369 | AL20: 57772468 | AM20: 66346925
C21: =IFERROR(IF(LANG="EN",INDEX(I18N_EN,MATCH("kpi.rec.provision",I18N_KEY,0)),INDEX(I18N_FR,MATCH("kpi.rec.provision",I18N_KEY,0))),"kpi.rec.provision") | D21: 0.0906 | E21: 0.0885 | F21: 0.0893 | G21: 0.0892 | H21: 0.0912 | I21: 0.0905 | J21: 0.0909 | K21: 0.091 | L21: 0.0877 | M21: 0.0923 | N21: 0.0906 | O21: 0.0893 | P21: 0.0933 | Q21: 0.0916 | R21: 0.0917 | S21: 0.0945 | T21: 0.0924 | U21: 0.0925 | V21: 0.0888 | W21: 0.0913 | X21: 0.0904 | Y21: 0.0931 | Z21: 0.0912 | AA21: 0.0904 | AB21: 0.0877 | AC21: 0.099 | AD21: 0.091 | AE21: 0.0871 | AF21: 0.0955 | AG21: 0.0923 | AH21: 0.0892 | AI21: 0.0967 | AJ21: 0.1009 | AK21: 0.093 | AL21: 0.0968 | AM21: 0.099
C22: =IFERROR(IF(LANG="EN",INDEX(I18N_EN,MATCH("kpi.rec.litige_count",I18N_KEY,0)),INDEX(I18N_FR,MATCH("kpi.rec.litige_count",I18N_KEY,0))),"kpi.rec.litige_count") | D22: 14 | E22: 14 | F22: 14 | G22: 14 | H22: 14 | I22: 14 | J22: 14 | K22: 14 | L22: 14 | M22: 15 | N22: 14 | O22: 14 | P22: 14 | Q22: 14 | R22: 15 | S22: 14 | T22: 14 | U22: 15 | V22: 15 | W22: 15 | X22: 14 | Y22: 15 | Z22: 15 | AA22: 14 | AB22: 13 | AC22: 15 | AD22: 15 | AE22: 14 | AF22: 14 | AG22: 15 | AH22: 14 | AI22: 14 | AJ22: 15 | AK22: 15 | AL22: 15 | AM22: 15
C23: =IFERROR(IF(LANG="EN",INDEX(I18N_EN,MATCH("kpi.rec.litige_amount",I18N_KEY,0)),INDEX(I18N_FR,MATCH("kpi.rec.litige_amount",I18N_KEY,0))),"kpi.rec.litige_amount") | D23: 83496880 | E23: 84697690 | F23: 85567591 | G23: 85908152 | H23: 84659385 | I23: 86797143 | J23: 86289139 | K23: 86890374 | L23: 85696934 | M23: 85417832 | N23: 86404952 | O23: 86185739 | P23: 87471877 | Q23: 84546634 | R23: 85783269 | S23: 86019434 | T23: 87167239 | U23: 85139159 | V23: 83965271 | W23: 88439644 | X23: 85964028 | Y23: 90383346 | Z23: 86971843 | AA23: 85349747 | AB23: 92261282 | AC23: 93880486 | AD23: 86533019 | AE23: 87929315 | AF23: 83853924 | AG23: 86736780 | AH23: 93409483 | AI23: 94983554 | AJ23: 94477756 | AK23: 87707496 | AL23: 94236288 | AM23: 88479649
C24: =IFERROR(IF(LANG="EN",INDEX(I18N_EN,MATCH("kpi.rec.litige_resolved",I18N_KEY,0)),INDEX(I18N_FR,MATCH("kpi.rec.litige_resolved",I18N_KEY,0))),"kpi.rec.litige_resolved") | D24: 0.5514 | E24: 0.5529 | F24: 0.5534 | G24: 0.5583 | H24: 0.5581 | I24: 0.5524 | J24: 0.5434 | K24: 0.5462 | L24: 0.5731 | M24: 0.5589 | N24: 0.5705 | O24: 0.5578 | P24: 0.5548 | Q24: 0.5502 | R24: 0.5875 | S24: 0.5519 | T24: 0.583 | U24: 0.5713 | V24: 0.5819 | W24: 0.5327 | X24: 0.5765 | Y24: 0.5695 | Z24: 0.5936 | AA24: 0.5467 | AB24: 0.596 | AC24: 0.5841 | AD24: 0.5424 | AE24: 0.5521 | AF24: 0.5719 | AG24: 0.5414 | AH24: 0.5655 | AI24: 0.6132 | AJ24: 0.5507 | AK24: 0.529 | AL24: 0.6038 | AM24: 0.589
C25: =IFERROR(IF(LANG="EN",INDEX(I18N_EN,MATCH("kpi.rec.litige_age",I18N_KEY,0)),INDEX(I18N_FR,MATCH("kpi.rec.litige_age",I18N_KEY,0))),"kpi.rec.litige_age") | D25: 6.95 | E25: 6.92 | F25: 7.01 | G25: 6.98 | H25: 6.99 | I25: 7.02 | J25: 7.05 | K25: 7.14 | L25: 6.83 | M25: 7.34 | N25: 7.04 | O25: 7.09 | P25: 7.21 | Q25: 7.09 | R25: 6.75 | S25: 7.38 | T25: 7.04 | U25: 7.35 | V25: 6.84 | W25: 6.96 | X25: 7.43 | Y25: 6.87 | Z25: 6.85 | AA25: 6.88 | AB25: 7.48 | AC25: 7.3 | AD25: 7.02 | AE25: 7.2 | AF25: 6.93 | AG25: 7.05 | AH25: 7.37 | AI25: 7.77 | AJ25: 8.03 | AK25: 7.16 | AL25: 7.43 | AM25: 7.32
C27: 💬 Commentaires (KPI × mois)
C28: =IFERROR(IF(LANG="EN",INDEX(I18N_EN,MATCH("kpi.rec.ar",I18N_KEY,0)),INDEX(I18N_FR,MATCH("kpi.rec.ar",I18N_KEY,0))),"kpi.rec.ar")
C29: =IFERROR(IF(LANG="EN",INDEX(I18N_EN,MATCH("kpi.rec.aged_0_30",I18N_KEY,0)),INDEX(I18N_FR,MATCH("kpi.rec.aged_0_30",I18N_KEY,0))),"kpi.rec.aged_0_30")
C30: =IFERROR(IF(LANG="EN",INDEX(I18N_EN,MATCH("kpi.rec.aged_30_60",I18N_KEY,0)),INDEX(I18N_FR,MATCH("kpi.rec.aged_30_60",I18N_KEY,0))),"kpi.rec.aged_30_60")
C31: =IFERROR(IF(LANG="EN",INDEX(I18N_EN,MATCH("kpi.rec.aged_60_90",I18N_KEY,0)),INDEX(I18N_FR,MATCH("kpi.rec.aged_60_90",I18N_KEY,0))),"kpi.rec.aged_60_90")
C32: =IFERROR(IF(LANG="EN",INDEX(I18N_EN,MATCH("kpi.rec.aged_90p",I18N_KEY,0)),INDEX(I18N_FR,MATCH("kpi.rec.aged_90p",I18N_KEY,0))),"kpi.rec.aged_90p")
C33: =IFERROR(IF(LANG="EN",INDEX(I18N_EN,MATCH("kpi.rec.dso",I18N_KEY,0)),INDEX(I18N_FR,MATCH("kpi.rec.dso",I18N_KEY,0))),"kpi.rec.dso")
C34: =IFERROR(IF(LANG="EN",INDEX(I18N_EN,MATCH("kpi.rec.recovery",I18N_KEY,0)),INDEX(I18N_FR,MATCH("kpi.rec.recovery",I18N_KEY,0))),"kpi.rec.recovery")
C35: =IFERROR(IF(LANG="EN",INDEX(I18N_EN,MATCH("kpi.rec.collected",I18N_KEY,0)),INDEX(I18N_FR,MATCH("kpi.rec.collected",I18N_KEY,0))),"kpi.rec.collected")
C36: =IFERROR(IF(LANG="EN",INDEX(I18N_EN,MATCH("kpi.rec.billed",I18N_KEY,0)),INDEX(I18N_FR,MATCH("kpi.rec.billed",I18N_KEY,0))),"kpi.rec.billed")
C37: =IFERROR(IF(LANG="EN",INDEX(I18N_EN,MATCH("kpi.rec.dunning",I18N_KEY,0)),INDEX(I18N_FR,MATCH("kpi.rec.dunning",I18N_KEY,0))),"kpi.rec.dunning")
C38: =IFERROR(IF(LANG="EN",INDEX(I18N_EN,MATCH("kpi.rec.promises",I18N_KEY,0)),INDEX(I18N_FR,MATCH("kpi.rec.promises",I18N_KEY,0))),"kpi.rec.promises")
C39: =IFERROR(IF(LANG="EN",INDEX(I18N_EN,MATCH("kpi.rec.promise_kept",I18N_KEY,0)),INDEX(I18N_FR,MATCH("kpi.rec.promise_kept",I18N_KEY,0))),"kpi.rec.promise_kept")
C40: =IFERROR(IF(LANG="EN",INDEX(I18N_EN,MATCH("kpi.rec.collected_dun",I18N_KEY,0)),INDEX(I18N_FR,MATCH("kpi.rec.collected_dun",I18N_KEY,0))),"kpi.rec.collected_dun")
C41: =IFERROR(IF(LANG="EN",INDEX(I18N_EN,MATCH("kpi.rec.provision",I18N_KEY,0)),INDEX(I18N_FR,MATCH("kpi.rec.provision",I18N_KEY,0))),"kpi.rec.provision")
C42: =IFERROR(IF(LANG="EN",INDEX(I18N_EN,MATCH("kpi.rec.litige_count",I18N_KEY,0)),INDEX(I18N_FR,MATCH("kpi.rec.litige_count",I18N_KEY,0))),"kpi.rec.litige_count")
C43: =IFERROR(IF(LANG="EN",INDEX(I18N_EN,MATCH("kpi.rec.litige_amount",I18N_KEY,0)),INDEX(I18N_FR,MATCH("kpi.rec.litige_amount",I18N_KEY,0))),"kpi.rec.litige_amount")
C44: =IFERROR(IF(LANG="EN",INDEX(I18N_EN,MATCH("kpi.rec.litige_resolved",I18N_KEY,0)),INDEX(I18N_FR,MATCH("kpi.rec.litige_resolved",I18N_KEY,0))),"kpi.rec.litige_resolved")
C45: =IFERROR(IF(LANG="EN",INDEX(I18N_EN,MATCH("kpi.rec.litige_age",I18N_KEY,0)),INDEX(I18N_FR,MATCH("kpi.rec.litige_age",I18N_KEY,0))),"kpi.rec.litige_age")

Sheet C4 · Footfall
C1: ="▌ "&IFERROR(IF(LANG="EN",INDEX(I18N_EN,MATCH("msg.collect",I18N_KEY,0)),INDEX(I18N_FR,MATCH("msg.collect",I18N_KEY,0))),"msg.collect")&" · "&IFERROR(IF(LANG="EN",INDEX(I18N_EN,MATCH("dept.foot",I18N_KEY,0)),INDEX(I18N_FR,MATCH("dept.foot",I18N_KEY,0))),"dept.foot")
C2: =IFERROR(IF(LANG="EN",INDEX(I18N_EN,MATCH("msg.help",I18N_KEY,0)),INDEX(I18N_FR,MATCH("msg.help",I18N_KEY,0))),"msg.help")
C6: KPI \ Mois | D6: =DATE(2024,1,1) | E6: =DATE(2024,2,1) | F6: =DATE(2024,3,1) | G6: =DATE(2024,4,1) | H6: =DATE(2024,5,1) | I6: =DATE(2024,6,1) | J6: =DATE(2024,7,1) | K6: =DATE(2024,8,1) | L6: =DATE(2024,9,1) | M6: =DATE(2024,10,1) | N6: =DATE(2024,11,1) | O6: =DATE(2024,12,1) | P6: =DATE(2025,1,1) | Q6: =DATE(2025,2,1) | R6: =DATE(2025,3,1) | S6: =DATE(2025,4,1) | T6: =DATE(2025,5,1) | U6: =DATE(2025,6,1) | V6: =DATE(2025,7,1) | W6: =DATE(2025,8,1) | X6: =DATE(2025,9,1) | Y6: =DATE(2025,10,1) | Z6: =DATE(2025,11,1) | AA6: =DATE(2025,12,1) | AB6: =DATE(2026,1,1) | AC6: =DATE(2026,2,1) | AD6: =DATE(2026,3,1) | AE6: =DATE(2026,4,1) | AF6: =DATE(2026,5,1) | AG6: =DATE(2026,6,1) | AH6: =DATE(2026,7,1) | AI6: =DATE(2026,8,1) | AJ6: =DATE(2026,9,1) | AK6: =DATE(2026,10,1) | AL6: =DATE(2026,11,1) | AM6: =DATE(2026,12,1)
C8: =IFERROR(IF(LANG="EN",INDEX(I18N_EN,MATCH("kpi.foot.total",I18N_KEY,0)),INDEX(I18N_FR,MATCH("kpi.foot.total",I18N_KEY,0))),"kpi.foot.total") | D8: 476522 | E8: 487514 | F8: 474424 | G8: 486667 | H8: 495263 | I8: 482251 | J8: 482213 | K8: 498884 | L8: 485272 | M8: 485898 | N8: 492226 | O8: 504406 | P8: 479344 | Q8: 503627 | R8: 496438 | S8: 507130 | T8: 494975 | U8: 486490 | V8: 511035 | W8: 482894 | X8: 466103 | Y8: 478711 | Z8: 472979 | AA8: 469843 | AB8: 518778 | AC8: 517364 | AD8: 465397 | AE8: 534681 | AF8: 532735 | AG8: 534093 | AH8: 534931 | AI8: 463527 | AJ8: 463458 | AK8: 548845 | AL8: 549139 | AM8: 481723
C9: =IFERROR(IF(LANG="EN",INDEX(I18N_EN,MATCH("kpi.foot.vs_budget",I18N_KEY,0)),INDEX(I18N_FR,MATCH("kpi.foot.vs_budget",I18N_KEY,0))),"kpi.foot.vs_budget") | D9: 0.9866 | E9: 0.9622 | F9: 0.9612 | G9: 0.9783 | H9: 0.9762 | I9: 1.0068 | J9: 0.9939 | K9: 0.9796 | L9: 1.002 | M9: 0.995 | N9: 1.0044 | O9: 0.9729 | P9: 0.9879 | Q9: 0.979 | R9: 0.9656 | S9: 1.0174 | T9: 0.9783 | U9: 0.9532 | V9: 0.9555 | W9: 0.9394 | X9: 1.0417 | Y9: 1.0436 | Z9: 0.9875 | AA9: 0.9503 | AB9: 1.0575 | AC9: 1.0175 | AD9: 0.958 | AE9: 0.9697 | AF9: 1.0624 | AG9: 0.9523 | AH9: 1.052 | AI9: 1.0656 | AJ9: 1.0354 | AK9: 0.9944 | AL9: 1.0875 | AM9: 1.0808
C10: =IFERROR(IF(LANG="EN",INDEX(I18N_EN,MATCH("kpi.foot.per_sqm",I18N_KEY,0)),INDEX(I18N_FR,MATCH("kpi.foot.per_sqm",I18N_KEY,0))),"kpi.foot.per_sqm") | D10: 11.86 | E10: 12.09 | F10: 12.18 | G10: 11.9 | H10: 11.78 | I10: 12.27 | J10: 11.89 | K10: 11.99 | L10: 12.27 | M10: 11.74 | N10: 11.85 | O10: 12.04 | P10: 12 | Q10: 12.29 | R10: 11.87 | S10: 12.12 | T10: 12.1 | U10: 12 | V10: 11.86 | W10: 11.88 | X10: 12.37 | Y10: 12.15 | Z10: 13.13 | AA10: 12.64 | AB10: 12.9 | AC10: 12.67 | AD10: 12.58 | AE10: 12.22 | AF10: 13.36 | AG10: 12.69 | AH10: 13.22 | AI10: 12.6 | AJ10: 12.96 | AK10: 13.89 | AL10: 13.12 | AM10: 12.65
C11: =IFERROR(IF(LANG="EN",INDEX(I18N_EN,MATCH("kpi.foot.conversion",I18N_KEY,0)),INDEX(I18N_FR,MATCH("kpi.foot.conversion",I18N_KEY,0))),"kpi.foot.conversion") | D11: 0.2244 | E11: 0.2234 | F11: 0.2236 | G11: 0.2187 | H11: 0.2198 | I11: 0.2185 | J11: 0.2249 | K11: 0.2258 | L11: 0.222 | M11: 0.2188 | N11: 0.2265 | O11: 0.2333 | P11: 0.2212 | Q11: 0.2209 | R11: 0.2209 | S11: 0.2224 | T11: 0.2231 | U11: 0.2174 | V11: 0.2298 | W11: 0.2184 | X11: 0.2197 | Y11: 0.2368 | Z11: 0.2337 | AA11: 0.2347 | AB11: 0.2208 | AC11: 0.2305 | AD11: 0.237 | AE11: 0.2441 | AF11: 0.2382 | AG11: 0.2274 | AH11: 0.2151 | AI11: 0.2445 | AJ11: 0.2437 | AK11: 0.2438 | AL11: 0.2144 | AM11: 0.2281
C12: =IFERROR(IF(LANG="EN",INDEX(I18N_EN,MATCH("kpi.foot.dwell",I18N_KEY,0)),INDEX(I18N_FR,MATCH("kpi.foot.dwell",I18N_KEY,0))),"kpi.foot.dwell") | D12: 47.71 | E12: 46.36 | F12: 47.95 | G12: 46.92 | H12: 48.1 | I12: 47.64 | J12: 47.67 | K12: 45.88 | L12: 47.44 | M12: 47.52 | N12: 47.62 | O12: 47.49 | P12: 48.96 | Q12: 46.91 | R12: 46.81 | S12: 50.55 | T12: 49.04 | U12: 46.92 | V12: 46.42 | W12: 48.72 | X12: 50.83 | Y12: 48.06 | Z12: 47.59 | AA12: 48.22 | AB12: 49.39 | AC12: 47.56 | AD12: 46.95 | AE12: 50.71 | AF12: 47.36 | AG12: 49.34 | AH12: 51.54 | AI12: 50.51 | AJ12: 46.68 | AK12: 46.27 | AL12: 51.25 | AM12: 47.5
C13: =IFERROR(IF(LANG="EN",INDEX(I18N_EN,MATCH("kpi.foot.peak_share",I18N_KEY,0)),INDEX(I18N_FR,MATCH("kpi.foot.peak_share",I18N_KEY,0))),"kpi.foot.peak_share") | D13: 0.1786 | E13: 0.1818 | F13: 0.1835 | G13: 0.1824 | H13: 0.183 | I13: 0.1835 | J13: 0.1829 | K13: 0.1804 | L13: 0.1797 | M13: 0.1807 | N13: 0.1829 | O13: 0.1853 | P13: 0.1893 | Q13: 0.1859 | R13: 0.1912 | S13: 0.176 | T13: 0.1763 | U13: 0.1917 | V13: 0.1801 | W13: 0.1787 | X13: 0.1839 | Y13: 0.1833 | Z13: 0.1801 | AA13: 0.1836 | AB13: 0.1881 | AC13: 0.1918 | AD13: 0.178 | AE13: 0.1896 | AF13: 0.1823 | AG13: 0.1767 | AH13: 0.1744 | AI13: 0.1856 | AJ13: 0.2013 | AK13: 0.1838 | AL13: 0.1984 | AM13: 0.1914
C14: =IFERROR(IF(LANG="EN",INDEX(I18N_EN,MATCH("kpi.foot.weekend_share",I18N_KEY,0)),INDEX(I18N_FR,MATCH("kpi.foot.weekend_share",I18N_KEY,0))),"kpi.foot.weekend_share") | D14: 0.4117 | E14: 0.4244 | F14: 0.4241 | G14: 0.4262 | H14: 0.4204 | I14: 0.423 | J14: 0.4283 | K14: 0.4114 | L14: 0.4142 | M14: 0.4272 | N14: 0.4215 | O14: 0.4257 | P14: 0.4302 | Q14: 0.4143 | R14: 0.4258 | S14: 0.4373 | T14: 0.4254 | U14: 0.4314 | V14: 0.4559 | W14: 0.431 | X14: 0.42 | Y14: 0.4622 | Z14: 0.4235 | AA14: 0.4401 | AB14: 0.4494 | AC14: 0.4129 | AD14: 0.4372 | AE14: 0.4565 | AF14: 0.4316 | AG14: 0.4746 | AH14: 0.441 | AI14: 0.4513 | AJ14: 0.4308 | AK14: 0.4319 | AL14: 0.4585 | AM14: 0.427
C16: 💬 Commentaires (KPI × mois)
C17: =IFERROR(IF(LANG="EN",INDEX(I18N_EN,MATCH("kpi.foot.total",I18N_KEY,0)),INDEX(I18N_FR,MATCH("kpi.foot.total",I18N_KEY,0))),"kpi.foot.total")
C18: =IFERROR(IF(LANG="EN",INDEX(I18N_EN,MATCH("kpi.foot.vs_budget",I18N_KEY,0)),INDEX(I18N_FR,MATCH("kpi.foot.vs_budget",I18N_KEY,0))),"kpi.foot.vs_budget")
C19: =IFERROR(IF(LANG="EN",INDEX(I18N_EN,MATCH("kpi.foot.per_sqm",I18N_KEY,0)),INDEX(I18N_FR,MATCH("kpi.foot.per_sqm",I18N_KEY,0))),"kpi.foot.per_sqm")
C20: =IFERROR(IF(LANG="EN",INDEX(I18N_EN,MATCH("kpi.foot.conversion",I18N_KEY,0)),INDEX(I18N_FR,MATCH("kpi.foot.conversion",I18N_KEY,0))),"kpi.foot.conversion")
C21: =IFERROR(IF(LANG="EN",INDEX(I18N_EN,MATCH("kpi.foot.dwell",I18N_KEY,0)),INDEX(I18N_FR,MATCH("kpi.foot.dwell",I18N_KEY,0))),"kpi.foot.dwell")
C22: =IFERROR(IF(LANG="EN",INDEX(I18N_EN,MATCH("kpi.foot.peak_share",I18N_KEY,0)),INDEX(I18N_FR,MATCH("kpi.foot.peak_share",I18N_KEY,0))),"kpi.foot.peak_share")
C23: =IFERROR(IF(LANG="EN",INDEX(I18N_EN,MATCH("kpi.foot.weekend_share",I18N_KEY,0)),INDEX(I18N_FR,MATCH("kpi.foot.weekend_share",I18N_KEY,0))),"kpi.foot.weekend_share")

Sheet C5 · Marketing
C1: ="▌ "&IFERROR(IF(LANG="EN",INDEX(I18N_EN,MATCH("msg.collect",I18N_KEY,0)),INDEX(I18N_FR,MATCH("msg.collect",I18N_KEY,0))),"msg.collect")&" · "&IFERROR(IF(LANG="EN",INDEX(I18N_EN,MATCH("dept.mkt",I18N_KEY,0)),INDEX(I18N_FR,MATCH("dept.mkt",I18N_KEY,0))),"dept.mkt")
C2: =IFERROR(IF(LANG="EN",INDEX(I18N_EN,MATCH("msg.help",I18N_KEY,0)),INDEX(I18N_FR,MATCH("msg.help",I18N_KEY,0))),"msg.help")
C6: KPI \ Mois | D6: =DATE(2024,1,1) | E6: =DATE(2024,2,1) | F6: =DATE(2024,3,1) | G6: =DATE(2024,4,1) | H6: =DATE(2024,5,1) | I6: =DATE(2024,6,1) | J6: =DATE(2024,7,1) | K6: =DATE(2024,8,1) | L6: =DATE(2024,9,1) | M6: =DATE(2024,10,1) | N6: =DATE(2024,11,1) | O6: =DATE(2024,12,1) | P6: =DATE(2025,1,1) | Q6: =DATE(2025,2,1) | R6: =DATE(2025,3,1) | S6: =DATE(2025,4,1) | T6: =DATE(2025,5,1) | U6: =DATE(2025,6,1) | V6: =DATE(2025,7,1) | W6: =DATE(2025,8,1) | X6: =DATE(2025,9,1) | Y6: =DATE(2025,10,1) | Z6: =DATE(2025,11,1) | AA6: =DATE(2025,12,1) | AB6: =DATE(2026,1,1) | AC6: =DATE(2026,2,1) | AD6: =DATE(2026,3,1) | AE6: =DATE(2026,4,1) | AF6: =DATE(2026,5,1) | AG6: =DATE(2026,6,1) | AH6: =DATE(2026,7,1) | AI6: =DATE(2026,8,1) | AJ6: =DATE(2026,9,1) | AK6: =DATE(2026,10,1) | AL6: =DATE(2026,11,1) | AM6: =DATE(2026,12,1)
C8: =IFERROR(IF(LANG="EN",INDEX(I18N_EN,MATCH("kpi.mkt.events",I18N_KEY,0)),INDEX(I18N_FR,MATCH("kpi.mkt.events",I18N_KEY,0))),"kpi.mkt.events") | D8: 4 | E8: 4 | F8: 4 | G8: 4 | H8: 4 | I8: 4 | J8: 4 | K8: 4 | L8: 4 | M8: 4 | N8: 4 | O8: 4 | P8: 4 | Q8: 4 | R8: 4 | S8: 4 | T8: 4 | U8: 4 | V8: 4 | W8: 4 | X8: 4 | Y8: 4 | Z8: 4 | AA8: 4 | AB8: 4 | AC8: 4 | AD8: 4 | AE8: 4 | AF8: 4 | AG8: 4 | AH8: 4 | AI8: 4 | AJ8: 4 | AK8: 4 | AL8: 4 | AM8: 4
C9: =IFERROR(IF(LANG="EN",INDEX(I18N_EN,MATCH("kpi.mkt.event_att",I18N_KEY,0)),INDEX(I18N_FR,MATCH("kpi.mkt.event_att",I18N_KEY,0))),"kpi.mkt.event_att") | D9: 12086 | E9: 11938 | F9: 11789 | G9: 12252 | H9: 12021 | I9: 12044 | J9: 11848 | K9: 11916 | L9: 12335 | M9: 12356 | N9: 12445 | O9: 12239 | P9: 12321 | Q9: 11940 | R9: 11925 | S9: 12383 | T9: 12674 | U9: 12646 | V9: 12321 | W9: 12949 | X9: 12645 | Y9: 12224 | Z9: 12871 | AA9: 12026 | AB9: 12125 | AC9: 12503 | AD9: 12524 | AE9: 12182 | AF9: 12549 | AG9: 11665 | AH9: 12392 | AI9: 11712 | AJ9: 12716 | AK9: 12444 | AL9: 13199 | AM9: 12058
C10: =IFERROR(IF(LANG="EN",INDEX(I18N_EN,MATCH("kpi.mkt.event_roi",I18N_KEY,0)),INDEX(I18N_FR,MATCH("kpi.mkt.event_roi",I18N_KEY,0))),"kpi.mkt.event_roi") | D10: 1.3 | E10: 1.3 | F10: 1.3 | G10: 1.3 | H10: 1.3 | I10: 1.3 | J10: 1.3 | K10: 1.3 | L10: 1.3 | M10: 1.3 | N10: 1.3 | O10: 1.3 | P10: 1.3 | Q10: 1.3 | R10: 1.3 | S10: 1.3 | T10: 1.3 | U10: 1.3 | V10: 1.3 | W10: 1.3 | X10: 1.3 | Y10: 1.3 | Z10: 1.3 | AA10: 1.3 | AB10: 1.3 | AC10: 1.3 | AD10: 1.3 | AE10: 1.3 | AF10: 1.3 | AG10: 1.3 | AH10: 1.3 | AI10: 1.3 | AJ10: 1.3 | AK10: 1.3 | AL10: 1.3 | AM10: 1.3
C11: =IFERROR(IF(LANG="EN",INDEX(I18N_EN,MATCH("kpi.mkt.event_sat",I18N_KEY,0)),INDEX(I18N_FR,MATCH("kpi.mkt.event_sat",I18N_KEY,0))),"kpi.mkt.event_sat") | D11: 8.1 | E11: 8.15 | F11: 8.27 | G11: 8.35 | H11: 8.33 | I11: 8.25 | J11: 8.11 | K11: 8.3 | L11: 8.33 | M11: 8.52 | N11: 8.33 | O11: 8.5 | P11: 7.96 | Q11: 8.36 | R11: 8.42 | S11: 8.14 | T11: 8.7 | U11: 8.32 | V11: 8.12 | W11: 8.19 | X11: 8.78 | Y11: 8.7 | Z11: 8.28 | AA11: 8.72 | AB11: 8.81 | AC11: 8.51 | AD11: 9.02 | AE11: 8.42 | AF11: 8.24 | AG11: 9.04 | AH11: 9.15 | AI11: 8.91 | AJ11: 8.97 | AK11: 8.84 | AL11: 9.27 | AM11: 8.14
C12: =IFERROR(IF(LANG="EN",INDEX(I18N_EN,MATCH("kpi.mkt.engagement",I18N_KEY,0)),INDEX(I18N_FR,MATCH("kpi.mkt.engagement",I18N_KEY,0))),"kpi.mkt.engagement") | D12: 0.0444 | E12: 0.0448 | F12: 0.0452 | G12: 0.0451 | H12: 0.0447 | I12: 0.045 | J12: 0.0445 | K12: 0.0454 | L12: 0.046 | M12: 0.0457 | N12: 0.0458 | O12: 0.0447 | P12: 0.044 | Q12: 0.0457 | R12: 0.0453 | S12: 0.0444 | T12: 0.0451 | U12: 0.0453 | V12: 0.0472 | W12: 0.0487 | X12: 0.0441 | Y12: 0.0468 | Z12: 0.0473 | AA12: 0.0495 | AB12: 0.0462 | AC12: 0.0493 | AD12: 0.0465 | AE12: 0.0502 | AF12: 0.0464 | AG12: 0.0456 | AH12: 0.0494 | AI12: 0.0479 | AJ12: 0.0451 | AK12: 0.0466 | AL12: 0.0437 | AM12: 0.0504
C13: =IFERROR(IF(LANG="EN",INDEX(I18N_EN,MATCH("kpi.mkt.followers",I18N_KEY,0)),INDEX(I18N_FR,MATCH("kpi.mkt.followers",I18N_KEY,0))),"kpi.mkt.followers") | D13: 76764 | E13: 78761 | F13: 79506 | G13: 79902 | H13: 77806 | I13: 77941 | J13: 76175 | K13: 79879 | L13: 78309 | M13: 77685 | N13: 79486 | O13: 77398 | P13: 79965 | Q13: 80933 | R13: 80721 | S13: 78149 | T13: 77869 | U13: 77099 | V13: 81940 | W13: 79730 | X13: 80101 | Y13: 76596 | Z13: 83511 | AA13: 84169 | AB13: 83863 | AC13: 84789 | AD13: 80829 | AE13: 81825 | AF13: 74874 | AG13: 82597 | AH13: 86710 | AI13: 86144 | AJ13: 79066 | AK13: 83863 | AL13: 75779 | AM13: 86168
C14: =IFERROR(IF(LANG="EN",INDEX(I18N_EN,MATCH("kpi.mkt.reach",I18N_KEY,0)),INDEX(I18N_FR,MATCH("kpi.mkt.reach",I18N_KEY,0))),"kpi.mkt.reach") | D14: 546473 | E14: 549448 | F14: 554888 | G14: 543028 | H14: 531157 | I14: 542531 | J14: 540738 | K14: 540728 | L14: 538880 | M14: 554119 | N14: 548704 | O14: 543708 | P14: 548757 | Q14: 541112 | R14: 523926 | S14: 543862 | T14: 556536 | U14: 538963 | V14: 574072 | W14: 542174 | X14: 551614 | Y14: 570492 | Z14: 573547 | AA14: 555370 | AB14: 577977 | AC14: 516133 | AD14: 550507 | AE14: 565602 | AF14: 578155 | AG14: 567927 | AH14: 608708 | AI14: 587341 | AJ14: 543243 | AK14: 584692 | AL14: 562750 | AM14: 555900
C15: =IFERROR(IF(LANG="EN",INDEX(I18N_EN,MATCH("kpi.mkt.cpa",I18N_KEY,0)),INDEX(I18N_FR,MATCH("kpi.mkt.cpa",I18N_KEY,0))),"kpi.mkt.cpa") | D15: 3548.72 | E15: 3527.1 | F15: 3498.61 | G15: 3466.85 | H15: 3578.21 | I15: 3604.8 | J15: 3508.25 | K15: 3493.9 | L15: 3451.78 | M15: 3421.65 | N15: 3612.12 | O15: 3541.98 | P15: 3518.43 | Q15: 3547.78 | R15: 3622.14 | S15: 3642.33 | T15: 3548.53 | U15: 3618.39 | V15: 3692.17 | W15: 3584.02 | X15: 3765.19 | Y15: 3594.7 | Z15: 3601.71 | AA15: 3663.19 | AB15: 3399.89 | AC15: 3433.63 | AD15: 3436.16 | AE15: 3591.02 | AF15: 3388.51 | AG15: 3856.32 | AH15: 3635.94 | AI15: 3428.21 | AJ15: 3806.5 | AK15: 3373.76 | AL15: 3457.7 | AM15: 3362.55
C16: =IFERROR(IF(LANG="EN",INDEX(I18N_EN,MATCH("kpi.mkt.digital_conv",I18N_KEY,0)),INDEX(I18N_FR,MATCH("kpi.mkt.digital_conv",I18N_KEY,0))),"kpi.mkt.digital_conv") | D16: 0.0297 | E16: 0.0305 | F16: 0.0302 | G16: 0.0301 | H16: 0.03 | I16: 0.0298 | J16: 0.0312 | K16: 0.0303 | L16: 0.0308 | M16: 0.0305 | N16: 0.0304 | O16: 0.0307 | P16: 0.0305 | Q16: 0.0298 | R16: 0.0293 | S16: 0.0316 | T16: 0.03 | U16: 0.0295 | V16: 0.0306 | W16: 0.0317 | X16: 0.0295 | Y16: 0.0297 | Z16: 0.0327 | AA16: 0.0322 | AB16: 0.031 | AC16: 0.0292 | AD16: 0.0303 | AE16: 0.0324 | AF16: 0.0319 | AG16: 0.0328 | AH16: 0.0288 | AI16: 0.0309 | AJ16: 0.0331 | AK16: 0.0334 | AL16: 0.0299 | AM16: 0.0333
C17: =IFERROR(IF(LANG="EN",INDEX(I18N_EN,MATCH("kpi.mkt.spend",I18N_KEY,0)),INDEX(I18N_FR,MATCH("kpi.mkt.spend",I18N_KEY,0))),"kpi.mkt.spend") | D17: 21566331 | E17: 22216092 | F17: 21895367 | G17: 22097475 | H17: 22314206 | I17: 21990863 | J17: 22178213 | K17: 22368016 | L17: 22521410 | M17: 22184334 | N17: 21834604 | O17: 22311317 | P17: 23045237 | Q17: 22886962 | R17: 22521401 | S17: 21582394 | T17: 22160668 | U17: 22815785 | V17: 22735100 | W17: 23271458 | X17: 21288340 | Y17: 23727407 | Z17: 21240957 | AA17: 21101797 | AB17: 22831595 | AC17: 23162377 | AD17: 23594567 | AE17: 24643260 | AF17: 23320121 | AG17: 21961997 | AH17: 23900717 | AI17: 21244268 | AJ17: 22833201 | AK17: 21257703 | AL17: 21514333 | AM17: 22029956
C18: =IFERROR(IF(LANG="EN",INDEX(I18N_EN,MATCH("kpi.mkt.spend_pct",I18N_KEY,0)),INDEX(I18N_FR,MATCH("kpi.mkt.spend_pct",I18N_KEY,0))),"kpi.mkt.spend_pct") | D18: 0.0298 | E18: 0.0301 | F18: 0.0304 | G18: 0.0294 | H18: 0.0304 | I18: 0.0304 | J18: 0.0305 | K18: 0.0301 | L18: 0.031 | M18: 0.0299 | N18: 0.0292 | O18: 0.0306 | P18: 0.0317 | Q18: 0.0318 | R18: 0.031 | S18: 0.0319 | T18: 0.0317 | U18: 0.032 | V18: 0.0308 | W18: 0.0288 | X18: 0.0295 | Y18: 0.0329 | Z18: 0.0297 | AA18: 0.0328 | AB18: 0.0294 | AC18: 0.0295 | AD18: 0.0323 | AE18: 0.0297 | AF18: 0.0309 | AG18: 0.0329 | AH18: 0.0338 | AI18: 0.0335 | AJ18: 0.03 | AK18: 0.0332 | AL18: 0.0294 | AM18: 0.0318
C19: =IFERROR(IF(LANG="EN",INDEX(I18N_EN,MATCH("kpi.mkt.impressions",I18N_KEY,0)),INDEX(I18N_FR,MATCH("kpi.mkt.impressions",I18N_KEY,0))),"kpi.mkt.impressions") | D19: 1525211 | E19: 1513455 | F19: 1522092 | G19: 1480031 | H19: 1515204 | I19: 1539508 | J19: 1555400 | K19: 1543512 | L19: 1532485 | M19: 1502447 | N19: 1501169 | O19: 1523973 | P19: 1519592 | Q19: 1529109 | R19: 1599076 | S19: 1538362 | T19: 1449980 | U19: 1537759 | V19: 1541554 | W19: 1532852 | X19: 1544730 | Y19: 1520793 | Z19: 1504600 | AA19: 1545372 | AB19: 1486889 | AC19: 1479083 | AD19: 1471216 | AE19: 1488765 | AF19: 1536586 | AG19: 1501659 | AH19: 1492510 | AI19: 1480474 | AJ19: 1725460 | AK19: 1588758 | AL19: 1644013 | AM19: 1597712
C20: =IFERROR(IF(LANG="EN",INDEX(I18N_EN,MATCH("kpi.mkt.campaigns",I18N_KEY,0)),INDEX(I18N_FR,MATCH("kpi.mkt.campaigns",I18N_KEY,0))),"kpi.mkt.campaigns") | D20: 3 | E20: 3 | F20: 3 | G20: 3 | H20: 3 | I20: 3 | J20: 3 | K20: 3 | L20: 3 | M20: 3 | N20: 3 | O20: 3 | P20: 3 | Q20: 3 | R20: 3 | S20: 3 | T20: 3 | U20: 3 | V20: 3 | W20: 3 | X20: 3 | Y20: 3 | Z20: 3 | AA20: 3 | AB20: 3 | AC20: 3 | AD20: 3 | AE20: 3 | AF20: 3 | AG20: 3 | AH20: 3 | AI20: 3 | AJ20: 3 | AK20: 3 | AL20: 3 | AM20: 3
C21: =IFERROR(IF(LANG="EN",INDEX(I18N_EN,MATCH("kpi.mkt.nps",I18N_KEY,0)),INDEX(I18N_FR,MATCH("kpi.mkt.nps",I18N_KEY,0))),"kpi.mkt.nps") | D21: 42.21 | E21: 42.54 | F21: 42.17 | G21: 42.15 | H21: 43.02 | I21: 41.97 | J21: 43.07 | K21: 42.21 | L21: 42.89 | M21: 42.94 | N21: 42.89 | O21: 41.9 | P21: 43.35 | Q21: 42.37 | R21: 41.7 | S21: 41.63 | T21: 44.03 | U21: 42.07 | V21: 45.65 | W21: 42.21 | X21: 42.52 | Y21: 41.08 | Z21: 42.5 | AA21: 43.54 | AB21: 41.9 | AC21: 42.63 | AD21: 41.95 | AE21: 42.38 | AF21: 46.95 | AG21: 44.66 | AH21: 46.07 | AI21: 43.81 | AJ21: 41.13 | AK21: 45.26 | AL21: 42.39 | AM21: 40.67
C22: =IFERROR(IF(LANG="EN",INDEX(I18N_EN,MATCH("kpi.mkt.members",I18N_KEY,0)),INDEX(I18N_FR,MATCH("kpi.mkt.members",I18N_KEY,0))),"kpi.mkt.members") | D22: 26036 | E22: 25577 | F22: 26230 | G22: 25935 | H22: 25934 | I22: 25872 | J22: 27008 | K22: 26525 | L22: 26453 | M22: 26476 | N22: 26335 | O22: 26040 | P22: 27385 | Q22: 26724 | R22: 26817 | S22: 27102 | T22: 26674 | U22: 26814 | V22: 27227 | W22: 26818 | X22: 26001 | Y22: 26707 | Z22: 28269 | AA22: 26155 | AB22: 26220 | AC22: 27986 | AD22: 25609 | AE22: 25953 | AF22: 25713 | AG22: 27812 | AH22: 25368 | AI22: 27138 | AJ22: 26150 | AK22: 25123 | AL22: 28310 | AM22: 30014
C23: =IFERROR(IF(LANG="EN",INDEX(I18N_EN,MATCH("kpi.mkt.member_act",I18N_KEY,0)),INDEX(I18N_FR,MATCH("kpi.mkt.member_act",I18N_KEY,0))),"kpi.mkt.member_act") | D23: 0.3822 | E23: 0.3854 | F23: 0.3754 | G23: 0.3892 | H23: 0.389 | I23: 0.3774 | J23: 0.3836 | K23: 0.3843 | L23: 0.3831 | M23: 0.3839 | N23: 0.3739 | O23: 0.3859 | P23: 0.3857 | Q23: 0.3996 | R23: 0.3693 | S23: 0.3779 | T23: 0.3765 | U23: 0.3925 | V23: 0.3702 | W23: 0.4092 | X23: 0.3829 | Y23: 0.3992 | Z23: 0.3869 | AA23: 0.3931 | AB23: 0.3962 | AC23: 0.3953 | AD23: 0.3888 | AE23: 0.4087 | AF23: 0.4134 | AG23: 0.3887 | AH23: 0.406 | AI23: 0.4079 | AJ23: 0.4077 | AK23: 0.3899 | AL23: 0.3733 | AM23: 0.3767
C24: =IFERROR(IF(LANG="EN",INDEX(I18N_EN,MATCH("kpi.mkt.basket_member",I18N_KEY,0)),INDEX(I18N_FR,MATCH("kpi.mkt.basket_member",I18N_KEY,0))),"kpi.mkt.basket_member") | D24: 18189 | E24: 18233 | F24: 18889 | G24: 18456 | H24: 18933 | I24: 18168 | J24: 18241 | K24: 19355 | L24: 18537 | M24: 18538 | N24: 18606 | O24: 18699 | P24: 19071 | Q24: 18404 | R24: 18629 | S24: 19442 | T24: 18123 | U24: 18652 | V24: 18694 | W24: 18778 | X24: 19001 | Y24: 18571 | Z24: 19644 | AA24: 19737 | AB24: 19083 | AC24: 20178 | AD24: 18853 | AE24: 18988 | AF24: 20267 | AG24: 19573 | AH24: 20711 | AI24: 18459 | AJ24: 20195 | AK24: 20636 | AL24: 18633 | AM24: 19949
C26: 💬 Commentaires (KPI × mois)
C27: =IFERROR(IF(LANG="EN",INDEX(I18N_EN,MATCH("kpi.mkt.events",I18N_KEY,0)),INDEX(I18N_FR,MATCH("kpi.mkt.events",I18N_KEY,0))),"kpi.mkt.events")
C28: =IFERROR(IF(LANG="EN",INDEX(I18N_EN,MATCH("kpi.mkt.event_att",I18N_KEY,0)),INDEX(I18N_FR,MATCH("kpi.mkt.event_att",I18N_KEY,0))),"kpi.mkt.event_att")
C29: =IFERROR(IF(LANG="EN",INDEX(I18N_EN,MATCH("kpi.mkt.event_roi",I18N_KEY,0)),INDEX(I18N_FR,MATCH("kpi.mkt.event_roi",I18N_KEY,0))),"kpi.mkt.event_roi")
C30: =IFERROR(IF(LANG="EN",INDEX(I18N_EN,MATCH("kpi.mkt.event_sat",I18N_KEY,0)),INDEX(I18N_FR,MATCH("kpi.mkt.event_sat",I18N_KEY,0))),"kpi.mkt.event_sat")
C31: =IFERROR(IF(LANG="EN",INDEX(I18N_EN,MATCH("kpi.mkt.engagement",I18N_KEY,0)),INDEX(I18N_FR,MATCH("kpi.mkt.engagement",I18N_KEY,0))),"kpi.mkt.engagement")
C32: =IFERROR(IF(LANG="EN",INDEX(I18N_EN,MATCH("kpi.mkt.followers",I18N_KEY,0)),INDEX(I18N_FR,MATCH("kpi.mkt.followers",I18N_KEY,0))),"kpi.mkt.followers")
C33: =IFERROR(IF(LANG="EN",INDEX(I18N_EN,MATCH("kpi.mkt.reach",I18N_KEY,0)),INDEX(I18N_FR,MATCH("kpi.mkt.reach",I18N_KEY,0))),"kpi.mkt.reach")
C34: =IFERROR(IF(LANG="EN",INDEX(I18N_EN,MATCH("kpi.mkt.cpa",I18N_KEY,0)),INDEX(I18N_FR,MATCH("kpi.mkt.cpa",I18N_KEY,0))),"kpi.mkt.cpa")
C35: =IFERROR(IF(LANG="EN",INDEX(I18N_EN,MATCH("kpi.mkt.digital_conv",I18N_KEY,0)),INDEX(I18N_FR,MATCH("kpi.mkt.digital_conv",I18N_KEY,0))),"kpi.mkt.digital_conv")
C36: =IFERROR(IF(LANG="EN",INDEX(I18N_EN,MATCH("kpi.mkt.spend",I18N_KEY,0)),INDEX(I18N_FR,MATCH("kpi.mkt.spend",I18N_KEY,0))),"kpi.mkt.spend")
C37: =IFERROR(IF(LANG="EN",INDEX(I18N_EN,MATCH("kpi.mkt.spend_pct",I18N_KEY,0)),INDEX(I18N_FR,MATCH("kpi.mkt.spend_pct",I18N_KEY,0))),"kpi.mkt.spend_pct")
C38: =IFERROR(IF(LANG="EN",INDEX(I18N_EN,MATCH("kpi.mkt.impressions",I18N_KEY,0)),INDEX(I18N_FR,MATCH("kpi.mkt.impressions",I18N_KEY,0))),"kpi.mkt.impressions")
C39: =IFERROR(IF(LANG="EN",INDEX(I18N_EN,MATCH("kpi.mkt.campaigns",I18N_KEY,0)),INDEX(I18N_FR,MATCH("kpi.mkt.campaigns",I18N_KEY,0))),"kpi.mkt.campaigns")
C40: =IFERROR(IF(LANG="EN",INDEX(I18N_EN,MATCH("kpi.mkt.nps",I18N_KEY,0)),INDEX(I18N_FR,MATCH("kpi.mkt.nps",I18N_KEY,0))),"kpi.mkt.nps")
C41: =IFERROR(IF(LANG="EN",INDEX(I18N_EN,MATCH("kpi.mkt.members",I18N_KEY,0)),INDEX(I18N_FR,MATCH("kpi.mkt.members",I18N_KEY,0))),"kpi.mkt.members")
C42: =IFERROR(IF(LANG="EN",INDEX(I18N_EN,MATCH("kpi.mkt.member_act",I18N_KEY,0)),INDEX(I18N_FR,MATCH("kpi.mkt.member_act",I18N_KEY,0))),"kpi.mkt.member_act")
C43: =IFERROR(IF(LANG="EN",INDEX(I18N_EN,MATCH("kpi.mkt.basket_member",I18N_KEY,0)),INDEX(I18N_FR,MATCH("kpi.mkt.basket_member",I18N_KEY,0))),"kpi.mkt.basket_member")

Sheet C6 · Commercial
C1: ="▌ "&IFERROR(IF(LANG="EN",INDEX(I18N_EN,MATCH("msg.collect",I18N_KEY,0)),INDEX(I18N_FR,MATCH("msg.collect",I18N_KEY,0))),"msg.collect")&" · "&IFERROR(IF(LANG="EN",INDEX(I18N_EN,MATCH("dept.com",I18N_KEY,0)),INDEX(I18N_FR,MATCH("dept.com",I18N_KEY,0))),"dept.com")
C2: =IFERROR(IF(LANG="EN",INDEX(I18N_EN,MATCH("msg.help",I18N_KEY,0)),INDEX(I18N_FR,MATCH("msg.help",I18N_KEY,0))),"msg.help")
C6: KPI \ Mois | D6: =DATE(2024,1,1) | E6: =DATE(2024,2,1) | F6: =DATE(2024,3,1) | G6: =DATE(2024,4,1) | H6: =DATE(2024,5,1) | I6: =DATE(2024,6,1) | J6: =DATE(2024,7,1) | K6: =DATE(2024,8,1) | L6: =DATE(2024,9,1) | M6: =DATE(2024,10,1) | N6: =DATE(2024,11,1) | O6: =DATE(2024,12,1) | P6: =DATE(2025,1,1) | Q6: =DATE(2025,2,1) | R6: =DATE(2025,3,1) | S6: =DATE(2025,4,1) | T6: =DATE(2025,5,1) | U6: =DATE(2025,6,1) | V6: =DATE(2025,7,1) | W6: =DATE(2025,8,1) | X6: =DATE(2025,9,1) | Y6: =DATE(2025,10,1) | Z6: =DATE(2025,11,1) | AA6: =DATE(2025,12,1) | AB6: =DATE(2026,1,1) | AC6: =DATE(2026,2,1) | AD6: =DATE(2026,3,1) | AE6: =DATE(2026,4,1) | AF6: =DATE(2026,5,1) | AG6: =DATE(2026,6,1) | AH6: =DATE(2026,7,1) | AI6: =DATE(2026,8,1) | AJ6: =DATE(2026,9,1) | AK6: =DATE(2026,10,1) | AL6: =DATE(2026,11,1) | AM6: =DATE(2026,12,1)
C8: =IFERROR(IF(LANG="EN",INDEX(I18N_EN,MATCH("kpi.com.tenant_sales",I18N_KEY,0)),INDEX(I18N_FR,MATCH("kpi.com.tenant_sales",I18N_KEY,0))),"kpi.com.tenant_sales") | D8: 1226886815 | E8: 1232675094 | F8: 1255780398 | G8: 1265189301 | H8: 1240472916 | I8: 1285566219 | J8: 1284941518 | K8: 1262430387 | L8: 1278931343 | M8: 1297039423 | N8: 1265138986 | O8: 1254560446 | P8: 1246909879 | Q8: 1274950604 | R8: 1285043726 | S8: 1302741582 | T8: 1301146988 | U8: 1234902249 | V8: 1257273208 | W8: 1223656935 | X8: 1235774369 | Y8: 1223145567 | Z8: 1320320768 | AA8: 1286893563 | AB8: 1279772169 | AC8: 1251820233 | AD8: 1207248078 | AE8: 1289457669 | AF8: 1259092209 | AG8: 1315854616 | AH8: 1206109647 | AI8: 1317880066 | AJ8: 1326747465 | AK8: 1348054071 | AL8: 1227670475 | AM8: 1372863557
C9: =IFERROR(IF(LANG="EN",INDEX(I18N_EN,MATCH("kpi.com.total_sales",I18N_KEY,0)),INDEX(I18N_FR,MATCH("kpi.com.total_sales",I18N_KEY,0))),"kpi.com.total_sales") | D9: 1278658922 | E9: 1299157093 | F9: 1292138969 | G9: 1282922303 | H9: 1326986803 | I9: 1339090772 | J9: 1290149640 | K9: 1305878572 | L9: 1290448545 | M9: 1352289366 | N9: 1266612163 | O9: 1379303402 | P9: 1371804318 | Q9: 1287260738 | R9: 1282976113 | S9: 1259546143 | T9: 1318829176 | U9: 1321959793 | V9: 1343114976 | W9: 1294999737 | X9: 1269905407 | Y9: 1340771486 | Z9: 1275746658 | AA9: 1398258374 | AB9: 1272940322 | AC9: 1249328752 | AD9: 1322424261 | AE9: 1401197096 | AF9: 1271073634 | AG9: 1372065341 | AH9: 1353911518 | AI9: 1255769594 | AJ9: 1448256846 | AK9: 1284447019 | AL9: 1374701586 | AM9: 1227451390
C10: =IFERROR(IF(LANG="EN",INDEX(I18N_EN,MATCH("kpi.com.sales_sqm",I18N_KEY,0)),INDEX(I18N_FR,MATCH("kpi.com.sales_sqm",I18N_KEY,0))),"kpi.com.sales_sqm") | D10: 61587.25 | E10: 61200.18 | F10: 61701.32 | G10: 61744.6 | H10: 63035.13 | I10: 63307.32 | J10: 64304.59 | K10: 62233.92 | L10: 62319.17 | M10: 62671.58 | N10: 62419.43 | O10: 63657.53 | P10: 63852.22 | Q10: 61252.13 | R10: 62684.57 | S10: 65082.65 | T10: 62929.31 | U10: 61431.47 | V10: 66407.32 | W10: 62905.88 | X10: 63035.53 | Y10: 68727.83 | Z10: 62256.7 | AA10: 66983.4 | AB10: 65725.8 | AC10: 60381.93 | AD10: 68363.02 | AE10: 67873.23 | AF10: 63407.18 | AG10: 65058.73 | AH10: 69920.64 | AI10: 62953.54 | AJ10: 59594.37 | AK10: 68268.96 | AL10: 62369.39 | AM10: 61099.11
C11: =IFERROR(IF(LANG="EN",INDEX(I18N_EN,MATCH("kpi.com.lfl",I18N_KEY,0)),INDEX(I18N_FR,MATCH("kpi.com.lfl",I18N_KEY,0))),"kpi.com.lfl") | D11: 0.0597 | E11: 0.0601 | F11: 0.0604 | G11: 0.0602 | H11: 0.0608 | I11: 0.0591 | J11: 0.0602 | K11: 0.0589 | L11: 0.061 | M11: 0.0629 | N11: 0.0604 | O11: 0.0637 | P11: 0.0606 | Q11: 0.0603 | R11: 0.0596 | S11: 0.0622 | T11: 0.0606 | U11: 0.0631 | V11: 0.0626 | W11: 0.0635 | X11: 0.0622 | Y11: 0.0597 | Z11: 0.0618 | AA11: 0.064 | AB11: 0.0625 | AC11: 0.0578 | AD11: 0.0609 | AE11: 0.0653 | AF11: 0.0619 | AG11: 0.0581 | AH11: 0.0597 | AI11: 0.0627 | AJ11: 0.0592 | AK11: 0.0683 | AL11: 0.0585 | AM11: 0.0616
C12: =IFERROR(IF(LANG="EN",INDEX(I18N_EN,MATCH("kpi.com.new_leases",I18N_KEY,0)),INDEX(I18N_FR,MATCH("kpi.com.new_leases",I18N_KEY,0))),"kpi.com.new_leases") | D12: 3 | E12: 3 | F12: 3 | G12: 3 | H12: 3 | I12: 3 | J12: 3 | K12: 3 | L12: 3 | M12: 3 | N12: 3 | O12: 3 | P12: 3 | Q12: 3 | R12: 3 | S12: 3 | T12: 3 | U12: 3 | V12: 3 | W12: 3 | X12: 3 | Y12: 3 | Z12: 3 | AA12: 3 | AB12: 3 | AC12: 3 | AD12: 3 | AE12: 3 | AF12: 3 | AG12: 3 | AH12: 3 | AI12: 3 | AJ12: 3 | AK12: 3 | AL12: 3 | AM12: 3
C13: =IFERROR(IF(LANG="EN",INDEX(I18N_EN,MATCH("kpi.com.pipeline",I18N_KEY,0)),INDEX(I18N_FR,MATCH("kpi.com.pipeline",I18N_KEY,0))),"kpi.com.pipeline") | D13: 341073942 | E13: 335790535 | F13: 338404088 | G13: 334871799 | H13: 342064466 | I13: 335445912 | J13: 342115084 | K13: 344103106 | L13: 348453395 | M13: 340664107 | N13: 353988787 | O13: 347559410 | P13: 362557833 | Q13: 342419532 | R13: 342153809 | S13: 359724543 | T13: 337112624 | U13: 350701261 | V13: 344127466 | W13: 356103991 | X13: 361558370 | Y13: 332484927 | Z13: 339088517 | AA13: 371343899 | AB13: 345388579 | AC13: 356947373 | AD13: 323878247 | AE13: 345605705 | AF13: 343233806 | AG13: 337448465 | AH13: 363245518 | AI13: 370149742 | AJ13: 321855968 | AK13: 342958092 | AL13: 373567174 | AM13: 379194168
C14: =IFERROR(IF(LANG="EN",INDEX(I18N_EN,MATCH("kpi.com.leases_renewed",I18N_KEY,0)),INDEX(I18N_FR,MATCH("kpi.com.leases_renewed",I18N_KEY,0))),"kpi.com.leases_renewed") | D14: 2 | E14: 2 | F14: 2 | G14: 2 | H14: 2 | I14: 2 | J14: 2 | K14: 2 | L14: 2 | M14: 2 | N14: 2 | O14: 2 | P14: 2 | Q14: 2 | R14: 2 | S14: 2 | T14: 2 | U14: 2 | V14: 2 | W14: 2 | X14: 2 | Y14: 2 | Z14: 2 | AA14: 2 | AB14: 2 | AC14: 2 | AD14: 2 | AE14: 2 | AF14: 2 | AG14: 2 | AH14: 2 | AI14: 2 | AJ14: 2 | AK14: 2 | AL14: 2 | AM14: 2
C15: =IFERROR(IF(LANG="EN",INDEX(I18N_EN,MATCH("kpi.com.pipeline_conv",I18N_KEY,0)),INDEX(I18N_FR,MATCH("kpi.com.pipeline_conv",I18N_KEY,0))),"kpi.com.pipeline_conv") | D15: 0.3474 | E15: 0.3488 | F15: 0.3466 | G15: 0.3496 | H15: 0.344 | I15: 0.3434 | J15: 0.3547 | K15: 0.3473 | L15: 0.3461 | M15: 0.3551 | N15: 0.3439 | O15: 0.3557 | P15: 0.3495 | Q15: 0.3582 | R15: 0.3397 | S15: 0.3508 | T15: 0.3624 | U15: 0.3727 | V15: 0.3606 | W15: 0.3745 | X15: 0.3673 | Y15: 0.384 | Z15: 0.3543 | AA15: 0.3818 | AB15: 0.3599 | AC15: 0.3747 | AD15: 0.3574 | AE15: 0.3536 | AF15: 0.3763 | AG15: 0.361 | AH15: 0.379 | AI15: 0.3886 | AJ15: 0.3356 | AK15: 0.3562 | AL15: 0.3484 | AM15: 0.3696
C16: =IFERROR(IF(LANG="EN",INDEX(I18N_EN,MATCH("kpi.com.popup_count",I18N_KEY,0)),INDEX(I18N_FR,MATCH("kpi.com.popup_count",I18N_KEY,0))),"kpi.com.popup_count") | D16: 6 | E16: 6 | F16: 6 | G16: 6 | H16: 6 | I16: 6 | J16: 6 | K16: 6 | L16: 6 | M16: 6 | N16: 6 | O16: 6 | P16: 6 | Q16: 6 | R16: 6 | S16: 6 | T16: 6 | U16: 6 | V16: 6 | W16: 6 | X16: 6 | Y16: 7 | Z16: 6 | AA16: 6 | AB16: 6 | AC16: 6 | AD16: 6 | AE16: 7 | AF16: 7 | AG16: 7 | AH16: 6 | AI16: 7 | AJ16: 6 | AK16: 6 | AL16: 6 | AM16: 7
C17: =IFERROR(IF(LANG="EN",INDEX(I18N_EN,MATCH("kpi.com.popup_rev",I18N_KEY,0)),INDEX(I18N_FR,MATCH("kpi.com.popup_rev",I18N_KEY,0))),"kpi.com.popup_rev") | D17: 18263289 | E17: 18144082 | F17: 17898730 | G17: 17955702 | H17: 18238411 | I17: 17891171 | J17: 18388691 | K17: 18175846 | L17: 18737497 | M17: 17584531 | N17: 17918378 | O17: 18222260 | P17: 18614598 | Q17: 18463901 | R17: 18504710 | S17: 18493341 | T17: 17891245 | U17: 18492189 | V17: 17968738 | W17: 18749053 | X17: 19038171 | Y17: 18479537 | Z17: 18574400 | AA17: 19771860 | AB17: 18844388 | AC17: 18732528 | AD17: 17877942 | AE17: 20385495 | AF17: 19497899 | AG17: 17768387 | AH17: 17481657 | AI17: 19899272 | AJ17: 17530399 | AK17: 19725402 | AL17: 17197627 | AM17: 19880283
C18: =IFERROR(IF(LANG="EN",INDEX(I18N_EN,MATCH("kpi.com.kiosk_occ",I18N_KEY,0)),INDEX(I18N_FR,MATCH("kpi.com.kiosk_occ",I18N_KEY,0))),"kpi.com.kiosk_occ") | D18: 0.779 | E18: 0.7797 | F18: 0.7956 | G18: 0.766 | H18: 0.7998 | I18: 0.7926 | J18: 0.7741 | K18: 0.7635 | L18: 0.816 | M18: 0.7884 | N18: 0.7727 | O18: 0.8026 | P18: 0.7669 | Q18: 0.8001 | R18: 0.7612 | S18: 0.792 | T18: 0.8036 | U18: 0.7871 | V18: 0.8082 | W18: 0.8269 | X18: 0.7542 | Y18: 0.8332 | Z18: 0.8195 | AA18: 0.8252 | AB18: 0.8046 | AC18: 0.783 | AD18: 0.7955 | AE18: 0.8289 | AF18: 0.7666 | AG18: 0.7943 | AH18: 0.8482 | AI18: 0.8043 | AJ18: 0.801 | AK18: 0.856 | AL18: 0.881 | AM18: 0.8613
C19: =IFERROR(IF(LANG="EN",INDEX(I18N_EN,MATCH("kpi.com.market_rev",I18N_KEY,0)),INDEX(I18N_FR,MATCH("kpi.com.market_rev",I18N_KEY,0))),"kpi.com.market_rev") | D19: 41228910 | E19: 42391123 | F19: 42224368 | G19: 43083028 | H19: 41690276 | I19: 42077229 | J19: 42662155 | K19: 43232119 | L19: 42137826 | M19: 42508466 | N19: 41911789 | O19: 43673435 | P19: 40638583 | Q19: 41453374 | R19: 41533178 | S19: 40994903 | T19: 42129744 | U19: 44222522 | V19: 45258092 | W19: 43450384 | X19: 44289160 | Y19: 44720056 | Z19: 44453681 | AA19: 45894627 | AB19: 41963699 | AC19: 46350244 | AD19: 45821944 | AE19: 43824550 | AF19: 45196916 | AG19: 40671599 | AH19: 45598265 | AI19: 41875850 | AJ19: 47023689 | AK19: 43495445 | AL19: 47722571 | AM19: 41385570
C20: =IFERROR(IF(LANG="EN",INDEX(I18N_EN,MATCH("kpi.com.market_occ",I18N_KEY,0)),INDEX(I18N_FR,MATCH("kpi.com.market_occ",I18N_KEY,0))),"kpi.com.market_occ") | D20: 0.8389 | E20: 0.8346 | F20: 0.8434 | G20: 0.8137 | H20: 0.8278 | I20: 0.8478 | J20: 0.8318 | K20: 0.8581 | L20: 0.8373 | M20: 0.8604 | N20: 0.8572 | O20: 0.8404 | P20: 0.8731 | Q20: 0.8643 | R20: 0.8287 | S20: 0.8698 | T20: 0.8685 | U20: 0.8448 | V20: 0.8472 | W20: 0.8803 | X20: 0.8723 | Y20: 0.8118 | Z20: 0.8888 | AA20: 0.8067 | AB20: 0.835 | AC20: 0.896 | AD20: 0.8723 | AE20: 0.8133 | AF20: 0.8825 | AG20: 0.8295 | AH20: 0.8784 | AI20: 0.8039 | AJ20: 0.8399 | AK20: 0.9198 | AL20: 0.9349 | AM20: 0.8074
C21: =IFERROR(IF(LANG="EN",INDEX(I18N_EN,MATCH("kpi.com.market_stalls",I18N_KEY,0)),INDEX(I18N_FR,MATCH("kpi.com.market_stalls",I18N_KEY,0))),"kpi.com.market_stalls") | D21: 44 | E21: 45 | F21: 45 | G21: 45 | H21: 46 | I21: 44 | J21: 46 | K21: 45 | L21: 45 | M21: 44 | N21: 46 | O21: 45 | P21: 47 | Q21: 45 | R21: 46 | S21: 47 | T21: 48 | U21: 47 | V21: 48 | W21: 45 | X21: 48 | Y21: 47 | Z21: 44 | AA21: 46 | AB21: 47 | AC21: 49 | AD21: 45 | AE21: 48 | AF21: 43 | AG21: 43 | AH21: 44 | AI21: 50 | AJ21: 50 | AK21: 48 | AL21: 48 | AM21: 47
C22: =IFERROR(IF(LANG="EN",INDEX(I18N_EN,MATCH("kpi.com.media_sales",I18N_KEY,0)),INDEX(I18N_FR,MATCH("kpi.com.media_sales",I18N_KEY,0))),"kpi.com.media_sales") | D22: 27482136 | E22: 27988674 | F22: 28366550 | G22: 28085236 | H22: 27546841 | I22: 27927829 | J22: 27697186 | K22: 28616953 | L22: 28263444 | M22: 28339029 | N22: 28242157 | O22: 29290832 | P22: 28068355 | Q22: 28362186 | R22: 28643761 | S22: 28257622 | T22: 29710610 | U22: 27707090 | V22: 29580595 | W22: 29611164 | X22: 28013897 | Y22: 29687746 | Z22: 27930024 | AA22: 29375585 | AB22: 29836533 | AC22: 27658534 | AD22: 30439323 | AE22: 27840772 | AF22: 29487494 | AG22: 27991761 | AH22: 28857766 | AI22: 27682767 | AJ22: 30488571 | AK22: 27330151 | AL22: 29912435 | AM22: 27758258
C23: =IFERROR(IF(LANG="EN",INDEX(I18N_EN,MATCH("kpi.com.partnership_rev",I18N_KEY,0)),INDEX(I18N_FR,MATCH("kpi.com.partnership_rev",I18N_KEY,0))),"kpi.com.partnership_rev") | D23: 14802721 | E23: 15239866 | F23: 15234351 | G23: 15166688 | H23: 15254631 | I23: 15011172 | J23: 15305686 | K23: 15502347 | L23: 15270009 | M23: 15512007 | N23: 14893510 | O23: 15545734 | P23: 15140918 | Q23: 15063742 | R23: 15600256 | S23: 15444860 | T23: 14721924 | U23: 15512889 | V23: 15852886 | W23: 15019639 | X23: 14731797 | Y23: 16039508 | Z23: 15174932 | AA23: 14673879 | AB23: 15234789 | AC23: 16451062 | AD23: 14470169 | AE23: 16432195 | AF23: 15546780 | AG23: 15277908 | AH23: 16202121 | AI23: 14759631 | AJ23: 14947028 | AK23: 15359426 | AL23: 17054082 | AM23: 16806051
C24: =IFERROR(IF(LANG="EN",INDEX(I18N_EN,MATCH("kpi.com.activations",I18N_KEY,0)),INDEX(I18N_FR,MATCH("kpi.com.activations",I18N_KEY,0))),"kpi.com.activations") | D24: 5 | E24: 5 | F24: 5 | G24: 5 | H24: 5 | I24: 5 | J24: 5 | K24: 5 | L24: 5 | M24: 5 | N24: 5 | O24: 5 | P24: 5 | Q24: 5 | R24: 5 | S24: 5 | T24: 5 | U24: 5 | V24: 5 | W24: 5 | X24: 5 | Y24: 5 | Z24: 5 | AA24: 5 | AB24: 5 | AC24: 5 | AD24: 5 | AE24: 5 | AF24: 5 | AG24: 5 | AH24: 5 | AI24: 5 | AJ24: 5 | AK24: 5 | AL24: 5 | AM24: 5
C25: =IFERROR(IF(LANG="EN",INDEX(I18N_EN,MATCH("kpi.com.activation_rev",I18N_KEY,0)),INDEX(I18N_FR,MATCH("kpi.com.activation_rev",I18N_KEY,0))),"kpi.com.activation_rev") | D25: 9052578 | E25: 9037533 | F25: 9169050 | G25: 8959595 | H25: 9079882 | I25: 8893478 | J25: 9241741 | K25: 9024145 | L25: 9026560 | M25: 9113975 | N25: 9160192 | O25: 9531287 | P25: 9333196 | Q25: 8841119 | R25: 8783614 | S25: 8818455 | T25: 8968595 | U25: 8745857 | V25: 9041125 | W25: 9161776 | X25: 9204389 | Y25: 9166717 | Z25: 8866529 | AA25: 8904604 | AB25: 9774159 | AC25: 9178466 | AD25: 9223738 | AE25: 10136730 | AF25: 9339118 | AG25: 9616622 | AH25: 9364484 | AI25: 9911935 | AJ25: 8836368 | AK25: 9063161 | AL25: 10013741 | AM25: 8556278
C26: =IFERROR(IF(LANG="EN",INDEX(I18N_EN,MATCH("kpi.com.discount",I18N_KEY,0)),INDEX(I18N_FR,MATCH("kpi.com.discount",I18N_KEY,0))),"kpi.com.discount") | D26: 0.0401 | E26: 0.0407 | F26: 0.0392 | G26: 0.0401 | H26: 0.0397 | I26: 0.0398 | J26: 0.0403 | K26: 0.0418 | L26: 0.0396 | M26: 0.041 | N26: 0.0399 | O26: 0.041 | P26: 0.0411 | Q26: 0.0413 | R26: 0.0429 | S26: 0.0406 | T26: 0.0425 | U26: 0.0419 | V26: 0.0407 | W26: 0.0398 | X26: 0.0436 | Y26: 0.0399 | Z26: 0.0419 | AA26: 0.0415 | AB26: 0.041 | AC26: 0.043 | AD26: 0.0388 | AE26: 0.0409 | AF26: 0.0392 | AG26: 0.0436 | AH26: 0.0421 | AI26: 0.0376 | AJ26: 0.0408 | AK26: 0.0444 | AL26: 0.0438 | AM26: 0.0413
C28: 💬 Commentaires (KPI × mois)
C29: =IFERROR(IF(LANG="EN",INDEX(I18N_EN,MATCH("kpi.com.tenant_sales",I18N_KEY,0)),INDEX(I18N_FR,MATCH("kpi.com.tenant_sales",I18N_KEY,0))),"kpi.com.tenant_sales")
C30: =IFERROR(IF(LANG="EN",INDEX(I18N_EN,MATCH("kpi.com.total_sales",I18N_KEY,0)),INDEX(I18N_FR,MATCH("kpi.com.total_sales",I18N_KEY,0))),"kpi.com.total_sales")
C31: =IFERROR(IF(LANG="EN",INDEX(I18N_EN,MATCH("kpi.com.sales_sqm",I18N_KEY,0)),INDEX(I18N_FR,MATCH("kpi.com.sales_sqm",I18N_KEY,0))),"kpi.com.sales_sqm")
C32: =IFERROR(IF(LANG="EN",INDEX(I18N_EN,MATCH("kpi.com.lfl",I18N_KEY,0)),INDEX(I18N_FR,MATCH("kpi.com.lfl",I18N_KEY,0))),"kpi.com.lfl")
C33: =IFERROR(IF(LANG="EN",INDEX(I18N_EN,MATCH("kpi.com.new_leases",I18N_KEY,0)),INDEX(I18N_FR,MATCH("kpi.com.new_leases",I18N_KEY,0))),"kpi.com.new_leases")
C34: =IFERROR(IF(LANG="EN",INDEX(I18N_EN,MATCH("kpi.com.pipeline",I18N_KEY,0)),INDEX(I18N_FR,MATCH("kpi.com.pipeline",I18N_KEY,0))),"kpi.com.pipeline")
C35: =IFERROR(IF(LANG="EN",INDEX(I18N_EN,MATCH("kpi.com.leases_renewed",I18N_KEY,0)),INDEX(I18N_FR,MATCH("kpi.com.leases_renewed",I18N_KEY,0))),"kpi.com.leases_renewed")
C36: =IFERROR(IF(LANG="EN",INDEX(I18N_EN,MATCH("kpi.com.pipeline_conv",I18N_KEY,0)),INDEX(I18N_FR,MATCH("kpi.com.pipeline_conv",I18N_KEY,0))),"kpi.com.pipeline_conv")
C37: =IFERROR(IF(LANG="EN",INDEX(I18N_EN,MATCH("kpi.com.popup_count",I18N_KEY,0)),INDEX(I18N_FR,MATCH("kpi.com.popup_count",I18N_KEY,0))),"kpi.com.popup_count")
C38: =IFERROR(IF(LANG="EN",INDEX(I18N_EN,MATCH("kpi.com.popup_rev",I18N_KEY,0)),INDEX(I18N_FR,MATCH("kpi.com.popup_rev",I18N_KEY,0))),"kpi.com.popup_rev")
C39: =IFERROR(IF(LANG="EN",INDEX(I18N_EN,MATCH("kpi.com.kiosk_occ",I18N_KEY,0)),INDEX(I18N_FR,MATCH("kpi.com.kiosk_occ",I18N_KEY,0))),"kpi.com.kiosk_occ")
C40: =IFERROR(IF(LANG="EN",INDEX(I18N_EN,MATCH("kpi.com.market_rev",I18N_KEY,0)),INDEX(I18N_FR,MATCH("kpi.com.market_rev",I18N_KEY,0))),"kpi.com.market_rev")
C41: =IFERROR(IF(LANG="EN",INDEX(I18N_EN,MATCH("kpi.com.market_occ",I18N_KEY,0)),INDEX(I18N_FR,MATCH("kpi.com.market_occ",I18N_KEY,0))),"kpi.com.market_occ")
C42: =IFERROR(IF(LANG="EN",INDEX(I18N_EN,MATCH("kpi.com.market_stalls",I18N_KEY,0)),INDEX(I18N_FR,MATCH("kpi.com.market_stalls",I18N_KEY,0))),"kpi.com.market_stalls")
C43: =IFERROR(IF(LANG="EN",INDEX(I18N_EN,MATCH("kpi.com.media_sales",I18N_KEY,0)),INDEX(I18N_FR,MATCH("kpi.com.media_sales",I18N_KEY,0))),"kpi.com.media_sales")
C44: =IFERROR(IF(LANG="EN",INDEX(I18N_EN,MATCH("kpi.com.partnership_rev",I18N_KEY,0)),INDEX(I18N_FR,MATCH("kpi.com.partnership_rev",I18N_KEY,0))),"kpi.com.partnership_rev")
C45: =IFERROR(IF(LANG="EN",INDEX(I18N_EN,MATCH("kpi.com.activations",I18N_KEY,0)),INDEX(I18N_FR,MATCH("kpi.com.activations",I18N_KEY,0))),"kpi.com.activations")
C46: =IFERROR(IF(LANG="EN",INDEX(I18N_EN,MATCH("kpi.com.activation_rev",I18N_KEY,0)),INDEX(I18N_FR,MATCH("kpi.com.activation_rev",I18N_KEY,0))),"kpi.com.activation_rev")
C47: =IFERROR(IF(LANG="EN",INDEX(I18N_EN,MATCH("kpi.com.discount",I18N_KEY,0)),INDEX(I18N_FR,MATCH("kpi.com.discount",I18N_KEY,0))),"kpi.com.discount")

Sheet C7 · HSSE
C1: ="▌ "&IFERROR(IF(LANG="EN",INDEX(I18N_EN,MATCH("msg.collect",I18N_KEY,0)),INDEX(I18N_FR,MATCH("msg.collect",I18N_KEY,0))),"msg.collect")&" · "&IFERROR(IF(LANG="EN",INDEX(I18N_EN,MATCH("dept.hsse",I18N_KEY,0)),INDEX(I18N_FR,MATCH("dept.hsse",I18N_KEY,0))),"dept.hsse")
C2: =IFERROR(IF(LANG="EN",INDEX(I18N_EN,MATCH("msg.help",I18N_KEY,0)),INDEX(I18N_FR,MATCH("msg.help",I18N_KEY,0))),"msg.help")
C6: KPI \ Mois | D6: =DATE(2024,1,1) | E6: =DATE(2024,2,1) | F6: =DATE(2024,3,1) | G6: =DATE(2024,4,1) | H6: =DATE(2024,5,1) | I6: =DATE(2024,6,1) | J6: =DATE(2024,7,1) | K6: =DATE(2024,8,1) | L6: =DATE(2024,9,1) | M6: =DATE(2024,10,1) | N6: =DATE(2024,11,1) | O6: =DATE(2024,12,1) | P6: =DATE(2025,1,1) | Q6: =DATE(2025,2,1) | R6: =DATE(2025,3,1) | S6: =DATE(2025,4,1) | T6: =DATE(2025,5,1) | U6: =DATE(2025,6,1) | V6: =DATE(2025,7,1) | W6: =DATE(2025,8,1) | X6: =DATE(2025,9,1) | Y6: =DATE(2025,10,1) | Z6: =DATE(2025,11,1) | AA6: =DATE(2025,12,1) | AB6: =DATE(2026,1,1) | AC6: =DATE(2026,2,1) | AD6: =DATE(2026,3,1) | AE6: =DATE(2026,4,1) | AF6: =DATE(2026,5,1) | AG6: =DATE(2026,6,1) | AH6: =DATE(2026,7,1) | AI6: =DATE(2026,8,1) | AJ6: =DATE(2026,9,1) | AK6: =DATE(2026,10,1) | AL6: =DATE(2026,11,1) | AM6: =DATE(2026,12,1)
C8: =IFERROR(IF(LANG="EN",INDEX(I18N_EN,MATCH("kpi.hsse.incidents",I18N_KEY,0)),INDEX(I18N_FR,MATCH("kpi.hsse.incidents",I18N_KEY,0))),"kpi.hsse.incidents") | D8: 2 | E8: 2 | F8: 2 | G8: 2 | H8: 2 | I8: 2 | J8: 2 | K8: 2 | L8: 2 | M8: 2 | N8: 2 | O8: 2 | P8: 2 | Q8: 2 | R8: 2 | S8: 2 | T8: 2 | U8: 2 | V8: 2 | W8: 2 | X8: 2 | Y8: 2 | Z8: 2 | AA8: 2 | AB8: 2 | AC8: 2 | AD8: 2 | AE8: 2 | AF8: 2 | AG8: 2 | AH8: 2 | AI8: 2 | AJ8: 2 | AK8: 2 | AL8: 2 | AM8: 2
C9: =IFERROR(IF(LANG="EN",INDEX(I18N_EN,MATCH("kpi.hsse.incident_sev",I18N_KEY,0)),INDEX(I18N_FR,MATCH("kpi.hsse.incident_sev",I18N_KEY,0))),"kpi.hsse.incident_sev") | D9: 2.12 | E9: 2.12 | F9: 2.12 | G9: 2.13 | H9: 2.07 | I9: 2.06 | J9: 2.1 | K9: 2.11 | L9: 2.17 | M9: 2.04 | N9: 2.17 | O9: 2.04 | P9: 2.06 | Q9: 2.19 | R9: 2.22 | S9: 2.13 | T9: 2.08 | U9: 2.1 | V9: 2.29 | W9: 2.09 | X9: 2.18 | Y9: 2.1 | Z9: 2.07 | AA9: 2.01 | AB9: 2.06 | AC9: 2.3 | AD9: 2.29 | AE9: 2.09 | AF9: 2.24 | AG9: 2.21 | AH9: 2.33 | AI9: 2.13 | AJ9: 2.06 | AK9: 2.09 | AL9: 2.02 | AM9: 2.07
C10: =IFERROR(IF(LANG="EN",INDEX(I18N_EN,MATCH("kpi.hsse.tf",I18N_KEY,0)),INDEX(I18N_FR,MATCH("kpi.hsse.tf",I18N_KEY,0))),"kpi.hsse.tf") | D10: 4.21 | E10: 4.17 | F10: 4.16 | G10: 4.19 | H10: 4.26 | I10: 4.2 | J10: 4.23 | K10: 4.23 | L10: 4.27 | M10: 4.27 | N10: 4.19 | O10: 4.28 | P10: 4.09 | Q10: 4.26 | R10: 4.22 | S10: 4.39 | T10: 4.45 | U10: 4.42 | V10: 4.2 | W10: 4.38 | X10: 4.44 | Y10: 4.26 | Z10: 4.39 | AA10: 4.34 | AB10: 4.29 | AC10: 4.26 | AD10: 4.07 | AE10: 4.38 | AF10: 4.06 | AG10: 3.99 | AH10: 4.59 | AI10: 4.33 | AJ10: 4.15 | AK10: 4.01 | AL10: 4.65 | AM10: 4.61
C11: =IFERROR(IF(LANG="EN",INDEX(I18N_EN,MATCH("kpi.hsse.tg",I18N_KEY,0)),INDEX(I18N_FR,MATCH("kpi.hsse.tg",I18N_KEY,0))),"kpi.hsse.tg") | D11: 0.15 | E11: 0.15 | F11: 0.15 | G11: 0.15 | H11: 0.15 | I11: 0.15 | J11: 0.15 | K11: 0.15 | L11: 0.15 | M11: 0.15 | N11: 0.15 | O11: 0.15 | P11: 0.16 | Q11: 0.16 | R11: 0.15 | S11: 0.15 | T11: 0.16 | U11: 0.15 | V11: 0.16 | W11: 0.14 | X11: 0.16 | Y11: 0.16 | Z11: 0.16 | AA11: 0.15 | AB11: 0.15 | AC11: 0.16 | AD11: 0.16 | AE11: 0.16 | AF11: 0.15 | AG11: 0.14 | AH11: 0.16 | AI11: 0.16 | AJ11: 0.15 | AK11: 0.16 | AL11: 0.15 | AM11: 0.16
C12: =IFERROR(IF(LANG="EN",INDEX(I18N_EN,MATCH("kpi.hsse.nearmiss",I18N_KEY,0)),INDEX(I18N_FR,MATCH("kpi.hsse.nearmiss",I18N_KEY,0))),"kpi.hsse.nearmiss") | D12: 5 | E12: 5 | F12: 5 | G12: 5 | H12: 5 | I12: 5 | J12: 5 | K12: 5 | L12: 5 | M12: 5 | N12: 5 | O12: 5 | P12: 5 | Q12: 5 | R12: 5 | S12: 5 | T12: 5 | U12: 5 | V12: 5 | W12: 5 | X12: 5 | Y12: 5 | Z12: 5 | AA12: 5 | AB12: 5 | AC12: 5 | AD12: 5 | AE12: 5 | AF12: 5 | AG12: 5 | AH12: 5 | AI12: 5 | AJ12: 5 | AK12: 5 | AL12: 5 | AM12: 5
C13: =IFERROR(IF(LANG="EN",INDEX(I18N_EN,MATCH("kpi.hsse.days_no_lti",I18N_KEY,0)),INDEX(I18N_FR,MATCH("kpi.hsse.days_no_lti",I18N_KEY,0))),"kpi.hsse.days_no_lti") | D13: 119 | E13: 122 | F13: 121 | G13: 121 | H13: 118 | I13: 118 | J13: 123 | K13: 121 | L13: 124 | M13: 120 | N13: 119 | O13: 127 | P13: 121 | Q13: 122 | R13: 128 | S13: 117 | T13: 127 | U13: 125 | V13: 131 | W13: 122 | X13: 118 | Y13: 127 | Z13: 125 | AA13: 127 | AB13: 121 | AC13: 121 | AD13: 122 | AE13: 126 | AF13: 125 | AG13: 121 | AH13: 131 | AI13: 135 | AJ13: 124 | AK13: 131 | AL13: 137 | AM13: 135
C14: =IFERROR(IF(LANG="EN",INDEX(I18N_EN,MATCH("kpi.hsse.evac_drills",I18N_KEY,0)),INDEX(I18N_FR,MATCH("kpi.hsse.evac_drills",I18N_KEY,0))),"kpi.hsse.evac_drills") | D14: 1 | E14: 1 | F14: 1 | G14: 1 | H14: 1 | I14: 1 | J14: 1 | K14: 1 | L14: 1 | M14: 1 | N14: 1 | O14: 1 | P14: 1 | Q14: 1 | R14: 1 | S14: 1 | T14: 1 | U14: 1 | V14: 1 | W14: 1 | X14: 1 | Y14: 1 | Z14: 1 | AA14: 1 | AB14: 1 | AC14: 1 | AD14: 1 | AE14: 1 | AF14: 1 | AG14: 1 | AH14: 1 | AI14: 1 | AJ14: 1 | AK14: 1 | AL14: 1 | AM14: 1
C15: =IFERROR(IF(LANG="EN",INDEX(I18N_EN,MATCH("kpi.hsse.fire_conform",I18N_KEY,0)),INDEX(I18N_FR,MATCH("kpi.hsse.fire_conform",I18N_KEY,0))),"kpi.hsse.fire_conform") | D15: 0.9339 | E15: 0.9378 | F15: 0.9362 | G15: 0.936 | H15: 0.9429 | I15: 0.9279 | J15: 0.922 | K15: 0.9229 | L15: 0.9053 | M15: 0.942 | N15: 0.9211 | O15: 0.9462 | P15: 0.9392 | Q15: 0.9189 | R15: 0.9289 | S15: 0.9542 | T15: 0.9269 | U15: 0.9779 | V15: 0.9825 | W15: 0.9597 | X15: 0.9236 | Y15: 0.9157 | Z15: 0.9775 | AA15: 0.9412 | AB15: 0.9282 | AC15: 0.8981 | AD15: 0.9874 | AE15: 0.9934 | AF15: 0.9826 | AG15: 0.8802 | AH15: 0.9233 | AI15: 1.0456 | AJ15: 1.0532 | AK15: 0.9895 | AL15: 0.8744 | AM15: 0.9807
C16: =IFERROR(IF(LANG="EN",INDEX(I18N_EN,MATCH("kpi.hsse.fire_alarms",I18N_KEY,0)),INDEX(I18N_FR,MATCH("kpi.hsse.fire_alarms",I18N_KEY,0))),"kpi.hsse.fire_alarms") | D16: 3 | E16: 3 | F16: 3 | G16: 3 | H16: 3 | I16: 3 | J16: 3 | K16: 3 | L16: 3 | M16: 3 | N16: 3 | O16: 3 | P16: 3 | Q16: 3 | R16: 3 | S16: 3 | T16: 3 | U16: 3 | V16: 3 | W16: 3 | X16: 3 | Y16: 3 | Z16: 3 | AA16: 3 | AB16: 3 | AC16: 3 | AD16: 3 | AE16: 3 | AF16: 3 | AG16: 3 | AH16: 3 | AI16: 3 | AJ16: 3 | AK16: 3 | AL16: 3 | AM16: 3
C17: =IFERROR(IF(LANG="EN",INDEX(I18N_EN,MATCH("kpi.hsse.evac_time",I18N_KEY,0)),INDEX(I18N_FR,MATCH("kpi.hsse.evac_time",I18N_KEY,0))),"kpi.hsse.evac_time") | D17: 7.13 | E17: 6.93 | F17: 7.08 | G17: 7.04 | H17: 7.14 | I17: 7.08 | J17: 7.22 | K17: 7.09 | L17: 7.28 | M17: 7.03 | N17: 6.96 | O17: 6.91 | P17: 7.04 | Q17: 7.04 | R17: 7.09 | S17: 7.25 | T17: 7.29 | U17: 7.3 | V17: 7.4 | W17: 6.9 | X17: 7.23 | Y17: 7.1 | Z17: 6.94 | AA17: 7.54 | AB17: 7.34 | AC17: 7.24 | AD17: 7.25 | AE17: 7.64 | AF17: 7.19 | AG17: 6.71 | AH17: 7.18 | AI17: 7.44 | AJ17: 7.35 | AK17: 7.3 | AL17: 7.37 | AM17: 7.22
C18: =IFERROR(IF(LANG="EN",INDEX(I18N_EN,MATCH("kpi.hsse.sec_interv",I18N_KEY,0)),INDEX(I18N_FR,MATCH("kpi.hsse.sec_interv",I18N_KEY,0))),"kpi.hsse.sec_interv") | D18: 24 | E18: 24 | F18: 24 | G18: 23 | H18: 24 | I18: 24 | J18: 24 | K18: 24 | L18: 24 | M18: 24 | N18: 24 | O18: 24 | P18: 24 | Q18: 25 | R18: 24 | S18: 26 | T18: 24 | U18: 25 | V18: 25 | W18: 24 | X18: 23 | Y18: 25 | Z18: 26 | AA18: 25 | AB18: 26 | AC18: 25 | AD18: 25 | AE18: 24 | AF18: 23 | AG18: 24 | AH18: 26 | AI18: 26 | AJ18: 25 | AK18: 26 | AL18: 24 | AM18: 25
C19: =IFERROR(IF(LANG="EN",INDEX(I18N_EN,MATCH("kpi.hsse.theft",I18N_KEY,0)),INDEX(I18N_FR,MATCH("kpi.hsse.theft",I18N_KEY,0))),"kpi.hsse.theft") | D19: 3 | E19: 3 | F19: 3 | G19: 3 | H19: 3 | I19: 3 | J19: 3 | K19: 3 | L19: 3 | M19: 3 | N19: 3 | O19: 3 | P19: 3 | Q19: 3 | R19: 3 | S19: 3 | T19: 3 | U19: 3 | V19: 3 | W19: 3 | X19: 3 | Y19: 3 | Z19: 3 | AA19: 3 | AB19: 3 | AC19: 3 | AD19: 3 | AE19: 3 | AF19: 3 | AG19: 3 | AH19: 3 | AI19: 3 | AJ19: 3 | AK19: 3 | AL19: 3 | AM19: 3
C20: =IFERROR(IF(LANG="EN",INDEX(I18N_EN,MATCH("kpi.hsse.cctv",I18N_KEY,0)),INDEX(I18N_FR,MATCH("kpi.hsse.cctv",I18N_KEY,0))),"kpi.hsse.cctv") | D20: 0.9317 | E20: 0.948 | F20: 0.9615 | G20: 0.9427 | H20: 0.9433 | I20: 0.9456 | J20: 0.94 | K20: 0.9479 | L20: 0.9555 | M20: 0.9376 | N20: 0.9745 | O20: 0.9829 | P20: 0.9917 | Q20: 0.9776 | R20: 0.9245 | S20: 0.9901 | T20: 1.0229 | U20: 0.9158 | V20: 1.0012 | W20: 1.0051 | X20: 0.9524 | Y20: 0.988 | Z20: 0.9376 | AA20: 0.9468 | AB20: 1.0257 | AC20: 0.9827 | AD20: 0.9611 | AE20: 0.9636 | AF20: 0.9201 | AG20: 1.0242 | AH20: 1.0043 | AI20: 1.0318 | AJ20: 0.9577 | AK20: 0.9758 | AL20: 1.0019 | AM20: 1.0482
C21: =IFERROR(IF(LANG="EN",INDEX(I18N_EN,MATCH("kpi.hsse.guards",I18N_KEY,0)),INDEX(I18N_FR,MATCH("kpi.hsse.guards",I18N_KEY,0))),"kpi.hsse.guards") | D21: 18 | E21: 18 | F21: 18 | G21: 18 | H21: 18 | I21: 18 | J21: 19 | K21: 18 | L21: 18 | M21: 18 | N21: 18 | O21: 18 | P21: 19 | Q21: 18 | R21: 19 | S21: 19 | T21: 18 | U21: 19 | V21: 19 | W21: 19 | X21: 18 | Y21: 17 | Z21: 19 | AA21: 18 | AB21: 18 | AC21: 19 | AD21: 19 | AE21: 18 | AF21: 19 | AG21: 20 | AH21: 20 | AI21: 17 | AJ21: 19 | AK21: 17 | AL21: 17 | AM21: 20
C22: =IFERROR(IF(LANG="EN",INDEX(I18N_EN,MATCH("kpi.hsse.risks_id",I18N_KEY,0)),INDEX(I18N_FR,MATCH("kpi.hsse.risks_id",I18N_KEY,0))),"kpi.hsse.risks_id") | D22: 6 | E22: 6 | F22: 6 | G22: 6 | H22: 6 | I22: 6 | J22: 6 | K22: 6 | L22: 6 | M22: 6 | N22: 6 | O22: 6 | P22: 6 | Q22: 6 | R22: 6 | S22: 6 | T22: 6 | U22: 6 | V22: 6 | W22: 6 | X22: 6 | Y22: 6 | Z22: 6 | AA22: 6 | AB22: 6 | AC22: 7 | AD22: 6 | AE22: 6 | AF22: 6 | AG22: 6 | AH22: 6 | AI22: 6 | AJ22: 7 | AK22: 6 | AL22: 7 | AM22: 6
C23: =IFERROR(IF(LANG="EN",INDEX(I18N_EN,MATCH("kpi.hsse.risks_treated",I18N_KEY,0)),INDEX(I18N_FR,MATCH("kpi.hsse.risks_treated",I18N_KEY,0))),"kpi.hsse.risks_treated") | D23: 0.6894 | E23: 0.7108 | F23: 0.7034 | G23: 0.715 | H23: 0.7078 | I23: 0.7124 | J23: 0.7124 | K23: 0.7045 | L23: 0.7166 | M23: 0.7111 | N23: 0.714 | O23: 0.6963 | P23: 0.7268 | Q23: 0.7399 | R23: 0.7324 | S23: 0.7294 | T23: 0.7408 | U23: 0.7106 | V23: 0.7137 | W23: 0.7302 | X23: 0.6862 | Y23: 0.6942 | Z23: 0.7463 | AA23: 0.7542 | AB23: 0.6859 | AC23: 0.7053 | AD23: 0.7648 | AE23: 0.7631 | AF23: 0.7043 | AG23: 0.7576 | AH23: 0.7201 | AI23: 0.7705 | AJ23: 0.6901 | AK23: 0.6708 | AL23: 0.6787 | AM23: 0.6721
C24: =IFERROR(IF(LANG="EN",INDEX(I18N_EN,MATCH("kpi.hsse.action_close",I18N_KEY,0)),INDEX(I18N_FR,MATCH("kpi.hsse.action_close",I18N_KEY,0))),"kpi.hsse.action_close") | D24: 0.8091 | E24: 0.816 | F24: 0.8034 | G24: 0.8161 | H24: 0.8173 | I24: 0.8337 | J24: 0.8066 | K24: 0.8393 | L24: 0.8374 | M24: 0.8131 | N24: 0.81 | O24: 0.8276 | P24: 0.8201 | Q24: 0.8512 | R24: 0.8725 | S24: 0.8215 | T24: 0.8537 | U24: 0.8188 | V24: 0.8428 | W24: 0.8798 | X24: 0.8982 | Y24: 0.8458 | Z24: 0.8866 | AA24: 0.792 | AB24: 0.8782 | AC24: 0.8882 | AD24: 0.9027 | AE24: 0.8751 | AF24: 0.8322 | AG24: 0.8747 | AH24: 0.8417 | AI24: 0.8931 | AJ24: 0.8242 | AK24: 0.7885 | AL24: 0.8616 | AM24: 0.8535
C25: =IFERROR(IF(LANG="EN",INDEX(I18N_EN,MATCH("kpi.hsse.audits",I18N_KEY,0)),INDEX(I18N_FR,MATCH("kpi.hsse.audits",I18N_KEY,0))),"kpi.hsse.audits") | D25: 1 | E25: 1 | F25: 1 | G25: 1 | H25: 1 | I25: 1 | J25: 1 | K25: 1 | L25: 1 | M25: 1 | N25: 1 | O25: 1 | P25: 1 | Q25: 1 | R25: 1 | S25: 1 | T25: 1 | U25: 1 | V25: 1 | W25: 1 | X25: 1 | Y25: 1 | Z25: 1 | AA25: 1 | AB25: 1 | AC25: 1 | AD25: 1 | AE25: 1 | AF25: 1 | AG25: 1 | AH25: 1 | AI25: 1 | AJ25: 1 | AK25: 1 | AL25: 1 | AM25: 1
C26: =IFERROR(IF(LANG="EN",INDEX(I18N_EN,MATCH("kpi.hsse.train_cover",I18N_KEY,0)),INDEX(I18N_FR,MATCH("kpi.hsse.train_cover",I18N_KEY,0))),"kpi.hsse.train_cover") | D26: 0.702 | E26: 0.7006 | F26: 0.6956 | G26: 0.7189 | H26: 0.708 | I26: 0.7017 | J26: 0.7172 | K26: 0.7234 | L26: 0.7059 | M26: 0.7204 | N26: 0.706 | O26: 0.7057 | P26: 0.7352 | Q26: 0.6925 | R26: 0.7081 | S26: 0.6768 | T26: 0.6912 | U26: 0.6914 | V26: 0.7503 | W26: 0.6797 | X26: 0.6879 | Y26: 0.7203 | Z26: 0.7289 | AA26: 0.735 | AB26: 0.7011 | AC26: 0.6785 | AD26: 0.697 | AE26: 0.7173 | AF26: 0.7854 | AG26: 0.7503 | AH26: 0.7473 | AI26: 0.6673 | AJ26: 0.667 | AK26: 0.7667 | AL26: 0.6951 | AM26: 0.7213
C28: 💬 Commentaires (KPI × mois)
C29: =IFERROR(IF(LANG="EN",INDEX(I18N_EN,MATCH("kpi.hsse.incidents",I18N_KEY,0)),INDEX(I18N_FR,MATCH("kpi.hsse.incidents",I18N_KEY,0))),"kpi.hsse.incidents")
C30: =IFERROR(IF(LANG="EN",INDEX(I18N_EN,MATCH("kpi.hsse.incident_sev",I18N_KEY,0)),INDEX(I18N_FR,MATCH("kpi.hsse.incident_sev",I18N_KEY,0))),"kpi.hsse.incident_sev")
C31: =IFERROR(IF(LANG="EN",INDEX(I18N_EN,MATCH("kpi.hsse.tf",I18N_KEY,0)),INDEX(I18N_FR,MATCH("kpi.hsse.tf",I18N_KEY,0))),"kpi.hsse.tf")
C32: =IFERROR(IF(LANG="EN",INDEX(I18N_EN,MATCH("kpi.hsse.tg",I18N_KEY,0)),INDEX(I18N_FR,MATCH("kpi.hsse.tg",I18N_KEY,0))),"kpi.hsse.tg")
C33: =IFERROR(IF(LANG="EN",INDEX(I18N_EN,MATCH("kpi.hsse.nearmiss",I18N_KEY,0)),INDEX(I18N_FR,MATCH("kpi.hsse.nearmiss",I18N_KEY,0))),"kpi.hsse.nearmiss")
C34: =IFERROR(IF(LANG="EN",INDEX(I18N_EN,MATCH("kpi.hsse.days_no_lti",I18N_KEY,0)),INDEX(I18N_FR,MATCH("kpi.hsse.days_no_lti",I18N_KEY,0))),"kpi.hsse.days_no_lti")
C35: =IFERROR(IF(LANG="EN",INDEX(I18N_EN,MATCH("kpi.hsse.evac_drills",I18N_KEY,0)),INDEX(I18N_FR,MATCH("kpi.hsse.evac_drills",I18N_KEY,0))),"kpi.hsse.evac_drills")
C36: =IFERROR(IF(LANG="EN",INDEX(I18N_EN,MATCH("kpi.hsse.fire_conform",I18N_KEY,0)),INDEX(I18N_FR,MATCH("kpi.hsse.fire_conform",I18N_KEY,0))),"kpi.hsse.fire_conform")
C37: =IFERROR(IF(LANG="EN",INDEX(I18N_EN,MATCH("kpi.hsse.fire_alarms",I18N_KEY,0)),INDEX(I18N_FR,MATCH("kpi.hsse.fire_alarms",I18N_KEY,0))),"kpi.hsse.fire_alarms")
C38: =IFERROR(IF(LANG="EN",INDEX(I18N_EN,MATCH("kpi.hsse.evac_time",I18N_KEY,0)),INDEX(I18N_FR,MATCH("kpi.hsse.evac_time",I18N_KEY,0))),"kpi.hsse.evac_time")
C39: =IFERROR(IF(LANG="EN",INDEX(I18N_EN,MATCH("kpi.hsse.sec_interv",I18N_KEY,0)),INDEX(I18N_FR,MATCH("kpi.hsse.sec_interv",I18N_KEY,0))),"kpi.hsse.sec_interv")
C40: =IFERROR(IF(LANG="EN",INDEX(I18N_EN,MATCH("kpi.hsse.theft",I18N_KEY,0)),INDEX(I18N_FR,MATCH("kpi.hsse.theft",I18N_KEY,0))),"kpi.hsse.theft")
C41: =IFERROR(IF(LANG="EN",INDEX(I18N_EN,MATCH("kpi.hsse.cctv",I18N_KEY,0)),INDEX(I18N_FR,MATCH("kpi.hsse.cctv",I18N_KEY,0))),"kpi.hsse.cctv")
C42: =IFERROR(IF(LANG="EN",INDEX(I18N_EN,MATCH("kpi.hsse.guards",I18N_KEY,0)),INDEX(I18N_FR,MATCH("kpi.hsse.guards",I18N_KEY,0))),"kpi.hsse.guards")
C43: =IFERROR(IF(LANG="EN",INDEX(I18N_EN,MATCH("kpi.hsse.risks_id",I18N_KEY,0)),INDEX(I18N_FR,MATCH("kpi.hsse.risks_id",I18N_KEY,0))),"kpi.hsse.risks_id")
C44: =IFERROR(IF(LANG="EN",INDEX(I18N_EN,MATCH("kpi.hsse.risks_treated",I18N_KEY,0)),INDEX(I18N_FR,MATCH("kpi.hsse.risks_treated",I18N_KEY,0))),"kpi.hsse.risks_treated")
C45: =IFERROR(IF(LANG="EN",INDEX(I18N_EN,MATCH("kpi.hsse.action_close",I18N_KEY,0)),INDEX(I18N_FR,MATCH("kpi.hsse.action_close",I18N_KEY,0))),"kpi.hsse.action_close")
C46: =IFERROR(IF(LANG="EN",INDEX(I18N_EN,MATCH("kpi.hsse.audits",I18N_KEY,0)),INDEX(I18N_FR,MATCH("kpi.hsse.audits",I18N_KEY,0))),"kpi.hsse.audits")
C47: =IFERROR(IF(LANG="EN",INDEX(I18N_EN,MATCH("kpi.hsse.train_cover",I18N_KEY,0)),INDEX(I18N_FR,MATCH("kpi.hsse.train_cover",I18N_KEY,0))),"kpi.hsse.train_cover")

Sheet C8 · Facility
C1: ="▌ "&IFERROR(IF(LANG="EN",INDEX(I18N_EN,MATCH("msg.collect",I18N_KEY,0)),INDEX(I18N_FR,MATCH("msg.collect",I18N_KEY,0))),"msg.collect")&" · "&IFERROR(IF(LANG="EN",INDEX(I18N_EN,MATCH("dept.fac",I18N_KEY,0)),INDEX(I18N_FR,MATCH("dept.fac",I18N_KEY,0))),"dept.fac")
C2: =IFERROR(IF(LANG="EN",INDEX(I18N_EN,MATCH("msg.help",I18N_KEY,0)),INDEX(I18N_FR,MATCH("msg.help",I18N_KEY,0))),"msg.help")
C6: KPI \ Mois | D6: =DATE(2024,1,1) | E6: =DATE(2024,2,1) | F6: =DATE(2024,3,1) | G6: =DATE(2024,4,1) | H6: =DATE(2024,5,1) | I6: =DATE(2024,6,1) | J6: =DATE(2024,7,1) | K6: =DATE(2024,8,1) | L6: =DATE(2024,9,1) | M6: =DATE(2024,10,1) | N6: =DATE(2024,11,1) | O6: =DATE(2024,12,1) | P6: =DATE(2025,1,1) | Q6: =DATE(2025,2,1) | R6: =DATE(2025,3,1) | S6: =DATE(2025,4,1) | T6: =DATE(2025,5,1) | U6: =DATE(2025,6,1) | V6: =DATE(2025,7,1) | W6: =DATE(2025,8,1) | X6: =DATE(2025,9,1) | Y6: =DATE(2025,10,1) | Z6: =DATE(2025,11,1) | AA6: =DATE(2025,12,1) | AB6: =DATE(2026,1,1) | AC6: =DATE(2026,2,1) | AD6: =DATE(2026,3,1) | AE6: =DATE(2026,4,1) | AF6: =DATE(2026,5,1) | AG6: =DATE(2026,6,1) | AH6: =DATE(2026,7,1) | AI6: =DATE(2026,8,1) | AJ6: =DATE(2026,9,1) | AK6: =DATE(2026,10,1) | AL6: =DATE(2026,11,1) | AM6: =DATE(2026,12,1)
C8: =IFERROR(IF(LANG="EN",INDEX(I18N_EN,MATCH("kpi.fac.prev_corr",I18N_KEY,0)),INDEX(I18N_FR,MATCH("kpi.fac.prev_corr",I18N_KEY,0))),"kpi.fac.prev_corr") | D8: 0.6387 | E8: 0.6531 | F8: 0.6473 | G8: 0.6548 | H8: 0.6523 | I8: 0.6449 | J8: 0.6607 | K8: 0.6695 | L8: 0.664 | M8: 0.6666 | N8: 0.6449 | O8: 0.6465 | P8: 0.6494 | Q8: 0.6492 | R8: 0.6638 | S8: 0.6654 | T8: 0.6549 | U8: 0.6731 | V8: 0.6525 | W8: 0.7067 | X8: 0.6646 | Y8: 0.6818 | Z8: 0.6507 | AA8: 0.6474 | AB8: 0.6846 | AC8: 0.6323 | AD8: 0.7158 | AE8: 0.6593 | AF8: 0.6555 | AG8: 0.7035 | AH8: 0.7016 | AI8: 0.7369 | AJ8: 0.6617 | AK8: 0.7404 | AL8: 0.6625 | AM8: 0.6841
C9: =IFERROR(IF(LANG="EN",INDEX(I18N_EN,MATCH("kpi.fac.wo_prev",I18N_KEY,0)),INDEX(I18N_FR,MATCH("kpi.fac.wo_prev",I18N_KEY,0))),"kpi.fac.wo_prev") | D9: 42 | E9: 41 | F9: 42 | G9: 42 | H9: 42 | I9: 42 | J9: 43 | K9: 41 | L9: 41 | M9: 42 | N9: 43 | O9: 41 | P9: 41 | Q9: 44 | R9: 42 | S9: 41 | T9: 45 | U9: 41 | V9: 43 | W9: 42 | X9: 42 | Y9: 45 | Z9: 46 | AA9: 47 | AB9: 45 | AC9: 42 | AD9: 45 | AE9: 43 | AF9: 45 | AG9: 41 | AH9: 44 | AI9: 45 | AJ9: 42 | AK9: 47 | AL9: 48 | AM9: 47
C10: =IFERROR(IF(LANG="EN",INDEX(I18N_EN,MATCH("kpi.fac.wo_corr",I18N_KEY,0)),INDEX(I18N_FR,MATCH("kpi.fac.wo_corr",I18N_KEY,0))),"kpi.fac.wo_corr") | D10: 23 | E10: 23 | F10: 23 | G10: 23 | H10: 23 | I10: 23 | J10: 24 | K10: 23 | L10: 24 | M10: 23 | N10: 23 | O10: 24 | P10: 23 | Q10: 24 | R10: 23 | S10: 22 | T10: 23 | U10: 24 | V10: 24 | W10: 23 | X10: 24 | Y10: 23 | Z10: 23 | AA10: 23 | AB10: 25 | AC10: 25 | AD10: 25 | AE10: 22 | AF10: 23 | AG10: 23 | AH10: 25 | AI10: 23 | AJ10: 27 | AK10: 25 | AL10: 26 | AM10: 24
C11: =IFERROR(IF(LANG="EN",INDEX(I18N_EN,MATCH("kpi.fac.ot_backlog",I18N_KEY,0)),INDEX(I18N_FR,MATCH("kpi.fac.ot_backlog",I18N_KEY,0))),"kpi.fac.ot_backlog") | D11: 12 | E11: 12 | F11: 12 | G11: 12 | H11: 12 | I11: 12 | J11: 12 | K11: 12 | L11: 12 | M11: 12 | N11: 12 | O11: 12 | P11: 12 | Q11: 12 | R11: 12 | S11: 12 | T11: 13 | U11: 12 | V11: 12 | W11: 12 | X11: 12 | Y11: 13 | Z11: 13 | AA11: 13 | AB11: 13 | AC11: 13 | AD11: 12 | AE11: 12 | AF11: 13 | AG11: 13 | AH11: 12 | AI11: 12 | AJ11: 12 | AK11: 12 | AL11: 12 | AM11: 13
C12: =IFERROR(IF(LANG="EN",INDEX(I18N_EN,MATCH("kpi.fac.mttr",I18N_KEY,0)),INDEX(I18N_FR,MATCH("kpi.fac.mttr",I18N_KEY,0))),"kpi.fac.mttr") | D12: 6.5 | E12: 6.59 | F12: 6.42 | G12: 6.49 | H12: 6.42 | I12: 6.73 | J12: 6.4 | K12: 6.6 | L12: 6.59 | M12: 6.75 | N12: 6.64 | O12: 6.38 | P12: 6.34 | Q12: 6.65 | R12: 6.75 | S12: 6.84 | T12: 6.76 | U12: 6.62 | V12: 6.69 | W12: 6.77 | X12: 6.85 | Y12: 6.38 | Z12: 7.09 | AA12: 6.78 | AB12: 6.46 | AC12: 6.75 | AD12: 6.59 | AE12: 6.56 | AF12: 6.65 | AG12: 7.04 | AH12: 6.46 | AI12: 7.37 | AJ12: 7.28 | AK12: 6.39 | AL12: 6.58 | AM12: 6.51
C13: =IFERROR(IF(LANG="EN",INDEX(I18N_EN,MATCH("kpi.fac.ot_opened",I18N_KEY,0)),INDEX(I18N_FR,MATCH("kpi.fac.ot_opened",I18N_KEY,0))),"kpi.fac.ot_opened") | D13: 64 | E13: 66 | F13: 66 | G13: 65 | H13: 64 | I13: 66 | J13: 66 | K13: 65 | L13: 66 | M13: 65 | N13: 66 | O13: 63 | P13: 65 | Q13: 65 | R13: 68 | S13: 64 | T13: 64 | U13: 67 | V13: 69 | W13: 69 | X13: 69 | Y13: 66 | Z13: 62 | AA13: 70 | AB13: 71 | AC13: 64 | AD13: 68 | AE13: 65 | AF13: 69 | AG13: 73 | AH13: 71 | AI13: 64 | AJ13: 63 | AK13: 68 | AL13: 65 | AM13: 73
C14: =IFERROR(IF(LANG="EN",INDEX(I18N_EN,MATCH("kpi.fac.ot_closed",I18N_KEY,0)),INDEX(I18N_FR,MATCH("kpi.fac.ot_closed",I18N_KEY,0))),"kpi.fac.ot_closed") | D14: 58 | E14: 58 | F14: 58 | G14: 57 | H14: 59 | I14: 57 | J14: 57 | K14: 60 | L14: 58 | M14: 61 | N14: 59 | O14: 60 | P14: 60 | Q14: 62 | R14: 59 | S14: 61 | T14: 61 | U14: 59 | V14: 60 | W14: 60 | X14: 61 | Y14: 58 | Z14: 62 | AA14: 62 | AB14: 60 | AC14: 59 | AD14: 56 | AE14: 57 | AF14: 62 | AG14: 62 | AH14: 59 | AI14: 63 | AJ14: 66 | AK14: 57 | AL14: 64 | AM14: 58
C15: =IFERROR(IF(LANG="EN",INDEX(I18N_EN,MATCH("kpi.fac.energy_int",I18N_KEY,0)),INDEX(I18N_FR,MATCH("kpi.fac.energy_int",I18N_KEY,0))),"kpi.fac.energy_int") | D15: 14.09 | E15: 14.1 | F15: 14.14 | G15: 13.93 | H15: 13.78 | I15: 14.01 | J15: 14.05 | K15: 13.77 | L15: 13.95 | M15: 14.66 | N15: 13.75 | O15: 14.31 | P15: 14.31 | Q15: 13.78 | R15: 14.01 | S15: 14.33 | T15: 14.44 | U15: 14.93 | V15: 13.85 | W15: 14.52 | X15: 15 | Y15: 14.64 | Z15: 14.43 | AA15: 15.17 | AB15: 14.47 | AC15: 14.82 | AD15: 14.42 | AE15: 14.33 | AF15: 13.4 | AG15: 14.32 | AH15: 13.58 | AI15: 14.75 | AJ15: 14.86 | AK15: 16.09 | AL15: 14.33 | AM15: 15.14
C16: =IFERROR(IF(LANG="EN",INDEX(I18N_EN,MATCH("kpi.fac.util_cost",I18N_KEY,0)),INDEX(I18N_FR,MATCH("kpi.fac.util_cost",I18N_KEY,0))),"kpi.fac.util_cost") | D16: 1.011 | E16: 1.0292 | F16: 1.0211 | G16: 1.0232 | H16: 1.0548 | I16: 1.0372 | J16: 1.0536 | K16: 1.0641 | L16: 1.0423 | M16: 1.0315 | N16: 1.0597 | O16: 1.065 | P16: 1.029 | Q16: 1.0529 | R16: 1.0776 | S16: 1.0621 | T16: 1.085 | U16: 1.0925 | V16: 1.0821 | W16: 1.0472 | X16: 1.0639 | Y16: 1.0222 | Z16: 1.1295 | AA16: 1.0401 | AB16: 1.0683 | AC16: 1.0833 | AD16: 1.1005 | AE16: 1.0303 | AF16: 1.1299 | AG16: 1.0474 | AH16: 1.1732 | AI16: 0.967 | AJ16: 1.1151 | AK16: 1.1182 | AL16: 1.009 | AM16: 1.1111
C17: =IFERROR(IF(LANG="EN",INDEX(I18N_EN,MATCH("kpi.fac.consumption",I18N_KEY,0)),INDEX(I18N_FR,MATCH("kpi.fac.consumption",I18N_KEY,0))),"kpi.fac.consumption") | D17: 32574 | E17: 32439 | F17: 31412 | G17: 32295 | H17: 32522 | I17: 32308 | J17: 32882 | K17: 31628 | L17: 31901 | M17: 32261 | N17: 32638 | O17: 31138 | P17: 32470 | Q17: 33414 | R17: 31637 | S17: 31466 | T17: 34490 | U17: 34086 | V17: 32196 | W17: 32919 | X17: 35146 | Y17: 34865 | Z17: 31950 | AA17: 32229 | AB17: 31287 | AC17: 34338 | AD17: 34571 | AE17: 34210 | AF17: 32406 | AG17: 34828 | AH17: 34224 | AI17: 33165 | AJ17: 32259 | AK17: 36670 | AL17: 30370 | AM17: 31087
C18: =IFERROR(IF(LANG="EN",INDEX(I18N_EN,MATCH("kpi.fac.capex",I18N_KEY,0)),INDEX(I18N_FR,MATCH("kpi.fac.capex",I18N_KEY,0))),"kpi.fac.capex") | D18: 44899751 | E18: 44912036 | F18: 44432941 | G18: 45913920 | H18: 46576666 | I18: 46509922 | J18: 45376125 | K18: 44258829 | L18: 45684947 | M18: 46412661 | N18: 45220207 | O18: 45456754 | P18: 46596461 | Q18: 44629378 | R18: 44809199 | S18: 44445860 | T18: 47358066 | U18: 44180896 | V18: 46544251 | W18: 49042008 | X18: 47151979 | Y18: 44998538 | Z18: 47984638 | AA18: 44386509 | AB18: 47196781 | AC18: 48509537 | AD18: 50037593 | AE18: 47693893 | AF18: 46305871 | AG18: 48411161 | AH18: 48136208 | AI18: 50387015 | AJ18: 44090603 | AK18: 42883053 | AL18: 50076061 | AM18: 48760551
C19: =IFERROR(IF(LANG="EN",INDEX(I18N_EN,MATCH("kpi.fac.capex_var",I18N_KEY,0)),INDEX(I18N_FR,MATCH("kpi.fac.capex_var",I18N_KEY,0))),"kpi.fac.capex_var") | D19: 0.9736 | E19: 0.9668 | F19: 0.9405 | G19: 0.978 | H19: 0.9691 | I19: 0.97 | J19: 0.9787 | K19: 0.9628 | L19: 0.9678 | M19: 0.9568 | N19: 1.011 | O19: 0.9734 | P19: 0.9695 | Q19: 1.0012 | R19: 0.9986 | S19: 0.9837 | T19: 0.968 | U19: 1.0017 | V19: 1.017 | W19: 1.0026 | X19: 1.0338 | Y19: 1.0155 | Z19: 1.0302 | AA19: 0.9996 | AB19: 1.0287 | AC19: 0.9884 | AD19: 1.0709 | AE19: 1.0675 | AF19: 0.9995 | AG19: 1.0469 | AH19: 1.0394 | AI19: 0.9989 | AJ19: 1.0266 | AK19: 1.0657 | AL19: 0.9475 | AM19: 1.0351
C20: =IFERROR(IF(LANG="EN",INDEX(I18N_EN,MATCH("kpi.fac.capex_proj",I18N_KEY,0)),INDEX(I18N_FR,MATCH("kpi.fac.capex_proj",I18N_KEY,0))),"kpi.fac.capex_proj") | D20: 4 | E20: 4 | F20: 4 | G20: 4 | H20: 4 | I20: 4 | J20: 4 | K20: 4 | L20: 4 | M20: 4 | N20: 4 | O20: 4 | P20: 4 | Q20: 4 | R20: 4 | S20: 4 | T20: 4 | U20: 4 | V20: 4 | W20: 4 | X20: 4 | Y20: 4 | Z20: 4 | AA20: 4 | AB20: 4 | AC20: 4 | AD20: 4 | AE20: 4 | AF20: 4 | AG20: 4 | AH20: 4 | AI20: 4 | AJ20: 4 | AK20: 4 | AL20: 4 | AM20: 4
C21: =IFERROR(IF(LANG="EN",INDEX(I18N_EN,MATCH("kpi.fac.inspections",I18N_KEY,0)),INDEX(I18N_FR,MATCH("kpi.fac.inspections",I18N_KEY,0))),"kpi.fac.inspections") | D21: 8 | E21: 8 | F21: 8 | G21: 8 | H21: 8 | I21: 8 | J21: 8 | K21: 8 | L21: 8 | M21: 8 | N21: 8 | O21: 8 | P21: 8 | Q21: 8 | R21: 8 | S21: 8 | T21: 8 | U21: 8 | V21: 8 | W21: 9 | X21: 8 | Y21: 8 | Z21: 8 | AA21: 8 | AB21: 9 | AC21: 8 | AD21: 8 | AE21: 8 | AF21: 8 | AG21: 8 | AH21: 8 | AI21: 9 | AJ21: 8 | AK21: 9 | AL21: 8 | AM21: 9
C22: =IFERROR(IF(LANG="EN",INDEX(I18N_EN,MATCH("kpi.fac.insp_conform",I18N_KEY,0)),INDEX(I18N_FR,MATCH("kpi.fac.insp_conform",I18N_KEY,0))),"kpi.fac.insp_conform") | D22: 0.8971 | E22: 0.9172 | F22: 0.8848 | G22: 0.8902 | H22: 0.8834 | I22: 0.892 | J22: 0.9071 | K22: 0.8948 | L22: 0.9156 | M22: 0.8845 | N22: 0.9326 | O22: 0.9071 | P22: 0.9036 | Q22: 0.9153 | R22: 0.9183 | S22: 0.9479 | T22: 0.9287 | U22: 0.9447 | V22: 0.9605 | W22: 0.918 | X22: 0.975 | Y22: 0.9498 | Z22: 0.9123 | AA22: 0.872 | AB22: 0.8749 | AC22: 0.925 | AD22: 0.8818 | AE22: 1.0081 | AF22: 0.9038 | AG22: 0.9567 | AH22: 1.0243 | AI22: 0.9321 | AJ22: 0.9452 | AK22: 1.0185 | AL22: 0.9225 | AM22: 1.0222
C23: =IFERROR(IF(LANG="EN",INDEX(I18N_EN,MATCH("kpi.fac.nonconform",I18N_KEY,0)),INDEX(I18N_FR,MATCH("kpi.fac.nonconform",I18N_KEY,0))),"kpi.fac.nonconform") | D23: 5 | E23: 5 | F23: 5 | G23: 5 | H23: 5 | I23: 5 | J23: 5 | K23: 5 | L23: 5 | M23: 5 | N23: 5 | O23: 5 | P23: 5 | Q23: 5 | R23: 5 | S23: 5 | T23: 5 | U23: 5 | V23: 5 | W23: 5 | X23: 5 | Y23: 5 | Z23: 5 | AA23: 5 | AB23: 5 | AC23: 5 | AD23: 5 | AE23: 5 | AF23: 5 | AG23: 5 | AH23: 6 | AI23: 5 | AJ23: 5 | AK23: 5 | AL23: 5 | AM23: 5
C24: =IFERROR(IF(LANG="EN",INDEX(I18N_EN,MATCH("kpi.fac.cleanliness",I18N_KEY,0)),INDEX(I18N_FR,MATCH("kpi.fac.cleanliness",I18N_KEY,0))),"kpi.fac.cleanliness") | D24: 8.29 | E24: 8.27 | F24: 8.28 | G24: 8.32 | H24: 8.37 | I24: 8.43 | J24: 8.36 | K24: 8.39 | L24: 8.48 | M24: 8.32 | N24: 8.57 | O24: 8.43 | P24: 8.59 | Q24: 8.26 | R24: 8.22 | S24: 8.89 | T24: 8.23 | U24: 8.64 | V24: 8.39 | W24: 8.77 | X24: 8.79 | Y24: 9.05 | Z24: 8.81 | AA24: 9.02 | AB24: 8.11 | AC24: 8.01 | AD24: 8.8 | AE24: 8.44 | AF24: 8.68 | AG24: 9.06 | AH24: 8.45 | AI24: 9.08 | AJ24: 8.25 | AK24: 8.49 | AL24: 9.57 | AM24: 8.5
C25: =IFERROR(IF(LANG="EN",INDEX(I18N_EN,MATCH("kpi.fac.hygiene_audits",I18N_KEY,0)),INDEX(I18N_FR,MATCH("kpi.fac.hygiene_audits",I18N_KEY,0))),"kpi.fac.hygiene_audits") | D25: 4 | E25: 4 | F25: 4 | G25: 4 | H25: 4 | I25: 4 | J25: 4 | K25: 4 | L25: 4 | M25: 4 | N25: 4 | O25: 4 | P25: 4 | Q25: 4 | R25: 4 | S25: 4 | T25: 4 | U25: 4 | V25: 4 | W25: 4 | X25: 4 | Y25: 4 | Z25: 4 | AA25: 4 | AB25: 4 | AC25: 4 | AD25: 4 | AE25: 4 | AF25: 4 | AG25: 4 | AH25: 4 | AI25: 4 | AJ25: 4 | AK25: 4 | AL25: 4 | AM25: 4
C26: =IFERROR(IF(LANG="EN",INDEX(I18N_EN,MATCH("kpi.fac.clean_complaints",I18N_KEY,0)),INDEX(I18N_FR,MATCH("kpi.fac.clean_complaints",I18N_KEY,0))),"kpi.fac.clean_complaints") | D26: 3 | E26: 3 | F26: 3 | G26: 3 | H26: 3 | I26: 3 | J26: 3 | K26: 3 | L26: 3 | M26: 3 | N26: 3 | O26: 3 | P26: 3 | Q26: 3 | R26: 3 | S26: 3 | T26: 3 | U26: 3 | V26: 3 | W26: 3 | X26: 3 | Y26: 3 | Z26: 3 | AA26: 3 | AB26: 3 | AC26: 3 | AD26: 3 | AE26: 3 | AF26: 3 | AG26: 3 | AH26: 3 | AI26: 3 | AJ26: 3 | AK26: 3 | AL26: 3 | AM26: 3
C27: =IFERROR(IF(LANG="EN",INDEX(I18N_EN,MATCH("kpi.fac.sla",I18N_KEY,0)),INDEX(I18N_FR,MATCH("kpi.fac.sla",I18N_KEY,0))),"kpi.fac.sla") | D27: 0.9235 | E27: 0.9407 | F27: 0.9257 | G27: 0.9294 | H27: 0.9467 | I27: 0.9597 | J27: 0.9323 | K27: 0.9441 | L27: 0.9609 | M27: 0.9503 | N27: 0.9497 | O27: 0.9341 | P27: 0.975 | Q27: 0.9135 | R27: 0.9605 | S27: 0.9669 | T27: 0.9125 | U27: 0.9737 | V27: 0.9615 | W27: 0.9523 | X27: 0.9088 | Y27: 0.9501 | Z27: 0.893 | AA27: 0.9446 | AB27: 1.007 | AC27: 0.9752 | AD27: 1.0109 | AE27: 0.9305 | AF27: 1.0256 | AG27: 0.9738 | AH27: 0.9142 | AI27: 0.9171 | AJ27: 0.9071 | AK27: 1.0395 | AL27: 1.0118 | AM27: 1.004
C29: 💬 Commentaires (KPI × mois)
C30: =IFERROR(IF(LANG="EN",INDEX(I18N_EN,MATCH("kpi.fac.prev_corr",I18N_KEY,0)),INDEX(I18N_FR,MATCH("kpi.fac.prev_corr",I18N_KEY,0))),"kpi.fac.prev_corr")
C31: =IFERROR(IF(LANG="EN",INDEX(I18N_EN,MATCH("kpi.fac.wo_prev",I18N_KEY,0)),INDEX(I18N_FR,MATCH("kpi.fac.wo_prev",I18N_KEY,0))),"kpi.fac.wo_prev")
C32: =IFERROR(IF(LANG="EN",INDEX(I18N_EN,MATCH("kpi.fac.wo_corr",I18N_KEY,0)),INDEX(I18N_FR,MATCH("kpi.fac.wo_corr",I18N_KEY,0))),"kpi.fac.wo_corr")
C33: =IFERROR(IF(LANG="EN",INDEX(I18N_EN,MATCH("kpi.fac.ot_backlog",I18N_KEY,0)),INDEX(I18N_FR,MATCH("kpi.fac.ot_backlog",I18N_KEY,0))),"kpi.fac.ot_backlog")
C34: =IFERROR(IF(LANG="EN",INDEX(I18N_EN,MATCH("kpi.fac.mttr",I18N_KEY,0)),INDEX(I18N_FR,MATCH("kpi.fac.mttr",I18N_KEY,0))),"kpi.fac.mttr")
C35: =IFERROR(IF(LANG="EN",INDEX(I18N_EN,MATCH("kpi.fac.ot_opened",I18N_KEY,0)),INDEX(I18N_FR,MATCH("kpi.fac.ot_opened",I18N_KEY,0))),"kpi.fac.ot_opened")
C36: =IFERROR(IF(LANG="EN",INDEX(I18N_EN,MATCH("kpi.fac.ot_closed",I18N_KEY,0)),INDEX(I18N_FR,MATCH("kpi.fac.ot_closed",I18N_KEY,0))),"kpi.fac.ot_closed")
C37: =IFERROR(IF(LANG="EN",INDEX(I18N_EN,MATCH("kpi.fac.energy_int",I18N_KEY,0)),INDEX(I18N_FR,MATCH("kpi.fac.energy_int",I18N_KEY,0))),"kpi.fac.energy_int")
C38: =IFERROR(IF(LANG="EN",INDEX(I18N_EN,MATCH("kpi.fac.util_cost",I18N_KEY,0)),INDEX(I18N_FR,MATCH("kpi.fac.util_cost",I18N_KEY,0))),"kpi.fac.util_cost")
C39: =IFERROR(IF(LANG="EN",INDEX(I18N_EN,MATCH("kpi.fac.consumption",I18N_KEY,0)),INDEX(I18N_FR,MATCH("kpi.fac.consumption",I18N_KEY,0))),"kpi.fac.consumption")
C40: =IFERROR(IF(LANG="EN",INDEX(I18N_EN,MATCH("kpi.fac.capex",I18N_KEY,0)),INDEX(I18N_FR,MATCH("kpi.fac.capex",I18N_KEY,0))),"kpi.fac.capex")
C41: =IFERROR(IF(LANG="EN",INDEX(I18N_EN,MATCH("kpi.fac.capex_var",I18N_KEY,0)),INDEX(I18N_FR,MATCH("kpi.fac.capex_var",I18N_KEY,0))),"kpi.fac.capex_var")
C42: =IFERROR(IF(LANG="EN",INDEX(I18N_EN,MATCH("kpi.fac.capex_proj",I18N_KEY,0)),INDEX(I18N_FR,MATCH("kpi.fac.capex_proj",I18N_KEY,0))),"kpi.fac.capex_proj")
C43: =IFERROR(IF(LANG="EN",INDEX(I18N_EN,MATCH("kpi.fac.inspections",I18N_KEY,0)),INDEX(I18N_FR,MATCH("kpi.fac.inspections",I18N_KEY,0))),"kpi.fac.inspections")
C44: =IFERROR(IF(LANG="EN",INDEX(I18N_EN,MATCH("kpi.fac.insp_conform",I18N_KEY,0)),INDEX(I18N_FR,MATCH("kpi.fac.insp_conform",I18N_KEY,0))),"kpi.fac.insp_conform")
C45: =IFERROR(IF(LANG="EN",INDEX(I18N_EN,MATCH("kpi.fac.nonconform",I18N_KEY,0)),INDEX(I18N_FR,MATCH("kpi.fac.nonconform",I18N_KEY,0))),"kpi.fac.nonconform")
C46: =IFERROR(IF(LANG="EN",INDEX(I18N_EN,MATCH("kpi.fac.cleanliness",I18N_KEY,0)),INDEX(I18N_FR,MATCH("kpi.fac.cleanliness",I18N_KEY,0))),"kpi.fac.cleanliness")
C47: =IFERROR(IF(LANG="EN",INDEX(I18N_EN,MATCH("kpi.fac.hygiene_audits",I18N_KEY,0)),INDEX(I18N_FR,MATCH("kpi.fac.hygiene_audits",I18N_KEY,0))),"kpi.fac.hygiene_audits")
C48: =IFERROR(IF(LANG="EN",INDEX(I18N_EN,MATCH("kpi.fac.clean_complaints",I18N_KEY,0)),INDEX(I18N_FR,MATCH("kpi.fac.clean_complaints",I18N_KEY,0))),"kpi.fac.clean_complaints")
C49: =IFERROR(IF(LANG="EN",INDEX(I18N_EN,MATCH("kpi.fac.sla",I18N_KEY,0)),INDEX(I18N_FR,MATCH("kpi.fac.sla",I18N_KEY,0))),"kpi.fac.sla")

Sheet M4 · Dictionnaire
C1: ="↩ "&IFERROR(IF(LANG="EN",INDEX(I18N_EN,MATCH("nav.title",I18N_KEY,0)),INDEX(I18N_FR,MATCH("nav.title",I18N_KEY,0))),"nav.title")
C2: M4 · Dictionnaire KPI & Méthodologie
C5: Clé | D5: FR | E5: EN | F5: Unité | G5: Agg | H5: Dépt | I5: Budget | J5: Sous-module H2
C6: kpi.rh.headcount | D6: Effectif (ETP) | E6: Headcount (FTE) | F6: ETP | G6: LAST | H6: rh | J6: Effectifs
C7: kpi.rh.fte_gap | D7: Écart ETP vs budget | E7: FTE gap vs budget | F7: ETP | G7: LAST | H7: rh | I7: ✓ | J7: Effectifs
C8: kpi.rh.open_pos | D8: Postes ouverts | E8: Open positions | F8: nb | G8: LAST | H8: rh | J8: Recrutement
C9: kpi.rh.ttf | D9: Time-to-fill | E9: Time-to-fill | F9: j | G9: AVG | H9: rh | J9: Recrutement
C10: kpi.rh.payroll | D10: Masse salariale | E10: Payroll | F10: FCFA | G10: SUM | H10: rh | I10: ✓ | J10: Masse salariale
C11: kpi.rh.payroll_var | D11: Masse sal. vs budget | E11: Payroll vs budget | F11: % | G11: RATIO | H11: rh | J11: Masse salariale
C12: kpi.rh.turnover | D12: Turnover | E12: Turnover | F12: % | G12: AVG | H12: rh | J12: Climat social
C13: kpi.rh.absence | D13: Absentéisme | E13: Absenteeism | F13: % | G13: AVG | H13: rh | J13: Climat social
C14: kpi.rh.train_hours | D14: Heures form./agent | E14: Training hrs/FTE | F14: h | G14: AVG | H14: rh | J14: Formation
C15: kpi.rh.train_cover | D15: Couverture formation | E15: Training coverage | F15: % | G15: AVG | H15: rh | J15: Formation
C16: kpi.lease.occ_gla | D16: Occupation (GLA) | E16: Occupancy (GLA) | F16: % | G16: AVG | H16: lease | I16: ✓ | J16: Occupation
C17: kpi.lease.occ_unit | D17: Occupation (unités) | E17: Occupancy (units) | F17: % | G17: AVG | H17: lease | J17: Occupation
C18: kpi.lease.gla_vacant | D18: GLA vacant | E18: Vacant GLA | F18: m² | G18: LAST | H18: lease | J18: Vacance & rétention
C19: kpi.lease.ocr | D19: Taux d'effort (OCR) | E19: Occupancy Cost Ratio | F19: % | G19: RATIO | H19: lease | I19: ✓ | J19: Effort locataire
C20: kpi.lease.passing | D20: Loyer en place | E20: Passing rent | F20: FCFA | G20: LAST | H20: lease | I20: ✓ | J20: Loyers & réversion
C21: kpi.lease.erv | D21: Valeur locative (ERV) | E21: Est. Rental Value | F21: FCFA | G21: LAST | H21: lease | J21: Loyers & réversion
C22: kpi.lease.reversion | D22: Réversion | E22: Reversion | F22: % | G22: RATIO | H22: lease | J22: Loyers & réversion
C23: kpi.lease.vac_age | D23: Ancienneté vacance | E23: Vacancy age | F23: mois | G23: AVG | H23: lease | J23: Vacance & rétention
C24: kpi.lease.retention | D24: Rétention renouvel. | E24: Renewal retention | F24: % | G24: AVG | H24: lease | J24: Vacance & rétention
C25: kpi.lease.incentives | D25: Franchises/incentives | E25: Incentives | F25: FCFA | G25: SUM | H25: lease | I25: ✓ | J25: Incentives & WALT
C26: kpi.lease.rent_sqm | D26: Loyer moyen /m² | E26: Avg rent/sqm | F26: FCFA/m² | G26: RATIO | H26: lease | I26: ✓ | J26: Loyers & réversion
C27: kpi.lease.walt | D27: Durée résiduelle (WALT) | E27: WALT | F27: ans | G27: AVG | H27: lease | J27: Incentives & WALT
C28: kpi.rec.ar | D28: Créances (AR) | E28: Receivables | F28: FCFA | G28: LAST | H28: rec | J28: Encours & balance âgée
C29: kpi.rec.aged_0_30 | D29: Âgée 0-30j | E29: Aged 0-30d | F29: FCFA | G29: LAST | H29: rec | J29: Encours & balance âgée
C30: kpi.rec.aged_30_60 | D30: Âgée 30-60j | E30: Aged 30-60d | F30: FCFA | G30: LAST | H30: rec | J30: Encours & balance âgée
C31: kpi.rec.aged_60_90 | D31: Âgée 60-90j | E31: Aged 60-90d | F31: FCFA | G31: LAST | H31: rec | J31: Encours & balance âgée
C32: kpi.rec.aged_90p | D32: Âgée 90j+ | E32: Aged 90d+ | F32: FCFA | G32: LAST | H32: rec | J32: Encours & balance âgée
C33: kpi.rec.dso | D33: DSO réel | E33: DSO | F33: j | G33: RATIO | H33: rec | J33: DSO & recouvrement
C34: kpi.rec.recovery | D34: Taux recouvrement | E34: Recovery rate | F34: % | G34: RATIO | H34: rec | I34: ✓ | J34: DSO & recouvrement
C35: kpi.rec.collected | D35: Encaissements | E35: Collections | F35: FCFA | G35: SUM | H35: rec | I35: ✓ | J35: DSO & recouvrement
C36: kpi.rec.billed | D36: Facturé | E36: Billed | F36: FCFA | G36: SUM | H36: rec | J36: DSO & recouvrement
C37: kpi.rec.dunning | D37: Relances émises | E37: Dunning notices | F37: nb | G37: SUM | H37: rec | J37: Suivi de recouvrement
C38: kpi.rec.promises | D38: Promesses de paiement | E38: Payment promises | F38: FCFA | G38: SUM | H38: rec | J38: Suivi de recouvrement
C39: kpi.rec.promise_kept | D39: Taux promesses tenues | E39: Promise-kept rate | F39: % | G39: AVG | H39: rec | J39: Suivi de recouvrement
C40: kpi.rec.collected_dun | D40: Encaissé sur relance | E40: Collected via dunning | F40: FCFA | G40: SUM | H40: rec | I40: ✓ | J40: Suivi de recouvrement
C41: kpi.rec.provision | D41: Provisions douteuses | E41: Doubtful provisions | F41: % | G41: RATIO | H41: rec | J41: Provisions
C42: kpi.rec.litige_count | D42: Dossiers en litige | E42: Disputed cases | F42: nb | G42: LAST | H42: rec | J42: Litiges & contentieux
C43: kpi.rec.litige_amount | D43: Montant en litige | E43: Disputed amount | F43: FCFA | G43: LAST | H43: rec | J43: Litiges & contentieux
C44: kpi.rec.litige_resolved | D44: Taux résolution litiges | E44: Dispute resolution rate | F44: % | G44: AVG | H44: rec | J44: Litiges & contentieux
C45: kpi.rec.litige_age | D45: Ancienneté litige | E45: Dispute age | F45: mois | G45: AVG | H45: rec | J45: Litiges & contentieux
C46: kpi.foot.total | D46: Fréquentation | E46: Total footfall | F46: visites | G46: SUM | H46: foot | I46: ✓ | J46: Fréquentation vs budget
C47: kpi.foot.vs_budget | D47: Footfall vs budget | E47: Footfall vs budget | F47: % | G47: RATIO | H47: foot | J47: Fréquentation vs budget
C48: kpi.foot.per_sqm | D48: Footfall /m² | E48: Footfall/sqm | F48: v/m² | G48: RATIO | H48: foot | J48: Densité & conversion
C49: kpi.foot.conversion | D49: Conversion→ventes | E49: Footfall→sales conv. | F49: % | G49: RATIO | H49: foot | J49: Densité & conversion
C50: kpi.foot.dwell | D50: Temps de visite | E50: Dwell time | F50: min | G50: AVG | H50: foot | J50: Dwell time
C51: kpi.foot.peak_share | D51: Part heure de pointe | E51: Peak-hour share | F51: % | G51: AVG | H51: foot | J51: Répartition par zone
C52: kpi.foot.weekend_share | D52: Part week-end | E52: Weekend share | F52: % | G52: AVG | H52: foot | J52: Répartition par zone
C53: kpi.mkt.events | D53: Événements | E53: Events | F53: nb | G53: SUM | H53: mkt | J53: Événements
C54: kpi.mkt.event_att | D54: Affluence événements | E54: Event attendance | F54: visites | G54: SUM | H54: mkt | J54: Événements
C55: kpi.mkt.event_roi | D55: ROI événement | E55: Event ROI | F55: % | G55: RATIO | H55: mkt | J55: Événements
C56: kpi.mkt.event_sat | D56: Satisfaction événement | E56: Event satisfaction | F56: score | G56: AVG | H56: mkt | J56: Événements
C57: kpi.mkt.engagement | D57: Taux d'engagement | E57: Engagement rate | F57: % | G57: AVG | H57: mkt | J57: Marketing digital
C58: kpi.mkt.followers | D58: Abonnés | E58: Followers | F58: nb | G58: LAST | H58: mkt | J58: Marketing digital
... C61: kpi.mkt.digital_conv | D61: Conversion digitale | E61: Digital conversion | F61: % | G61: RATIO | H61: mkt | J61: Marketing digital
C62: kpi.mkt.spend | D62: Dépense mkt | E62: Marketing spend | F62: FCFA | G62: SUM | H62: mkt | I62: ✓ | J62: Publicité & communication
C63: kpi.mkt.spend_pct | D63: Spend % du CA | E63: Spend % revenue | F63: % | G63: RATIO | H63: mkt | J63: Publicité & communication
C64: kpi.mkt.impressions | D64: Impressions pub | E64: Ad impressions | F64: nb | G64: SUM | H64: mkt | J64: Publicité & communication
C65: kpi.mkt.campaigns | D65: Campagnes actives | E65: Active campaigns | F65: nb | G65: LAST | H65: mkt | J65: Publicité & communication
C66: kpi.mkt.nps | D66: NPS | E66: NPS | F66: score | G66: AVG | H66: mkt | J66: Analyse données (CRM/fidélité)
C67: kpi.mkt.members | D67: Membres fidélité | E67: Loyalty members | F67: nb | G67: LAST | H67: mkt | J67: Analyse données (CRM/fidélité)
C68: kpi.mkt.member_act | D68: Activation membres | E68: Member activation | F68: % | G68: AVG | H68: mkt | J68: Analyse données (CRM/fidélité)
C69: kpi.mkt.basket_member | D69: Panier moyen membre | E69: Avg member basket | F69: FCFA | G69: AVG | H69: mkt | J69: Analyse données (CRM/fidélité)
C70: kpi.com.tenant_sales | D70: Ventes locataires | E70: Tenant sales | F70: FCFA | G70: SUM | H70: com | I70: ✓ | J70: Ventes & CA/m²
C71: kpi.com.total_sales | D71: CA total locataires | E71: Total turnover | F71: FCFA | G71: SUM | H71: com | I71: ✓ | J71: Ventes & CA/m²
C72: kpi.com.sales_sqm | D72: CA /m² | E72: Sales/sqm | F72: FCFA/m² | G72: RATIO | H72: com | J72: Ventes & CA/m²
C73: kpi.com.lfl | D73: Like-for-like | E73: Like-for-like | F73: % | G73: RATIO | H73: com | J73: Ventes & CA/m²
C74: kpi.com.new_leases | D74: Nouveaux baux | E74: New leases | F74: nb | G74: SUM | H74: com | I74: ✓ | J74: Location à bail
C75: kpi.com.pipeline | D75: Pipeline pondéré | E75: Weighted pipeline | F75: FCFA | G75: LAST | H75: com | I75: ✓ | J75: Location à bail
C76: kpi.com.leases_renewed | D76: Baux renouvelés | E76: Leases renewed | F76: nb | G76: SUM | H76: com | J76: Location à bail
C77: kpi.com.pipeline_conv | D77: Conversion pipeline | E77: Pipeline conversion | F77: % | G77: RATIO | H77: com | J77: Location à bail
C78: kpi.com.popup_count | D78: Locations pop-up (nb) | E78: Pop-up rentals (nb) | F78: nb | G78: LAST | H78: com | I78: ✓ | J78: Pop-store / specialty
C79: kpi.com.popup_rev | D79: Revenus pop-up | E79: Pop-up revenue | F79: FCFA | G79: SUM | H79: com | I79: ✓ | J79: Pop-store / specialty
C80: kpi.com.kiosk_occ | D80: Taux d'occupation pop-up | E80: Pop-up occupancy | F80: % | G80: AVG | H80: com | I80: ✓ | J80: Pop-store / specialty
C81: kpi.com.market_rev | D81: Revenus Le Market | E81: Le Market revenue | F81: FCFA | G81: SUM | H81: com | I81: ✓ | J81: Le Market
C82: kpi.com.market_occ | D82: Taux d'occupation Le Market | E82: Le Market occupancy | F82: % | G82: AVG | H82: com | I82: ✓ | J82: Le Market
C83: kpi.com.market_stalls | D83: Kiosques loués (Le Market) | E83: Le Market kiosks let | F83: nb | G83: LAST | H83: com | I83: ✓ | J83: Le Market
C84: kpi.com.media_sales | D84: Régie publicitaire | E84: Media sales | F84: FCFA | G84: SUM | H84: com | I84: ✓ | J84: Partenariats & activations
C85: kpi.com.partnership_rev | D85: Revenus partenariats | E85: Partnership revenue | F85: FCFA | G85: SUM | H85: com | J85: Partenariats & activations
C86: kpi.com.activations | D86: Activations annonceurs | E86: Advertiser activations | F86: nb | G86: SUM | H86: com | J86: Partenariats & activations
C87: kpi.com.activation_rev | D87: Revenus activations | E87: Activation revenue | F87: FCFA | G87: SUM | H87: com | J87: Partenariats & activations
C88: kpi.com.discount | D88: Escompte % CA brut | E88: Discount % gross | F88: % | G88: RATIO | H88: com | J88: Remises
C89: kpi.hsse.incidents | D89: Incidents | E89: Incidents | F89: nb | G89: SUM | H89: hsse | J89: Incidents
C90: kpi.hsse.incident_sev | D90: Gravité incidents | E90: Incident severity | F90: score | G90: AVG | H90: hsse | J90: Incidents
C91: kpi.hsse.tf | D91: Taux de fréquence | E91: Frequency rate | F91: TF | G91: RATIO | H91: hsse | J91: Accidentologie
C92: kpi.hsse.tg | D92: Taux de gravité | E92: Severity rate | F92: TG | G92: RATIO | H92: hsse | J92: Accidentologie
C93: kpi.hsse.nearmiss | D93: Presqu'accidents | E93: Near-misses | F93: nb | G93: SUM | H93: hsse | J93: Accidentologie
C94: kpi.hsse.days_no_lti | D94: Jours sans accident | E94: Days w/o LTI | F94: j | G94: LAST | H94: hsse | J94: Accidentologie
C95: kpi.hsse.evac_drills | D95: Exercices d'évacuation | E95: Evacuation drills | F95: nb | G95: SUM | H95: hsse | J95: Sécurité incendie
C96: kpi.hsse.fire_conform | D96: Conformité incendie | E96: Fire safety conformity | F96: % | G96: AVG | H96: hsse | J96: Sécurité incendie
... C104: kpi.hsse.risks_treated | D104: Risques traités | E104: Risks treated | F104: % | G104: AVG | H104: hsse | J104: Gestion des risques
C105: kpi.hsse.action_close | D105: Clôture plan d'actions | E105: Action closure | F105: % | G105: AVG | H105: hsse | I105: ✓ | J105: Gestion des risques
C106: kpi.hsse.audits | D106: Audits réalisés | E106: Audits done | F106: nb | G106: SUM | H106: hsse | J106: Gestion des risques
C107: kpi.hsse.train_cover | D107: Couverture form. HSSE | E107: HSSE training cov. | F107: % | G107: AVG | H107: hsse | I107: ✓ | J107: Formation HSSE
C108: kpi.fac.prev_corr | D108: Préventif/correctif | E108: Preventive/corrective | F108: % | G108: AVG | H108: fac | J108: Maintenance prév./corr.
C109: kpi.fac.wo_prev | D109: OT préventifs | E109: Preventive WOs | F109: nb | G109: SUM | H109: fac | J109: Maintenance prév./corr.
C110: kpi.fac.wo_corr | D110: OT correctifs | E110: Corrective WOs | F110: nb | G110: SUM | H110: fac | J110: Maintenance prév./corr.
C111: kpi.fac.ot_backlog | D111: Backlog d'OT | E111: WO backlog | F111: nb | G111: LAST | H111: fac | J111: Tickets OT
...

Sheet M1 · Paramètres
B1: M1 · PARAMÈTRES (RAG · budget · listes)
B3: tbl_param_rag — seuils paramétrables | H3: tbl_param_budget — budget mensuel (KPI × 12 mois)
B4: KEY | C4: SENS | D4: SEUIL_VERT | E4: SEUIL_AMBRE | G4: KEY | H4: 1 | I4: 2 | J4: 3 | K4: 4 | L4: 5 | M4: 6 | N4: 7 | O4: 8 | P4: 9 | Q4: 10 | R4: 11 | S4: 12
B5: kpi.rh.headcount | C5: UP | D5: 1 | E5: 0.95 | G5: kpi.rh.headcount
B6: kpi.rh.fte_gap | C6: DOWN | D6: 1 | E6: 1.05 | G6: kpi.rh.fte_gap | H6: 5 | I6: 5 | J6: 5 | K6: 5 | L6: 5 | M6: 5 | N6: 5 | O6: 5 | P6: 5 | Q6: 5 | R6: 5 | S6: 5
B7: kpi.rh.open_pos | C7: UP | D7: 1 | E7: 0.95 | G7: kpi.rh.open_pos
B8: kpi.rh.ttf | C8: DOWN | D8: 1 | E8: 1.05 | G8: kpi.rh.ttf
B9: kpi.rh.payroll | C9: UP | D9: 1 | E9: 0.95 | G9: kpi.rh.payroll | H9: 85000000 | I9: 85850000 | J9: 86700000 | K9: 87550000 | L9: 88400000 | M9: 89250000 | N9: 90100000 | O9: 90950000 | P9: 91800000 | Q9: 92650000 | R9: 93500000 | S9: 94350000
B10: kpi.rh.payroll_var | C10: UP | D10: 1 | E10: 0.95 | G10: kpi.rh.payroll_var
B11: kpi.rh.turnover | C11: DOWN | D11: 1 | E11: 1.05 | G11: kpi.rh.turnover
B12: kpi.rh.absence | C12: DOWN | D12: 1 | E12: 1.05 | G12: kpi.rh.absence
B13: kpi.rh.train_hours | C13: UP | D13: 1 | E13: 0.95 | G13: kpi.rh.train_hours
B14: kpi.rh.train_cover | C14: UP | D14: 1 | E14: 0.95 | G14: kpi.rh.train_cover
B15: kpi.lease.occ_gla | C15: UP | D15: 1 | E15: 0.95 | G15: kpi.lease.occ_gla | H15: 0.9 | I15: 0.9 | J15: 0.9 | K15: 0.9 | L15: 0.9 | M15: 0.9 | N15: 0.9 | O15: 0.9 | P15: 0.9 | Q15: 0.9 | R15: 0.9 | S15: 0.9
B16: kpi.lease.occ_unit | C16: UP | D16: 1 | E16: 0.95 | G16: kpi.lease.occ_unit
B17: kpi.lease.gla_vacant | C17: DOWN | D17: 1 | E17: 1.05 | G17: kpi.lease.gla_vacant
B18: kpi.lease.ocr | C18: DOWN | D18: 1 | E18: 1.05 | G18: kpi.lease.ocr | H18: 0.12 | I18: 0.12 | J18: 0.12 | K18: 0.12 | L18: 0.12 | M18: 0.12 | N18: 0.12 | O18: 0.12 | P18: 0.12 | Q18: 0.12 | R18: 0.12 | S18: 0.12
B19: kpi.lease.passing | C19: UP | D19: 1 | E19: 0.95 | G19: kpi.lease.passing | H19: 130000000 | I19: 130000000 | J19: 130000000 | K19: 130000000 | L19: 130000000 | M19: 130000000 | N19: 130000000 | O19: 130000000 | P19: 130000000 | Q19: 130000000 | R19: 130000000 | S19: 130000000
B20: kpi.lease.erv | C20: UP | D20: 1 | E20: 0.95 | G20: kpi.lease.erv
B21: kpi.lease.reversion | C21: UP | D21: 1 | E21: 0.95 | G21: kpi.lease.reversion
B22: kpi.lease.vac_age | C22: DOWN | D22: 1 | E22: 1.05 | G22: kpi.lease.vac_age
B23: kpi.lease.retention | C23: UP | D23: 1 | E23: 0.95 | G23: kpi.lease.retention
B24: kpi.lease.incentives | C24: UP | D24: 1 | E24: 0.95 | G24: kpi.lease.incentives | H24: 6000000 | I24: 6060000 | J24: 6120000 | K24: 6180000 | L24: 6240000 | M24: 6300000 | N24: 6360000 | O24: 6420000 | P24: 6480000 | Q24: 6540000 | R24: 6600000 | S24: 6660000
B25: kpi.lease.rent_sqm | C25: UP | D25: 1 | E25: 0.95 | G25: kpi.lease.rent_sqm | H25: 9000 | I25: 9000 | J25: 9000 | K25: 9000 | L25: 9000 | M25: 9000 | N25: 9000 | O25: 9000 | P25: 9000 | Q25: 9000 | R25: 9000 | S25: 9000
B26: kpi.lease.walt | C26: UP | D26: 1 | E26: 0.95 | G26: kpi.lease.walt
B27: kpi.rec.ar | C27: UP | D27: 1 | E27: 0.95 | G27: kpi.rec.ar
B28: kpi.rec.aged_0_30 | C28: UP | D28: 1 | E28: 0.95 | G28: kpi.rec.aged_0_30
B29: kpi.rec.aged_30_60 | C29: UP | D29: 1 | E29: 0.95 | G29: kpi.rec.aged_30_60
B30: kpi.rec.aged_60_90 | C30: UP | D30: 1 | E30: 0.95 | G30: kpi.rec.aged_60_90
B31: kpi.rec.aged_90p | C31: UP | D31: 1 | E31: 0.95 | G31: kpi.rec.aged_90p
B32: kpi.rec.dso | C32: DOWN | D32: 1 | E32: 1.05 | G32: kpi.rec.dso
B33: kpi.rec.recovery | C33: UP | D33: 1 | E33: 0.95 | G33: kpi.rec.recovery | H33: 0.86 | I33: 0.86 | J33: 0.86 | K33: 0.86 | L33: 0.86 | M33: 0.86 | N33: 0.86 | O33: 0.86 | P33: 0.86 | Q33: 0.86 | R33: 0.86 | S33: 0.86
B34: kpi.rec.collected | C34: UP | D34: 1 | E34: 0.95 | G34: kpi.rec.collected | H34: 220000000 | I34: 222200000 | J34: 224400000 | K34: 226600000 | L34: 228800000 | M34: 231000000 | N34: 233200000 | O34: 235400000 | P34: 237600000 | Q34: 239800000 | R34: 242000000 | S34: 244200000
B35: kpi.rec.billed | C35: UP | D35: 1 | E35: 0.95 | G35: kpi.rec.billed
B36: kpi.rec.dunning | C36: UP | D36: 1 | E36: 0.95 | G36: kpi.rec.dunning
B37: kpi.rec.promises | C37: UP | D37: 1 | E37: 0.95 | G37: kpi.rec.promises
B38: kpi.rec.promise_kept | C38: UP | D38: 1 | E38: 0.95 | G38: kpi.rec.promise_kept
B39: kpi.rec.collected_dun | C39: UP | D39: 1 | E39: 0.95 | G39: kpi.rec.collected_dun | H39: 60000000 | I39: 60600000 | J39: 61200000 | K39: 61800000 | L39: 62400000 | M39: 63000000 | N39: 63600000 | O39: 64200000 | P39: 64800000 | Q39: 65400000 | R39: 66000000 | S39: 66600000
B40: kpi.rec.provision | C40: DOWN | D40: 1 | E40: 1.05 | G40: kpi.rec.provision
B41: kpi.rec.litige_count | C41: DOWN | D41: 1 | E41: 1.05 | G41: kpi.rec.litige_count
B42: kpi.rec.litige_amount | C42: DOWN | D42: 1 | E42: 1.05 | G42: kpi.rec.litige_amount
B43: kpi.rec.litige_resolved | C43: UP | D43: 1 | E43: 0.95 | G43: kpi.rec.litige_resolved
B44: kpi.rec.litige_age | C44: DOWN | D44: 1 | E44: 1.05 | G44: kpi.rec.litige_age
B45: kpi.foot.total | C45: UP | D45: 1 | E45: 0.95 | G45: kpi.foot.total | H45: 480000 | I45: 484800 | J45: 489600 | K45: 494400 | L45: 499200 | M45: 504000 | N45: 508800 | O45: 513600 | P45: 518400 | Q45: 523200 | R45: 528000 | S45: 532800
B46: kpi.foot.vs_budget | C46: UP | D46: 1 | E46: 0.95 | G46: kpi.foot.vs_budget
B47: kpi.foot.per_sqm | C47: UP | D47: 1 | E47: 0.95 | G47: kpi.foot.per_sqm
B48: kpi.foot.conversion | C48: UP | D48: 1 | E48: 0.95 | G48: kpi.foot.conversion
B49: kpi.foot.dwell | C49: UP | D49: 1 | E49: 0.95 | G49: kpi.foot.dwell
B50: kpi.foot.peak_share | C50: UP | D50: 1 | E50: 0.95 | G50: kpi.foot.peak_share
B51: kpi.foot.weekend_share | C51: UP | D51: 1 | E51: 0.95 | G51: kpi.foot.weekend_share
B52: kpi.mkt.events | C52: UP | D52: 1 | E52: 0.95 | G52: kpi.mkt.events
B53: kpi.mkt.event_att | C53: UP | D53: 1 | E53: 0.95 | G53: kpi.mkt.event_att
B54: kpi.mkt.event_roi | C54: UP | D54: 1 | E54: 0.95 | G54: kpi.mkt.event_roi
B55: kpi.mkt.event_sat | C55: UP | D55: 1 | E55: 0.95 | G55: kpi.mkt.event_sat
B56: kpi.mkt.engagement | C56: UP | D56: 1 | E56: 0.95 | G56: kpi.mkt.engagement
B57: kpi.mkt.followers | C57: UP | D57: 1 | E57: 0.95 | G57: kpi.mkt.followers
... B60: kpi.mkt.digital_conv | C60: UP | D60: 1 | E60: 0.95 | G60: kpi.mkt.digital_conv
B61: kpi.mkt.spend | C61: UP | D61: 1 | E61: 0.95 | G61: kpi.mkt.spend | H61: 22000000 | I61: 22220000 | J61: 22440000 | K61: 22660000 | L61: 22880000 | M61: 23100000 | N61: 23320000 | O61: 23540000 | P61: 23760000 | Q61: 23980000 | R61: 24200000 | S61: 24420000
B62: kpi.mkt.spend_pct | C62: DOWN | D62: 1 | E62: 1.05 | G62: kpi.mkt.spend_pct
B63: kpi.mkt.impressions | C63: UP | D63: 1 | E63: 0.95 | G63: kpi.mkt.impressions
B64: kpi.mkt.campaigns | C64: UP | D64: 1 | E64: 0.95 | G64: kpi.mkt.campaigns
B65: kpi.mkt.nps | C65: UP | D65: 1 | E65: 0.95 | G65: kpi.mkt.nps
B66: kpi.mkt.members | C66: UP | D66: 1 | E66: 0.95 | G66: kpi.mkt.members
B67: kpi.mkt.member_act | C67: UP | D67: 1 | E67: 0.95 | G67: kpi.mkt.member_act
B68: kpi.mkt.basket_member | C68: UP | D68: 1 | E68: 0.95 | G68: kpi.mkt.basket_member
B69: kpi.com.tenant_sales | C69: UP | D69: 1 | E69: 0.95 | G69: kpi.com.tenant_sales | H69: 1250000000 | I69: 1262500000 | J69: 1275000000 | K69: 1287500000 | L69: 1300000000 | M69: 1312500000 | N69: 1325000000 | O69: 1337500000 | P69: 1350000000 | Q69: 1362500000 | R69: 1375000000 | S69: 1387500000
B70: kpi.com.total_sales | C70: UP | D70: 1 | E70: 0.95 | G70: kpi.com.total_sales | H70: 1300000000 | I70: 1313000000 | J70: 1326000000 | K70: 1339000000 | L70: 1352000000 | M70: 1365000000 | N70: 1378000000 | O70: 1391000000 | P70: 1404000000 | Q70: 1417000000 | R70: 1430000000 | S70: 1443000000
B71: kpi.com.sales_sqm | C71: UP | D71: 1 | E71: 0.95 | G71: kpi.com.sales_sqm
B72: kpi.com.lfl | C72: UP | D72: 1 | E72: 0.95 | G72: kpi.com.lfl
B73: kpi.com.new_leases | C73: UP | D73: 1 | E73: 0.95 | G73: kpi.com.new_leases | H73: 3 | I73: 3 | J73: 3 | K73: 3 | L73: 3 | M73: 3 | N73: 3 | O73: 3 | P73: 3 | Q73: 3 | R73: 3 | S73: 3
B74: kpi.com.pipeline | C74: UP | D74: 1 | E74: 0.95 | G74: kpi.com.pipeline | H74: 340000000 | I74: 340000000 | J74: 340000000 | K74: 340000000 | L74: 340000000 | M74: 340000000 | N74: 340000000 | O74: 340000000 | P74: 340000000 | Q74: 340000000 | R74: 340000000 | S74: 340000000
B75: kpi.com.leases_renewed | C75: UP | D75: 1 | E75: 0.95 | G75: kpi.com.leases_renewed
B76: kpi.com.pipeline_conv | C76: UP | D76: 1 | E76: 0.95 | G76: kpi.com.pipeline_conv
B77: kpi.com.popup_count | C77: UP | D77: 1 | E77: 0.95 | G77: kpi.com.popup_count | H77: 6 | I77: 6 | J77: 6 | K77: 6 | L77: 6 | M77: 6 | N77: 6 | O77: 6 | P77: 6 | Q77: 6 | R77: 6 | S77: 6
B78: kpi.com.popup_rev | C78: UP | D78: 1 | E78: 0.95 | G78: kpi.com.popup_rev | H78: 18000000 | I78: 18180000 | J78: 18360000 | K78: 18540000 | L78: 18720000 | M78: 18900000 | N78: 19080000 | O78: 19260000 | P78: 19440000 | Q78: 19620000 | R78: 19800000 | S78: 19980000
B79: kpi.com.kiosk_occ | C79: UP | D79: 1 | E79: 0.95 | G79: kpi.com.kiosk_occ | H79: 0.78 | I79: 0.78 | J79: 0.78 | K79: 0.78 | L79: 0.78 | M79: 0.78 | N79: 0.78 | O79: 0.78 | P79: 0.78 | Q79: 0.78 | R79: 0.78 | S79: 0.78
B80: kpi.com.market_rev | C80: UP | D80: 1 | E80: 0.95 | G80: kpi.com.market_rev | H80: 42000000 | I80: 42420000 | J80: 42840000 | K80: 43260000 | L80: 43680000 | M80: 44100000 | N80: 44520000 | O80: 44940000 | P80: 45360000 | Q80: 45780000 | R80: 46200000 | S80: 46620000
B81: kpi.com.market_occ | C81: UP | D81: 1 | E81: 0.95 | G81: kpi.com.market_occ | H81: 0.83 | I81: 0.83 | J81: 0.83 | K81: 0.83 | L81: 0.83 | M81: 0.83 | N81: 0.83 | O81: 0.83 | P81: 0.83 | Q81: 0.83 | R81: 0.83 | S81: 0.83
B82: kpi.com.market_stalls | C82: UP | D82: 1 | E82: 0.95 | G82: kpi.com.market_stalls | H82: 45 | I82: 45 | J82: 45 | K82: 45 | L82: 45 | M82: 45 | N82: 45 | O82: 45 | P82: 45 | Q82: 45 | R82: 45 | S82: 45
B83: kpi.com.media_sales | C83: UP | D83: 1 | E83: 0.95 | G83: kpi.com.media_sales | H83: 28000000 | I83: 28280000 | J83: 28560000 | K83: 28840000 | L83: 29120000 | M83: 29400000 | N83: 29680000 | O83: 29960000 | P83: 30240000 | Q83: 30520000 | R83: 30800000 | S83: 31080000
B84: kpi.com.partnership_rev | C84: UP | D84: 1 | E84: 0.95 | G84: kpi.com.partnership_rev
B85: kpi.com.activations | C85: UP | D85: 1 | E85: 0.95 | G85: kpi.com.activations
B86: kpi.com.activation_rev | C86: UP | D86: 1 | E86: 0.95 | G86: kpi.com.activation_rev
B87: kpi.com.discount | C87: DOWN | D87: 1 | E87: 1.05 | G87: kpi.com.discount
B88: kpi.hsse.incidents | C88: DOWN | D88: 1 | E88: 1.05 | G88: kpi.hsse.incidents
B89: kpi.hsse.incident_sev | C89: DOWN | D89: 1 | E89: 1.05 | G89: kpi.hsse.incident_sev
B90: kpi.hsse.tf | C90: DOWN | D90: 1 | E90: 1.05 | G90: kpi.hsse.tf
B91: kpi.hsse.tg | C91: DOWN | D91: 1 | E91: 1.05 | G91: kpi.hsse.tg
B92: kpi.hsse.nearmiss | C92: UP | D92: 1 | E92: 0.95 | G92: kpi.hsse.nearmiss
B93: kpi.hsse.days_no_lti | C93: UP | D93: 1 | E93: 0.95 | G93: kpi.hsse.days_no_lti
B94: kpi.hsse.evac_drills | C94: UP | D94: 1 | E94: 0.95 | G94: kpi.hsse.evac_drills
B95: kpi.hsse.fire_conform | C95: UP | D95: 1 | E95: 0.95 | G95: kpi.hsse.fire_conform
... B103: kpi.hsse.risks_treated | C103: UP | D103: 1 | E103: 0.95 | G103: kpi.hsse.risks_treated
B104: kpi.hsse.action_close | C104: UP | D104: 1 | E104: 0.95 | G104: kpi.hsse.action_close | H104: 0.82 | I104: 0.82 | J104: 0.82 | K104: 0.82 | L104: 0.82 | M104: 0.82 | N104: 0.82 | O104: 0.82 | P104: 0.82 | Q104: 0.82 | R104: 0.82 | S104: 0.82
B105: kpi.hsse.audits | C105: UP | D105: 1 | E105: 0.95 | G105: kpi.hsse.audits
B106: kpi.hsse.train_cover | C106: UP | D106: 1 | E106: 0.95 | G106: kpi.hsse.train_cover | H106: 0.7 | I106: 0.7 | J106: 0.7 | K106: 0.7 | L106: 0.7 | M106: 0.7 | N106: 0.7 | O106: 0.7 | P106: 0.7 | Q106: 0.7 | R106: 0.7 | S106: 0.7
B107: kpi.fac.prev_corr | C107: UP | D107: 1 | E107: 0.95 | G107: kpi.fac.prev_corr
B108: kpi.fac.wo_prev | C108: UP | D108: 1 | E108: 0.95 | G108: kpi.fac.wo_prev
B109: kpi.fac.wo_corr | C109: DOWN | D109: 1 | E109: 1.05 | G109: kpi.fac.wo_corr
B110: kpi.fac.ot_backlog | C110: DOWN | D110: 1 | E110: 1.05 | G110: kpi.fac.ot_backlog
...

Sheet M2 · i18n
B1: M2 · i18n (FR/EN) + MOIS
B3: KEY | C3: FR | D3: EN | F3: Clés vides (attendu 0) | G3: =SUMPRODUCT(--(C4:C215=""))+SUMPRODUCT(--(D4:D215="")) | I3: # | J3: FR | K3: EN
B4: nav.title | C4: Reporting mensuel — Cosmos | D4: Monthly Report — Cosmos | I4: 1 | J4: Janvier | K4: January
B5: nav.subtitle | C5: Cosmos Yopougon · EPLSA – Emergence Plaza | D5: Cosmos Yopougon · EPLSA – Emergence Plaza | I5: 2 | J5: Février | K5: February
B6: nav.period | C6: Période | D6: Period | I6: 3 | J6: Mars | K6: March
B7: nav.grain | C7: Granularité | D7: Granularity | I7: 4 | J7: Avril | K7: April
B8: nav.lang | C8: Langue | D8: Language | I8: 5 | J8: Mai | K8: May
B9: nav.summary | C9: Sommaire | D9: Contents | I9: 6 | J9: Juin | K9: June
B10: nav.synthesis | C10: Synthèse exécutive | D10: Executive summary | I10: 7 | J10: Juillet | K10: July
B11: nav.methodo | C11: Méthodologie | D11: Methodology | I11: 8 | J11: Août | K11: August
B12: grain.month | C12: Mois | D12: Month | I12: 9 | J12: Septembre | K12: September
B13: grain.quarter | C13: Trimestre | D13: Quarter | I13: 10 | J13: Octobre | K13: October
B14: grain.year | C14: Année | D14: Year | I14: 11 | J14: Novembre | K14: November
B15: col.kpi | C15: Indicateur | D15: KPI | I15: 12 | J15: Décembre | K15: December
B16: col.unit | C16: Unité | D16: Unit
B17: col.current | C17: Courant | D17: Current
B18: col.prev | C18: Période préc. | D18: Prior period
B19: col.py | C19: N-1 | D19: PY
B20: col.delta_prev | C20: Δ% préc. | D20: Δ% prior
B21: col.delta_py | C21: Δ% N-1 | D21: Δ% PY
B22: col.budget | C22: Budget | D22: Budget
B23: col.var | C23: Écart% | D23: Var%
B24: col.rag | C24: Statut | D24: Status
B25: col.trend | C25: Tendance | D25: Trend
B26: col.comment | C26: Commentaire | D26: Comment
B27: rag.green | C27: Conforme | D27: On track
... B215: h2.fac.7 | C215: SLA prestataires | D215: SLA prestataires

Sheet M3 · Base mensuelle
B1: M3 · BASE MENSUELLE — consolidation (réf. collectes : saisie unique)
B3: Clé KPI | C3: Agg | D3: =DATE(2024,1,1) | E3: =DATE(2024,2,1) | F3: =DATE(2024,3,1) | G3: =DATE(2024,4,1) | H3: =DATE(2024,5,1) | I3: =DATE(2024,6,1) | J3: =DATE(2024,7,1) | K3: =DATE(2024,8,1) | L3: =DATE(2024,9,1) | M3: =DATE(2024,10,1) | N3: =DATE(2024,11,1) | O3: =DATE(2024,12,1) | P3: =DATE(2025,1,1) | Q3: =DATE(2025,2,1) | R3: =DATE(2025,3,1) | S3: =DATE(2025,4,1) | T3: =DATE(2025,5,1) | U3: =DATE(2025,6,1) | V3: =DATE(2025,7,1) | W3: =DATE(2025,8,1) | X3: =DATE(2025,9,1) | Y3: =DATE(2025,10,1) | Z3: =DATE(2025,11,1) | AA3: =DATE(2025,12,1) | AB3: =DATE(2026,1,1) | AC3: =DATE(2026,2,1) | AD3: =DATE(2026,3,1) | AE3: =DATE(2026,4,1) | AF3: =DATE(2026,5,1) | AG3: =DATE(2026,6,1) | AH3: =DATE(2026,7,1) | AI3: =DATE(2026,8,1) | AJ3: =DATE(2026,9,1) | AK3: =DATE(2026,10,1) | AL3: =DATE(2026,11,1) | AM3: =DATE(2026,12,1)
B4: kpi.rh.headcount | C4: LAST | D4: ='C1 · Capital Humain'!D8 | E4: ='C1 · Capital Humain'!E8 | F4: ='C1 · Capital Humain'!F8 | G4: ='C1 · Capital Humain'!G8 | H4: ='C1 · Capital Humain'!H8 | I4: ='C1 · Capital Humain'!I8 | J4: ='C1 · Capital Humain'!J8 | K4: ='C1 · Capital Humain'!K8 | ... AM4: ='C1 · Capital Humain'!AM8
B5: kpi.rh.fte_gap | C5: LAST | D5: ='C1 · Capital Humain'!D9 | E5: ='C1 · Capital Humain'!E9 | F5: ='C1 · Capital Humain'!F9 | G5: ='C1 · Capital Humain'!G9 | H5: ='C1 · Capital Humain'!H9 | I5: ='C1 · Capital Humain'!I9 | J5: ='C1 · Capital Humain'!J9 | K5: ='C1 · Capital Humain'!K9 | ... AM5: ='C1 · Capital Humain'!AM9
B6: kpi.rh.open_pos | C6: LAST | D6: ='C1 · Capital Humain'!D10 | E6: ='C1 · Capital Humain'!E10 | F6: ='C1 · Capital Humain'!F10 | G6: ='C1 · Capital Humain'!G10 | H6: ='C1 · Capital Humain'!H10 | I6: ='C1 · Capital Humain'!I10 | J6: ='C1 · Capital Humain'!J10 | K6: ='C1 · Capital Humain'!K10 | ... AM6: ='C1 · Capital Humain'!AM10
B7: kpi.rh.ttf | C7: AVG | D7: ='C1 · Capital Humain'!D11 | E7: ='C1 · Capital Humain'!E11 | F7: ='C1 · Capital Humain'!F11 | G7: ='C1 · Capital Humain'!G11 | H7: ='C1 · Capital Humain'!H11 | I7: ='C1 · Capital Humain'!I11 | J7: ='C1 · Capital Humain'!J11 | K7: ='C1 · Capital Humain'!K11 | ... AM7: ='C1 · Capital Humain'!AM11
B8: kpi.rh.payroll | C8: SUM | D8: ='C1 · Capital Humain'!D12 | E8: ='C1 · Capital Humain'!E12 | F8: ='C1 · Capital Humain'!F12 | G8: ='C1 · Capital Humain'!G12 | H8: ='C1 · Capital Humain'!H12 | I8: ='C1 · Capital Humain'!I12 | J8: ='C1 · Capital Humain'!J12 | K8: ='C1 · Capital Humain'!K12 | ... AM8: ='C1 · Capital Humain'!AM12
B9: kpi.rh.payroll_var | C9: RATIO | D9: ='C1 · Capital Humain'!D13 | E9: ='C1 · Capital Humain'!E13 | F9: ='C1 · Capital Humain'!F13 | G9: ='C1 · Capital Humain'!G13 | H9: ='C1 · Capital Humain'!H13 | I9: ='C1 · Capital Humain'!I13 | J9: ='C1 · Capital Humain'!J13 | K9: ='C1 · Capital Humain'!K13 | ... AM9: ='C1 · Capital Humain'!AM13
B10: kpi.rh.turnover | C10: AVG | D10: ='C1 · Capital Humain'!D14 | E10: ='C1 · Capital Humain'!E14 | F10: ='C1 · Capital Humain'!F14 | G10: ='C1 · Capital Humain'!G14 | H10: ='C1 · Capital Humain'!H14 | I10: ='C1 · Capital Humain'!I14 | J10: ='C1 · Capital Humain'!J14 | K10: ='C1 · Capital Humain'!K14 | ... AM10: ='C1 · Capital Humain'!AM14
B11: kpi.rh.absence | C11: AVG | D11: ='C1 · Capital Humain'!D15 | E11: ='C1 · Capital Humain'!E15 | F11: ='C1 · Capital Humain'!F15 | G11: ='C1 · Capital Humain'!G15 | H11: ='C1 · Capital Humain'!H15 | I11: ='C1 · Capital Humain'!I15 | J11: ='C1 · Capital Humain'!J15 | K11: ='C1 · Capital Humain'!K15 | ... AM11: ='C1 · Capital Humain'!AM15
B12: kpi.rh.train_hours | C12: AVG | D12: ='C1 · Capital Humain'!D16 | E12: ='C1 · Capital Humain'!E16 | F12: ='C1 · Capital Humain'!F16 | G12: ='C1 · Capital Humain'!G16 | H12: ='C1 · Capital Humain'!H16 | I12: ='C1 · Capital Humain'!I16 | J12: ='C1 · Capital Humain'!J16 | K12: ='C1 · Capital Humain'!K16 | ... AM12: ='C1 · Capital Humain'!AM16
B13: kpi.rh.train_cover | C13: AVG | D13: ='C1 · Capital Humain'!D17 | E13: ='C1 · Capital Humain'!E17 | F13: ='C1 · Capital Humain'!F17 | G13: ='C1 · Capital Humain'!G17 | H13: ='C1 · Capital Humain'!H17 | I13: ='C1 · Capital Humain'!I17 | J13: ='C1 · Capital Humain'!J17 | K13: ='C1 · Capital Humain'!K17 | ... AM13: ='C1 · Capital Humain'!AM17
B14: kpi.lease.occ_gla | C14: AVG | D14: ='C2 · Lease'!D8 | E14: ='C2 · Lease'!E8 | F14: ='C2 · Lease'!F8 | G14: ='C2 · Lease'!G8 | H14: ='C2 · Lease'!H8 | I14: ='C2 · Lease'!I8 | J14: ='C2 · Lease'!J8 | K14: ='C2 · Lease'!K8 | ... AM14: ='C2 · Lease'!AM8
B15: kpi.lease.occ_unit | C15: AVG | D15: ='C2 · Lease'!D9 | E15: ='C2 · Lease'!E9 | F15: ='C2 · Lease'!F9 | G15: ='C2 · Lease'!G9 | H15: ='C2 · Lease'!H9 | I15: ='C2 · Lease'!I9 | J15: ='C2 · Lease'!J9 | K15: ='C2 · Lease'!K9 | ... AM15: ='C2 · Lease'!AM9
B16: kpi.lease.gla_vacant | C16: LAST | D16: ='C2 · Lease'!D10 | E16: ='C2 · Lease'!E10 | F16: ='C2 · Lease'!F10 | G16: ='C2 · Lease'!G10 | H16: ='C2 · Lease'!H10 | I16: ='C2 · Lease'!I10 | J16: ='C2 · Lease'!J10 | K16: ='C2 · Lease'!K10 | ... AM16: ='C2 · Lease'!AM10
B17: kpi.lease.ocr | C17: RATIO | D17: ='C2 · Lease'!D11 | E17: ='C2 · Lease'!E11 | F17: ='C2 · Lease'!F11 | G17: ='C2 · Lease'!G11 | H17: ='C2 · Lease'!H11 | I17: ='C2 · Lease'!I11 | J17: ='C2 · Lease'!J11 | K17: ='C2 · Lease'!K11 | ... AM17: ='C2 · Lease'!AM11
B18: kpi.lease.passing | C18: LAST | D18: ='C2 · Lease'!D12 | E18: ='C2 · Lease'!E12 | F18: ='C2 · Lease'!F12 | G18: ='C2 · Lease'!G12 | H18: ='C2 · Lease'!H12 | I18: ='C2 · Lease'!I12 | J18: ='C2 · Lease'!J12 | K18: ='C2 · Lease'!K12 | ... AM18: ='C2 · Lease'!AM12
B19: kpi.lease.erv | C19: LAST | D19: ='C2 · Lease'!D13 | E19: ='C2 · Lease'!E13 | F19: ='C2 · Lease'!F13 | G19: ='C2 · Lease'!G13 | H19: ='C2 · Lease'!H13 | I19: ='C2 · Lease'!I13 | J19: ='C2 · Lease'!J13 | K19: ='C2 · Lease'!K13 | ... AM19: ='C2 · Lease'!AM13
B20: kpi.lease.reversion | C20: RATIO | D20: ='C2 · Lease'!D14 | E20: ='C2 · Lease'!E14 | F20: ='C2 · Lease'!F14 | G20: ='C2 · Lease'!G14 | H20: ='C2 · Lease'!H14 | I20: ='C2 · Lease'!I14 | J20: ='C2 · Lease'!J14 | K20: ='C2 · Lease'!K14 | ... AM20: ='C2 · Lease'!AM14
B21: kpi.lease.vac_age | C21: AVG | D21: ='C2 · Lease'!D15 | E21: ='C2 · Lease'!E15 | F21: ='C2 · Lease'!F15 | G21: ='C2 · Lease'!G15 | H21: ='C2 · Lease'!H15 | I21: ='C2 · Lease'!I15 | J21: ='C2 · Lease'!J15 | K21: ='C2 · Lease'!K15 | ... AM21: ='C2 · Lease'!AM15
B22: kpi.lease.retention | C22: AVG | D22: ='C2 · Lease'!D16 | E22: ='C2 · Lease'!E16 | F22: ='C2 · Lease'!F16 | G22: ='C2 · Lease'!G16 | H22: ='C2 · Lease'!H16 | I22: ='C2 · Lease'!I16 | J22: ='C2 · Lease'!J16 | K22: ='C2 · Lease'!K16 | ... AM22: ='C2 · Lease'!AM16
B23: kpi.lease.incentives | C23: SUM | D23: ='C2 · Lease'!D17 | E23: ='C2 · Lease'!E17 | F23: ='C2 · Lease'!F17 | G23: ='C2 · Lease'!G17 | H23: ='C2 · Lease'!H17 | I23: ='C2 · Lease'!I17 | J23: ='C2 · Lease'!J17 | K23: ='C2 · Lease'!K17 | ... AM23: ='C2 · Lease'!AM17
B24: kpi.lease.rent_sqm | C24: RATIO | D24: ='C2 · Lease'!D18 | E24: ='C2 · Lease'!E18 | F24: ='C2 · Lease'!F18 | G24: ='C2 · Lease'!G18 | H24: ='C2 · Lease'!H18 | I24: ='C2 · Lease'!I18 | J24: ='C2 · Lease'!J18 | K24: ='C2 · Lease'!K18 | ... AM24: ='C2 · Lease'!AM18
B25: kpi.lease.walt | C25: AVG | D25: ='C2 · Lease'!D19 | E25: ='C2 · Lease'!E19 | F25: ='C2 · Lease'!F19 | G25: ='C2 · Lease'!G19 | H25: ='C2 · Lease'!H19 | I25: ='C2 · Lease'!I19 | J25: ='C2 · Lease'!J19 | K25: ='C2 · Lease'!K19 | ... AM25: ='C2 · Lease'!AM19
B26: kpi.rec.ar | C26: LAST | D26: ='C3 · Recouvrement'!D8 | E26: ='C3 · Recouvrement'!E8 | F26: ='C3 · Recouvrement'!F8 | G26: ='C3 · Recouvrement'!G8 | H26: ='C3 · Recouvrement'!H8 | I26: ='C3 · Recouvrement'!I8 | J26: ='C3 · Recouvrement'!J8 | K26: ='C3 · Recouvrement'!K8 | ... AM26: ='C3 · Recouvrement'!AM8
B27: kpi.rec.aged_0_30 | C27: LAST | D27: ='C3 · Recouvrement'!D9 | E27: ='C3 · Recouvrement'!E9 | F27: ='C3 · Recouvrement'!F9 | G27: ='C3 · Recouvrement'!G9 | H27: ='C3 · Recouvrement'!H9 | I27: ='C3 · Recouvrement'!I9 | J27: ='C3 · Recouvrement'!J9 | K27: ='C3 · Recouvrement'!K9 | ... AM27: ='C3 · Recouvrement'!AM9
B28: kpi.rec.aged_30_60 | C28: LAST | D28: ='C3 · Recouvrement'!D10 | E28: ='C3 · Recouvrement'!E10 | F28: ='C3 · Recouvrement'!F10 | G28: ='C3 · Recouvrement'!G10 | H28: ='C3 · Recouvrement'!H10 | I28: ='C3 · Recouvrement'!I10 | J28: ='C3 · Recouvrement'!J10 | K28: ='C3 · Recouvrement'!K10 | ... AM28: ='C3 · Recouvrement'!AM10
B29: kpi.rec.aged_60_90 | C29: LAST | D29: ='C3 · Recouvrement'!D11 | E29: ='C3 · Recouvrement'!E11 | F29: ='C3 · Recouvrement'!F11 | G29: ='C3 · Recouvrement'!G11 | H29: ='C3 · Recouvrement'!H11 | I29: ='C3 · Recouvrement'!I11 | J29: ='C3 · Recouvrement'!J11 | K29: ='C3 · Recouvrement'!K11 | ... AM29: ='C3 · Recouvrement'!AM11
B30: kpi.rec.aged_90p | C30: LAST | D30: ='C3 · Recouvrement'!D12 | E30: ='C3 · Recouvrement'!E12 | F30: ='C3 · Recouvrement'!F12 | G30: ='C3 · Recouvrement'!G12 | H30: ='C3 · Recouvrement'!H12 | I30: ='C3 · Recouvrement'!I12 | J30: ='C3 · Recouvrement'!J12 | K30: ='C3 · Recouvrement'!K12 | ... AM30: ='C3 · Recouvrement'!AM12
B31: kpi.rec.dso | C31: RATIO | D31: ='C3 · Recouvrement'!D13 | E31: ='C3 · Recouvrement'!E13 | F31: ='C3 · Recouvrement'!F13 | G31: ='C3 · Recouvrement'!G13 | H31: ='C3 · Recouvrement'!H13 | I31: ='C3 · Recouvrement'!I13 | J31: ='C3 · Recouvrement'!J13 | K31: ='C3 · Recouvrement'!K13 | ... AM31: ='C3 · Recouvrement'!AM13
B32: kpi.rec.recovery | C32: RATIO | D32: ='C3 · Recouvrement'!D14 | E32: ='C3 · Recouvrement'!E14 | F32: ='C3 · Recouvrement'!F14 | G32: ='C3 · Recouvrement'!G14 | H32: ='C3 · Recouvrement'!H14 | I32: ='C3 · Recouvrement'!I14 | J32: ='C3 · Recouvrement'!J14 | K32: ='C3 · Recouvrement'!K14 | ... AM32: ='C3 · Recouvrement'!AM14
B33: kpi.rec.collected | C33: SUM | D33: ='C3 · Recouvrement'!D15 | E33: ='C3 · Recouvrement'!E15 | F33: ='C3 · Recouvrement'!F15 | G33: ='C3 · Recouvrement'!G15 | H33: ='C3 · Recouvrement'!H15 | I33: ='C3 · Recouvrement'!I15 | J33: ='C3 · Recouvrement'!J15 | K33: ='C3 · Recouvrement'!K15 | ... AM33: ='C3 · Recouvrement'!AM15
B34: kpi.rec.billed | C34: SUM | D34: ='C3 · Recouvrement'!D16 | E34: ='C3 · Recouvrement'!E16 | F34: ='C3 · Recouvrement'!F16 | G34: ='C3 · Recouvrement'!G16 | H34: ='C3 · Recouvrement'!H16 | I34: ='C3 · Recouvrement'!I16 | J34: ='C3 · Recouvrement'!J16 | K34: ='C3 · Recouvrement'!K16 | ... AM34: ='C3 · Recouvrement'!AM16
B35: kpi.rec.dunning | C35: SUM | D35: ='C3 · Recouvrement'!D17 | E35: ='C3 · Recouvrement'!E17 | F35: ='C3 · Recouvrement'!F17 | G35: ='C3 · Recouvrement'!G17 | H35: ='C3 · Recouvrement'!H17 | I35: ='C3 · Recouvrement'!I17 | J35: ='C3 · Recouvrement'!J17 | K35: ='C3 · Recouvrement'!K17 | ... AM35: ='C3 · Recouvrement'!AM17
B36: kpi.rec.promises | C36: SUM | D36: ='C3 · Recouvrement'!D18 | E36: ='C3 · Recouvrement'!E18 | F36: ='C3 · Recouvrement'!F18 | G36: ='C3 · Recouvrement'!G18 | H36: ='C3 · Recouvrement'!H18 | I36: ='C3 · Recouvrement'!I18 | J36: ='C3 · Recouvrement'!J18 | K36: ='C3 · Recouvrement'!K18 | ... AM36: ='C3 · Recouvrement'!AM18
B37: kpi.rec.promise_kept | C37: AVG | D37: ='C3 · Recouvrement'!D19 | E37: ='C3 · Recouvrement'!E19 | F37: ='C3 · Recouvrement'!F19 | G37: ='C3 · Recouvrement'!G19 | H37: ='C3 · Recouvrement'!H19 | I37: ='C3 · Recouvrement'!I19 | J37: ='C3 · Recouvrement'!J19 | K37: ='C3 · Recouvrement'!K19 | ... AM37: ='C3 · Recouvrement'!AM19
... B43: kpi.rec.litige_age | C43: AVG | D43: ='C3 · Recouvrement'!D25 | E43: ='C3 · Recouvrement'!E25 | F43: ='C3 · Recouvrement'!F25 | G43: ='C3 · Recouvrement'!G25 | H43: ='C3 · Recouvrement'!H25 | I43: ='C3 · Recouvrement'!I25 | J43: ='C3 · Recouvrement'!J25 | K43: ='C3 · Recouvrement'!K25 | ... AM43: ='C3 · Recouvrement'!AM25
B44: kpi.foot.total | C44: SUM | D44: ='C4 · Footfall'!D8 | E44: ='C4 · Footfall'!E8 | F44: ='C4 · Footfall'!F8 | G44: ='C4 · Footfall'!G8 | H44: ='C4 · Footfall'!H8 | I44: ='C4 · Footfall'!I8 | J44: ='C4 · Footfall'!J8 | K44: ='C4 · Footfall'!K8 | ... AM44: ='C4 · Footfall'!AM8
B45: kpi.foot.vs_budget | C45: RATIO | D45: ='C4 · Footfall'!D9 | E45: ='C4 · Footfall'!E9 | F45: ='C4 · Footfall'!F9 | G45: ='C4 · Footfall'!G9 | H45: ='C4 · Footfall'!H9 | I45: ='C4 · Footfall'!I9 | J45: ='C4 · Footfall'!J9 | K45: ='C4 · Footfall'!K9 | ... AM45: ='C4 · Footfall'!AM9
B46: kpi.foot.per_sqm | C46: RATIO | D46: ='C4 · Footfall'!D10 | E46: ='C4 · Footfall'!E10 | F46: ='C4 · Footfall'!F10 | G46: ='C4 · Footfall'!G10 | H46: ='C4 · Footfall'!H10 | I46: ='C4 · Footfall'!I10 | J46: ='C4 · Footfall'!J10 | K46: ='C4 · Footfall'!K10 | ... AM46: ='C4 · Footfall'!AM10
B47: kpi.foot.conversion | C47: RATIO | D47: ='C4 · Footfall'!D11 | E47: ='C4 · Footfall'!E11 | F47: ='C4 · Footfall'!F11 | G47: ='C4 · Footfall'!G11 | H47: ='C4 · Footfall'!H11 | I47: ='C4 · Footfall'!I11 | J47: ='C4 · Footfall'!J11 | K47: ='C4 · Footfall'!K11 | ... AM47: ='C4 · Footfall'!AM11
B48: kpi.foot.dwell | C48: AVG | D48: ='C4 · Footfall'!D12 | E48: ='C4 · Footfall'!E12 | F48: ='C4 · Footfall'!F12 | G48: ='C4 · Footfall'!G12 | H48: ='C4 · Footfall'!H12 | I48: ='C4 · Footfall'!I12 | J48: ='C4 · Footfall'!J12 | K48: ='C4 · Footfall'!K12 | ... AM48: ='C4 · Footfall'!AM12
B49: kpi.foot.peak_share | C49: AVG | D49: ='C4 · Footfall'!D13 | E49: ='C4 · Footfall'!E13 | F49: ='C4 · Footfall'!F13 | G49: ='C4 · Footfall'!G13 | H49: ='C4 · Footfall'!H13 | I49: ='C4 · Footfall'!I13 | J49: ='C4 · Footfall'!J13 | K49: ='C4 · Footfall'!K13 | ... AM49: ='C4 · Footfall'!AM13
B50: kpi.foot.weekend_share | C50: AVG | D50: ='C4 · Footfall'!D14 | E50: ='C4 · Footfall'!E14 | F50: ='C4 · Footfall'!F14 | G50: ='C4 · Footfall'!G14 | H50: ='C4 · Footfall'!H14 | I50: ='C4 · Footfall'!I14 | J50: ='C4 · Footfall'!J14 | K50: ='C4 · Footfall'!K14 | ... AM50: ='C4 · Footfall'!AM14
B51: kpi.mkt.events | C51: SUM | D51: ='C5 · Marketing'!D8 | E51: ='C5 · Marketing'!E8 | F51: ='C5 · Marketing'!F8 | G51: ='C5 · Marketing'!G8 | H51: ='C5 · Marketing'!H8 | I51: ='C5 · Marketing'!I8 | J51: ='C5 · Marketing'!J8 | K51: ='C5 · Marketing'!K8 | ... AM51: ='C5 · Marketing'!AM8
B52: kpi.mkt.event_att | C52: SUM | D52: ='C5 · Marketing'!D9 | E52: ='C5 · Marketing'!E9 | F52: ='C5 · Marketing'!F9 | G52: ='C5 · Marketing'!G9 | H52: ='C5 · Marketing'!H9 | I52: ='C5 · Marketing'!I9 | J52: ='C5 · Marketing'!J9 | K52: ='C5 · Marketing'!K9 | ... AM52: ='C5 · Marketing'!AM9
B53: kpi.mkt.event_roi | C53: RATIO | D53: ='C5 · Marketing'!D10 | E53: ='C5 · Marketing'!E10 | F53: ='C5 · Marketing'!F10 | G53: ='C5 · Marketing'!G10 | H53: ='C5 · Marketing'!H10 | I53: ='C5 · Marketing'!I10 | J53: ='C5 · Marketing'!J10 | K53: ='C5 · Marketing'!K10 | ... AM53: ='C5 · Marketing'!AM10
B54: kpi.mkt.event_sat | C54: AVG | D54: ='C5 · Marketing'!D11 | E54: ='C5 · Marketing'!E11 | F54: ='C5 · Marketing'!F11 | G54: ='C5 · Marketing'!G11 | H54: ='C5 · Marketing'!H11 | I54: ='C5 · Marketing'!I11 | J54: ='C5 · Marketing'!J11 | K54: ='C5 · Marketing'!K11 | ... AM54: ='C5 · Marketing'!AM11
B55: kpi.mkt.engagement | C55: AVG | D55: ='C5 · Marketing'!D12 | E55: ='C5 · Marketing'!E12 | F55: ='C5 · Marketing'!F12 | G55: ='C5 · Marketing'!G12 | H55: ='C5 · Marketing'!H12 | I55: ='C5 · Marketing'!I12 | J55: ='C5 · Marketing'!J12 | K55: ='C5 · Marketing'!K12 | ... AM55: ='C5 · Marketing'!AM12
B56: kpi.mkt.followers | C56: LAST | D56: ='C5 · Marketing'!D13 | E56: ='C5 · Marketing'!E13 | F56: ='C5 · Marketing'!F13 | G56: ='C5 · Marketing'!G13 | H56: ='C5 · Marketing'!H13 | I56: ='C5 · Marketing'!I13 | J56: ='C5 · Marketing'!J13 | K56: ='C5 · Marketing'!K13 | ... AM56: ='C5 · Marketing'!AM13
B57: kpi.mkt.reach | C57: SUM | D57: ='C5 · Marketing'!D14 | E57: ='C5 · Marketing'!E14 | F57: ='C5 · Marketing'!F14 | G57: ='C5 · Marketing'!G14 | H57: ='C5 · Marketing'!H14 | I57: ='C5 · Marketing'!I14 | J57: ='C5 · Marketing'!J14 | K57: ='C5 · Marketing'!K14 | ... AM57: ='C5 · Marketing'!AM14
B58: kpi.mkt.cpa | C58: RATIO | D58: ='C5 · Marketing'!D15 | E58: ='C5 · Marketing'!E15 | F58: ='C5 · Marketing'!F15 | G58: ='C5 · Marketing'!G15 | H58: ='C5 · Marketing'!H15 | I58: ='C5 · Marketing'!I15 | J58: ='C5 · Marketing'!J15 | K58: ='C5 · Marketing'!K15 | ... AM58: ='C5 · Marketing'!AM15
B59: kpi.mkt.digital_conv | C59: RATIO | D59: ='C5 · Marketing'!D16 | E59: ='C5 · Marketing'!E16 | F59: ='C5 · Marketing'!F16 | G59: ='C5 · Marketing'!G16 | H59: ='C5 · Marketing'!H16 | I59: ='C5 · Marketing'!I16 | J59: ='C5 · Marketing'!J16 | K59: ='C5 · Marketing'!K16 | ... AM59: ='C5 · Marketing'!AM16
B60: kpi.mkt.spend | C60: SUM | D60: ='C5 · Marketing'!D17 | E60: ='C5 · Marketing'!E17 | F60: ='C5 · Marketing'!F17 | G60: ='C5 · Marketing'!G17 | H60: ='C5 · Marketing'!H17 | I60: ='C5 · Marketing'!I17 | J60: ='C5 · Marketing'!J17 | K60: ='C5 · Marketing'!K17 | ... AM60: ='C5 · Marketing'!AM17
B61: kpi.mkt.spend_pct | C61: RATIO | D61: ='C5 · Marketing'!D18 | E61: ='C5 · Marketing'!E18 | F61: ='C5 · Marketing'!F18 | G61: ='C5 · Marketing'!G18 | H61: ='C5 · Marketing'!H18 | I61: ='C5 · Marketing'!I18 | J61: ='C5 · Marketing'!J18 | K61: ='C5 · Marketing'!K18 | ... AM61: ='C5 · Marketing'!AM18
B62: kpi.mkt.impressions | C62: SUM | D62: ='C5 · Marketing'!D19 | E62: ='C5 · Marketing'!E19 | F62: ='C5 · Marketing'!F19 | G62: ='C5 · Marketing'!G19 | H62: ='C5 · Marketing'!H19 | I62: ='C5 · Marketing'!I19 | J62: ='C5 · Marketing'!J19 | K62: ='C5 · Marketing'!K19 | ... AM62: ='C5 · Marketing'!AM19
... B67: kpi.mkt.basket_member | C67: AVG | D67: ='C5 · Marketing'!D24 | E67: ='C5 · Marketing'!E24 | F67: ='C5 · Marketing'!F24 | G67: ='C5 · Marketing'!G24 | H67: ='C5 · Marketing'!H24 | I67: ='C5 · Marketing'!I24 | J67: ='C5 · Marketing'!J24 | K67: ='C5 · Marketing'!K24 | ... AM67: ='C5 · Marketing'!AM24
B68: kpi.com.tenant_sales | C68: SUM | D68: ='C6 · Commercial'!D8 | E68: ='C6 · Commercial'!E8 | F68: ='C6 · Commercial'!F8 | G68: ='C6 · Commercial'!G8 | H68: ='C6 · Commercial'!H8 | I68: ='C6 · Commercial'!I8 | J68: ='C6 · Commercial'!J8 | K68: ='C6 · Commercial'!K8 | ... AM68: ='C6 · Commercial'!AM8
B69: kpi.com.total_sales | C69: SUM | D69: ='C6 · Commercial'!D9 | E69: ='C6 · Commercial'!E9 | F69: ='C6 · Commercial'!F9 | G69: ='C6 · Commercial'!G9 | H69: ='C6 · Commercial'!H9 | I69: ='C6 · Commercial'!I9 | J69: ='C6 · Commercial'!J9 | K69: ='C6 · Commercial'!K9 | ... AM69: ='C6 · Commercial'!AM9
B70: kpi.com.sales_sqm | C70: RATIO | D70: ='C6 · Commercial'!D10 | E70: ='C6 · Commercial'!E10 | F70: ='C6 · Commercial'!F10 | G70: ='C6 · Commercial'!G10 | H70: ='C6 · Commercial'!H10 | I70: ='C6 · Commercial'!I10 | J70: ='C6 · Commercial'!J10 | K70: ='C6 · Commercial'!K10 | ... AM70: ='C6 · Commercial'!AM10
B71: kpi.com.lfl | C71: RATIO | D71: ='C6 · Commercial'!D11 | E71: ='C6 · Commercial'!E11 | F71: ='C6 · Commercial'!F11 | G71: ='C6 · Commercial'!G11 | H71: ='C6 · Commercial'!H11 | I71: ='C6 · Commercial'!I11 | J71: ='C6 · Commercial'!J11 | K71: ='C6 · Commercial'!K11 | ... AM71: ='C6 · Commercial'!AM11
B72: kpi.com.new_leases | C72: SUM | D72: ='C6 · Commercial'!D12 | E72: ='C6 · Commercial'!E12 | F72: ='C6 · Commercial'!F12 | G72: ='C6 · Commercial'!G12 | H72: ='C6 · Commercial'!H12 | I72: ='C6 · Commercial'!I12 | J72: ='C6 · Commercial'!J12 | K72: ='C6 · Commercial'!K12 | ... AM72: ='C6 · Commercial'!AM12
B73: kpi.com.pipeline | C73: LAST | D73: ='C6 · Commercial'!D13 | E73: ='C6 · Commercial'!E13 | F73: ='C6 · Commercial'!F13 | G73: ='C6 · Commercial'!G13 | H73: ='C6 · Commercial'!H13 | I73: ='C6 · Commercial'!I13 | J73: ='C6 · Commercial'!J13 | K73: ='C6 · Commercial'!K13 | ... AM73: ='C6 · Commercial'!AM13
B74: kpi.com.leases_renewed | C74: SUM | D74: ='C6 · Commercial'!D14 | E74: ='C6 · Commercial'!E14 | F74: ='C6 · Commercial'!F14 | G74: ='C6 · Commercial'!G14 | H74: ='C6 · Commercial'!H14 | I74: ='C6 · Commercial'!I14 | J74: ='C6 · Commercial'!J14 | K74: ='C6 · Commercial'!K14 | ... AM74: ='C6 · Commercial'!AM14
B75: kpi.com.pipeline_conv | C75: RATIO | D75: ='C6 · Commercial'!D15 | E75: ='C6 · Commercial'!E15 | F75: ='C6 · Commercial'!F15 | G75: ='C6 · Commercial'!G15 | H75: ='C6 · Commercial'!H15 | I75: ='C6 · Commercial'!I15 | J75: ='C6 · Commercial'!J15 | K75: ='C6 · Commercial'!K15 | ... AM75: ='C6 · Commercial'!AM15
B76: kpi.com.popup_count | C76: LAST | D76: ='C6 · Commercial'!D16 | E76: ='C6 · Commercial'!E16 | F76: ='C6 · Commercial'!F16 | G76: ='C6 · Commercial'!G16 | H76: ='C6 · Commercial'!H16 | I76: ='C6 · Commercial'!I16 | J76: ='C6 · Commercial'!J16 | K76: ='C6 · Commercial'!K16 | ... AM76: ='C6 · Commercial'!AM16
B77: kpi.com.popup_rev | C77: SUM | D77: ='C6 · Commercial'!D17 | E77: ='C6 · Commercial'!E17 | F77: ='C6 · Commercial'!F17 | G77: ='C6 · Commercial'!G17 | H77: ='C6 · Commercial'!H17 | I77: ='C6 · Commercial'!I17 | J77: ='C6 · Commercial'!J17 | K77: ='C6 · Commercial'!K17 | ... AM77: ='C6 · Commercial'!AM17
B78: kpi.com.kiosk_occ | C78: AVG | D78: ='C6 · Commercial'!D18 | E78: ='C6 · Commercial'!E18 | F78: ='C6 · Commercial'!F18 | G78: ='C6 · Commercial'!G18 | H78: ='C6 · Commercial'!H18 | I78: ='C6 · Commercial'!I18 | J78: ='C6 · Commercial'!J18 | K78: ='C6 · Commercial'!K18 | ... AM78: ='C6 · Commercial'!AM18
B79: kpi.com.market_rev | C79: SUM | D79: ='C6 · Commercial'!D19 | E79: ='C6 · Commercial'!E19 | F79: ='C6 · Commercial'!F19 | G79: ='C6 · Commercial'!G19 | H79: ='C6 · Commercial'!H19 | I79: ='C6 · Commercial'!I19 | J79: ='C6 · Commercial'!J19 | K79: ='C6 · Commercial'!K19 | ... AM79: ='C6 · Commercial'!AM19
... B86: kpi.com.discount | C86: RATIO | D86: ='C6 · Commercial'!D26 | E86: ='C6 · Commercial'!E26 | F86: ='C6 · Commercial'!F26 | G86: ='C6 · Commercial'!G26 | H86: ='C6 · Commercial'!H26 | I86: ='C6 · Commercial'!I26 | J86: ='C6 · Commercial'!J26 | K86: ='C6 · Commercial'!K26 | ... AM86: ='C6 · Commercial'!AM26
B87: kpi.hsse.incidents | C87: SUM | D87: ='C7 · HSSE'!D8 | E87: ='C7 · HSSE'!E8 | F87: ='C7 · HSSE'!F8 | G87: ='C7 · HSSE'!G8 | H87: ='C7 · HSSE'!H8 | I87: ='C7 · HSSE'!I8 | J87: ='C7 · HSSE'!J8 | K87: ='C7 · HSSE'!K8 | ... AM87: ='C7 · HSSE'!AM8
B88: kpi.hsse.incident_sev | C88: AVG | D88: ='C7 · HSSE'!D9 | E88: ='C7 · HSSE'!E9 | F88: ='C7 · HSSE'!F9 | G88: ='C7 · HSSE'!G9 | H88: ='C7 · HSSE'!H9 | I88: ='C7 · HSSE'!I9 | J88: ='C7 · HSSE'!J9 | K88: ='C7 · HSSE'!K9 | ... AM88: ='C7 · HSSE'!AM9
B89: kpi.hsse.tf | C89: RATIO | D89: ='C7 · HSSE'!D10 | E89: ='C7 · HSSE'!E10 | F89: ='C7 · HSSE'!F10 | G89: ='C7 · HSSE'!G10 | H89: ='C7 · HSSE'!H10 | I89: ='C7 · HSSE'!I10 | J89: ='C7 · HSSE'!J10 | K89: ='C7 · HSSE'!K10 | ... AM89: ='C7 · HSSE'!AM10
B90: kpi.hsse.tg | C90: RATIO | D90: ='C7 · HSSE'!D11 | E90: ='C7 · HSSE'!E11 | F90: ='C7 · HSSE'!F11 | G90: ='C7 · HSSE'!G11 | H90: ='C7 · HSSE'!H11 | I90: ='C7 · HSSE'!I11 | J90: ='C7 · HSSE'!J11 | K90: ='C7 · HSSE'!K11 | ... AM90: ='C7 · HSSE'!AM11
B91: kpi.hsse.nearmiss | C91: SUM | D91: ='C7 · HSSE'!D12 | E91: ='C7 · HSSE'!E12 | F91: ='C7 · HSSE'!F12 | G91: ='C7 · HSSE'!G12 | H91: ='C7 · HSSE'!H12 | I91: ='C7 · HSSE'!I12 | J91: ='C7 · HSSE'!J12 | K91: ='C7 · HSSE'!K12 | ... AM91: ='C7 · HSSE'!AM12
B92: kpi.hsse.days_no_lti | C92: LAST | D92: ='C7 · HSSE'!D13 | E92: ='C7 · HSSE'!E13 | F92: ='C7 · HSSE'!F13 | G92: ='C7 · HSSE'!G13 | H92: ='C7 · HSSE'!H13 | I92: ='C7 · HSSE'!I13 | J92: ='C7 · HSSE'!J13 | K92: ='C7 · HSSE'!K13 | ... AM92: ='C7 · HSSE'!AM13
B93: kpi.hsse.evac_drills | C93: SUM | D93: ='C7 · HSSE'!D14 | E93: ='C7 · HSSE'!E14 | F93: ='C7 · HSSE'!F14 | G93: ='C7 · HSSE'!G14 | H93: ='C7 · HSSE'!H14 | I93: ='C7 · HSSE'!I14 | J93: ='C7 · HSSE'!J14 | K93: ='C7 · HSSE'!K14 | ... AM93: ='C7 · HSSE'!AM14
